Workbook

Sheet Date range
A1: Last X Months | B1: 6 | C1: 45808

Sheet Past transactions
A1: Transaction Id | B1: Date | C1: Amount | D1: Name | E1: Category | F1: Memo | G1: Column 3
B2: 45833 | C2: 27.5 | E2: Software | F2: GC<>HUBOO TECH HU-MDQR59Q XXXXXXXX23512 Intl Electronic Debit | G2: =C2*-1 -> -27.5
B3: 45833 | C3: -179.62 | E3: Shopify | F3: SHOPIFY TRANSFER SHOPIFY Electronic Deposit | G3: =C3*-1 -> 179.62
B4: 45833 | C4: -55.34 | E4: Shopify | F4: Shopify TRANSFER ST-O8T3U5A0U9X0 Electronic Deposit | G4: =C4*-1 -> 55.34
B5: 45833 | C5: -592.64 | E5: Shopify | F5: Shopify TRANSFER ST-X1D3L3K8Q0O3 Electronic Deposit | G5: =C5*-1 -> 592.64
B6: 45833 | C6: -110.68 | E6: Shopify | F6: SHOPPAYINST AFRM PAYMENTS 4ZNMOY7IEOH6GG3 Electronic Deposit | G6: =C6*-1 -> 110.68
B7: 45832 | C7: 0.01 | E7: Tax Expenditures | F7: VA DEPT TAXATION TAX PAYMEN *****4666 Electronic Debit | G7: =C7*-1 -> -0.01
B8: 45832 | C8: -340 | E8: Shopify | F8: SHOPIFY TRANSFER SHOPIFY Electronic Deposit | G8: =C8*-1 -> 340
B9: 45832 | C9: -3521.59 | E9: Shopify | F9: SHOPIFY TRANSFER ST-C2N3H8H4R3M2 Electronic Deposit | G9: =C9*-1 -> 3521.59
B10: 45831 | C10: 250.51 | E10: Software | F10: INTUIT * QBooks Onl 8667280 Electronic Debit | G10: =C10*-1 -> -250.51
B11: 45831 | C11: -55.05 | E11: Shopify | F11: SHOPIFY TRANSFER SHOPIFY Electronic Deposit | G11: =C11*-1 -> 55.05
B12: 45831 | C12: -2271.5 | E12: Shopify | F12: Shopify TRANSFER ST-D9V1Y5G8R1X2 Electronic Deposit | G12: =C12*-1 -> 2271.5
B13: 45831 | C13: -217.53 | E13: Shopify | F13: SHOPIFY TRANSFER SHOPIFY Electronic Deposit | G13: =C13*-1 -> 217.53
... B20: 45828 | C20: 369.3 | E20: Tax Expenditures | F20: GEORGIA ITS TAX GA TX PYMT XXXXXX5216 Electronic Debit | G20: =C20*-1 -> -369.3
B21: 45828 | C21: 905.09 | D21: The Hartford | E21: Overhead Expenditures | F21: THE HARTFORD INSPMTCL 17122542 Electronic Debit | G21: =C21*-1 -> -905.09
B22: 45828 | C22: 1086.26 | E22: Tax Expenditures | F22: WEBFILE TAX PYMT DD 902/79387750 Electronic Debit | G22: =C22*-1 -> -1086.26
B23: 45828 | C23: -623.59 | D23: Shopify | E23: Shopify | F23: Shopify TRANSFER ST-W1M2I0T4O1U1 Electronic Deposit | G23: =C23*-1 -> 623.59
B24: 45828 | C24: -120.91 | D24: Shopify | E24: Shopify | F24: SHOPPAYINST AFRM PAYMENTS UYK2YKTRBEN7TU5 Electronic Deposit | G24: =C24*-1 -> 120.91
B25: 45828 | C25: -134.41 | D25: Shopify | E25: Shopify | F25: SHOPIFY TRANSFER SHOPIFY Electronic Deposit | G25: =C25*-1 -> 134.41
B26: 45826 | C26: 27.89 | D26: Huboo | E26: Software | F26: GC<>HUBOO TECH HU-MDQR59Q XXXXXXXX23512 Intl Electronic Debit | G26: =C26*-1 -> -27.89
B27: 45826 | C27: 123.86 | D27: Shopify | E27: Shopify | F27: SHOPIFY XXXXXXXXXX VOCHILL Electronic Debit | G27: =C27*-1 -> -123.86
B28: 45826 | C28: 270.59 | D28: Virginia Department of Taxation | E28: Tax Expenditures | F28: VA DEPT TAXATION TAX PAYMEN *****4666 Electronic Debit | G28: =C28*-1 -> -270.59
B29: 45826 | C29: -205.81 | D29: Shopify | E29: Shopify | F29: SHOPIFY TRANSFER SHOPIFY Electronic Deposit | G29: =C29*-1 -> 205.81
B30: 45826 | C30: -55.59 | D30: Shopify | E30: Shopify | F30: SHOPIFY TRANSFER ST-O7P1K1P2B1R8 Electronic Deposit | G30: =C30*-1 -> 55.59
B31: 45826 | C31: -408.66 | D31: Shopify | E31: Shopify | F31: SHOPIFY TRANSFER ST-Y7U7O5V2D6V7 Electronic Deposit | G31: =C31*-1 -> 408.66
B32: 45825 | C32: 40 | E32: Overhead Expenditures | F32: Treasury Mgmt Svcs | G32: =C32*-1 -> -40
B33: 45825 | C33: 94.72 | E33: Overhead Expenditures | F33: BILL.COM LLC BILLING 02B4JTVUDQMT00M Electronic Debit | G33: =C33*-1 -> -94.72
B34: 45825 | C34: -5196.75 | D34: Shopify | E34: Shopify | F34: Shopify TRANSFER ST-U2S0R0C9M1C1 Electronic Deposit | G34: =C34*-1 -> 5196.75
B35: 45825 | C35: -76.61 | D35: Shopify | E35: Shopify | F35: SHOPPAYINST AFRM PAYMENTS E7I6ZPF4BMK4LT2 Electronic Deposit | G35: =C35*-1 -> 76.61
B36: 45825 | C36: -255.93 | D36: Shopify | E36: Shopify | F36: SHOPIFY TRANSFER SHOPIFY Electronic Deposit | G36: =C36*-1 -> 255.93
B37: 45825 | C37: -44.26 | D37: Shopify | E37: Shopify | F37: SHOPPAYINST AFRM PAYMENTS 6KQEL2L4S9SW6WR Electronic Deposit | G37: =C37*-1 -> 44.26
B38: 45825 | C38: -170.51 | D38: Shopify | E38: Shopify | F38: SHOPPAYINST AFRM PAYMENTS 6X8YZ3TSTVZHIZG Electronic Deposit | G38: =C38*-1 -> 170.51
B39: 45824 | C39: 1.45 | E39: Overhead Expenditures | F39: GLOBAL - E PPD Electronic Debit | G39: =C39*-1 -> -1.45
B40: 45824 | C40: 36.02 | D40: Huboo | E40: Software | F40: GC<>HUBOO TECH HU-MDQR59Q XXXXXXXX23512 Intl Electronic Debit | G40: =C40*-1 -> -36.02
B41: 45824 | C41: -120.41 | D41: Shopify | E41: Shopify | F41: SHOPIFY TRANSFER SHOPIFY Electronic Deposit | G41: =C41*-1 -> 120.41
B42: 45824 | C42: -1120.64 | D42: Shopify | E42: Shopify | F42: Shopify TRANSFER ST-Y1A5D8Q1I8Z5 Electronic Deposit | G42: =C42*-1 -> 1120.64
B43: 45824 | C43: -235.36 | D43: Shopify | E43: Shopify | F43: SHOPIFY TRANSFER SHOPIFY Electronic Deposit | G43: =C43*-1 -> 235.36
B44: 45824 | C44: -79.9 | D44: Shopify | E44: Shopify | F44: SHOPIFY TRANSFER SHOPIFY Electronic Deposit | G44: =C44*-1 -> 79.9
B45: 45823 | C45: 11371.29 | E45: Credit Card | F45: Payment Thank You - Web | G45: =C45*-1 -> -11371.29
B46: 45821 | C46: -73.66 | D46: Shopify | E46: Shopify | F46: SHOPPAYINST AFRM PAYMENTS B0RL6T2D275UM8F Electronic Deposit | G46: =C46*-1 -> 73.66
B47: 45821 | C47: -1221.43 | D47: Shopify | E47: Shopify | F47: Shopify TRANSFER ST-H1P7U5K2Z1I5 Electronic Deposit | G47: =C47*-1 -> 1221.43
B48: 45821 | C48: -117.05 | D48: Shopify | E48: Shopify | F48: SHOPIFY TRANSFER SHOPIFY Electronic Deposit | G48: =C48*-1 -> 117.05
B49: 45821 | C49: -138.24 | D49: Faire | E49: Wholesale | F49: FAIRE WHOLESALE ORDER pay_x7w9efz33x Electronic Deposit | G49: =C49*-1 -> 138.24
B50: 45820 | C50: 7440.6 | E50: Sales&Marketing Expenditures | F50: Bill.com Payables 015CFEMCHCJ0RWJ Electronic Debit | G50: =C50*-1 -> -7440.6
B51: 45820 | C51: -101.11 | D51: Faire | E51: Wholesale | F51: FAIRE WHOLESALE ORDER pay_e9n6tqcrqk Electronic Deposit | G51: =C51*-1 -> 101.11
B52: 45820 | C52: -424.04 | D52: Shopify | E52: Shopify | F52: SHOPIFY TRANSFER SHOPIFY Electronic Deposit | G52: =C52*-1 -> 424.04
B53: 45820 | C53: -50.9 | D53: Shopify | E53: Shopify | F53: SHOPPAYINST AFRM PAYMENTS ECSABF5UK9E7D5K Electronic Deposit | G53: =C53*-1 -> 50.9
B54: 45820 | C54: -1649.92 | D54: Shopify | E54: Shopify | F54: Shopify TRANSFER ST-A7H7S7Z9W9H0 Electronic Deposit | G54: =C54*-1 -> 1649.92
B55: 45820 | C55: -267.92 | D55: Faire | E55: Wholesale | F55: FAIRE WHOLESALE ORDER pay_u765rewkf5 Electronic Deposit | G55: =C55*-1 -> 267.92
B56: 45819 | C56: 6839.01 | F56: Bill.com Payables 015KJWAZFJIZ6F0 Electronic Debit | G56: =C56*-1 -> -6839.01
B57: 45819 | C57: -203.13 | D57: Shopify - vo-vin Customer | E57: Shopify | F57: SHOPIFY TRANSFER SHOPIFY Electronic Deposit | G57: =C57*-1 -> 203.13
B58: 45819 | C58: -44.5 | D58: Affirm | E58: Shopify | F58: SHOPPAYINST AFRM PAYMENTS KS2FHVBX1C95900 Electronic Deposit | G58: =C58*-1 -> 44.5
B59: 45819 | C59: -56.08 | D59: Shopify | E59: Shopify | F59: Shopify TRANSFER ST-B5T7Q7G8U6T4 Electronic Deposit | G59: =C59*-1 -> 56.08
B60: 45819 | C60: -101.11 | D60: Faire | E60: Wholesale | F60: FAIRE WHOLESALE ORDER pay_uezhufja5w Electronic Deposit | G60: =C60*-1 -> 101.11
B61: 45819 | C61: -1761.09 | D61: Shopify | E61: Shopify | F61: Shopify TRANSFER ST-I2S6T7P0F0Z2 Electronic Deposit | G61: =C61*-1 -> 1761.09
B62: 45818 | C62: 21.18 | D62: Huboo | E62: Software | F62: GC<>HUBOO TECH HU-MDQR59Q XXXXXXXX23512 Intl Electronic Debit | G62: =C62*-1 -> -21.18
B63: 45818 | C63: -517 | D63: Shopify - vo-vin Customer | E63: Shopify | F63: SHOPIFY TRANSFER SHOPIFY Electronic Deposit | G63: =C63*-1 -> 517
B64: 45818 | C64: -144.64 | D64: AFRM PAYMENTS | E64: Shopify | F64: SHOPPAYINST AFRM PAYMENTS 5THWUOZZTTGAWXF Electronic Deposit | G64: =C64*-1 -> 144.64
B65: 45818 | C65: -98.64 | D65: AFRM PAYMENTS | E65: Shopify | F65: SHOPPAYINST AFRM PAYMENTS 65EKOATW01VTISR Electronic Deposit | G65: =C65*-1 -> 98.64
B66: 45818 | C66: -4929.75 | D66: Shopify | E66: Shopify | F66: Shopify TRANSFER ST-F6U3M9D5E6R6 Electronic Deposit | G66: =C66*-1 -> 4929.75
B67: 45818 | C67: -90.13 | D67: AFRM PAYMENTS | E67: Shopify | F67: SHOPPAYINST AFRM PAYMENTS RTTEXH7JADUMSVR Electronic Deposit | G67: =C67*-1 -> 90.13
B68: 45817 | C68: -308.65 | E68: Overhead Expenditures | F68: GLOBAL - E PAYMENT Electronic Deposit | G68: =C68*-1 -> 308.65
B69: 45817 | C69: -1252.69 | D69: Shopify | E69: Shopify | F69: Shopify TRANSFER ST-K4Q2E5M9F5W9 Electronic Deposit | G69: =C69*-1 -> 1252.69
B70: 45817 | C70: -45.02 | D70: Shopify - vo-vin Customer | E70: Shopify | F70: SHOPIFY TRANSFER SHOPIFY Electronic Deposit | G70: =C70*-1 -> 45.02
B71: 45816 | C71: 1145.01 | E71: Payroll | F71: Debit tax | G71: =C71*-1 -> -1145.01
B72: 45816 | C72: 3286.06 | E72: Payroll | F72: Debit tax | G72: =C72*-1 -> -3286.06
B73: 45816 | C73: 4297.63 | E73: Payroll | F73: Debit net pay | G73: =C73*-1 -> -4297.63
B74: 45816 | C74: 11756.8 | E74: Payroll | F74: Debit net pay | G74: =C74*-1 -> -11756.8
B75: 45814 | C75: -318.18 | D75: Shopify - vo-vin Customer | E75: Shopify | F75: SHOPIFY TRANSFER SHOPIFY Electronic Deposit | G75: =C75*-1 -> 318.18
B76: 45814 | C76: -106.92 | D76: Shopify | E76: Shopify | F76: Shopify TRANSFER ST-G5X2W2M6U5R5 Electronic Deposit | G76: =C76*-1 -> 106.92
B77: 45814 | C77: -1666.55 | D77: Shopify | E77: Shopify | F77: Shopify TRANSFER ST-P2Z7J2T5T3N6 Electronic Deposit | G77: =C77*-1 -> 1666.55
B78: 45813 | C78: 25000 | E78: Credit Card | F78: Payment Thank You - Web | G78: =C78*-1 -> -25000
B79: 45813 | C79: -180.93 | D79: Shopify - vo-vin Customer | E79: Shopify | F79: SHOPIFY TRANSFER SHOPIFY Electronic Deposit | G79: =C79*-1 -> 180.93
B80: 45813 | C80: -573.09 | D80: Shopify | E80: Shopify | F80: Shopify TRANSFER ST-A1G3A1U2M9E1 Electronic Deposit | G80: =C80*-1 -> 573.09
B81: 45812 | C81: 225 | D81: Ampersand | E81: Software | F81: AMPERSAND PRODUC SALE Electronic Debit | G81: =C81*-1 -> -225
B82: 45812 | C82: 358.13 | D82: Beam | E82: Overhead Expenditures | F82: Beam-Premium Beam2025 TX00829 Electronic Debit | G82: =C82*-1 -> -358.13
B83: 45812 | C83: -1095.62 | D83: Shopify | E83: Shopify | F83: Shopify TRANSFER ST-R5Q1V4D3I1P4 Electronic Deposit | G83: =C83*-1 -> 1095.62
B84: 45812 | C84: -199.03 | D84: Shopify | E84: Shopify | F84: SHOPIFY TRANSFER SHOPIFY Electronic Deposit | G84: =C84*-1 -> 199.03
B85: 45811 | C85: 329.23 | D85: City of Austin | E85: Overhead Expenditures | F85: City of Austin T PAYMENT XXXXXX7912 Electronic Debit | G85: =C85*-1 -> -329.23
B86: 45811 | C86: 688.24 | E86: Overhead Expenditures | F86: Bill.com Payables 015QXYYUVYIHTPE Electronic Debit | G86: =C86*-1 -> -688.24
B87: 45811 | C87: -68.47 | D87: Shopify - vo-vin Customer | E87: Shopify | F87: SHOPIFY TRANSFER SHOPIFY Electronic Deposit | G87: =C87*-1 -> 68.47
B88: 45811 | C88: -50.9 | D88: Shopify | E88: Shopify | F88: SHOPPAYINST AFRM PAYMENTS 5SLFTIF3S8456FS Electronic Deposit | G88: =C88*-1 -> 50.9
B89: 45811 | C89: -51.95 | D89: Shopify | E89: Shopify | F89: SHOPPAYINST AFRM PAYMENTS 835IIOKY4BZSZBN Electronic Deposit | G89: =C89*-1 -> 51.95
B90: 45811 | C90: -2352.62 | D90: Shopify | E90: Shopify | F90: Shopify TRANSFER ST-S2N8K0Z3J0R8 Electronic Deposit | G90: =C90*-1 -> 2352.62
B91: 45811 | C91: -64.93 | D91: Shopify | E91: Shopify | F91: SHOPPAYINST AFRM PAYMENTS BVDQ2ERGABRXTU7 Electronic Deposit | G91: =C91*-1 -> 64.93
B92: 45810 | C92: 900 | D92: Ampersand | E92: Software | F92: AMPERSAND PRODUC SALE Electronic Debit | G92: =C92*-1 -> -900
B93: 45810 | C93: 2720.73 | D93: Sana Benefits | E93: Payroll | F93: Sana Benefits PAYMENT fca56474232e466 Electronic Debit | G93: =C93*-1 -> -2720.73
B94: 45810 | C94: -151.47 | D94: Shopify - vo-vin Customer | E94: Shopify | F94: SHOPIFY TRANSFER SHOPIFY Electronic Deposit | G94: =C94*-1 -> 151.47
B95: 45810 | C95: -118.77 | D95: Shopify - vo-vin Customer | E95: Shopify | F95: SHOPIFY TRANSFER SHOPIFY Electronic Deposit | G95: =C95*-1 -> 118.77
B96: 45810 | C96: -53.85 | D96: Shopify - vo-vin Customer | E96: Shopify | F96: SHOPIFY TRANSFER SHOPIFY Electronic Deposit | G96: =C96*-1 -> 53.85
B97: 45810 | C97: -817.56 | D97: Shopify | E97: Shopify | F97: Shopify TRANSFER ST-B9J3H1O6Z1V5 Electronic Deposit | G97: =C97*-1 -> 817.56
B98: 45832 | C98: -7390 | D98: amaz | E98: Amazon

Sheet Recurring Transactions
A1: First payment date | B1: Counterparty | C1: Description | D1: Amount | E1: Category | F1: Frequency | G1: =IFERROR(ROWSDUMMYFUNCTION(AUTOFILL("Repayment 1",IFS($F2="bi-weekly",$A2+CEILING(('13-week CF Forecast'!$B$1-$A2)/14,1)*14+14*(COLUMN()-7),$F2="weekly",$A2+CEILING(('13-week CF Forecast'!$B$1-$A2)/7,1)*7+7*(COLUMN()-7),$F2="monthly",DATE(YEAR($A2),MONTH($A2)+CEILING(DATEDIF($A2,'13-week CF Forecast'!$B$1,"m")+1,1)+COLUMN()-7,DAY($A2)),$F2="quarterly",DATE(YEAR($A2),MONTH($A2)+3*CEILING((DATEDIF($A2,'13-week CF Forecast'!$B$1,"m")+1)/3,1)+(COLUMN()-7)*3,DAY($A2)),$F2="yearly",DATE(YEAR($A2)+CEILING((DATEDIF($A2,'13-week CF Forecast'!$B$1,"y")+1),1)+COLUMN()-7,MONTH($A2),DAY($A2)),TRUE,""))),"Repayment 1") -> Repayment 1 | H1: =IFERROR(ROWSDUMMYFUNCTION(AUTOFILL(CONCATENATE("Repayment ",SLICE(G1," ",2)+1),IFS($F2="bi-weekly",$A2+CEILING(('13-week CF Forecast'!$B$1-$A2)/14,1)*14+14*(COLUMN()-7),$F2="weekly",$A2+CEILING(('13-week CF Forecast'!$B$1-$A2)/7,1)*7+7*(COLUMN()-7),$F2="monthly",DATE(YEAR($A2),MONTH($A2)+CEILING(DATEDIF($A2,'13-week CF Forecast'!$B$1,"m")+1,1)+COLUMN()-7,DAY($A2)),$F2="quarterly",DATE(YEAR($A2),MONTH($A2)+3*CEILING((DATEDIF($A2,'13-week CF Forecast'!$B$1,"m")+1)/3,1)+(COLUMN()-7)*3,DAY($A2)),$F2="yearly",DATE(YEAR($A2)+CEILING((DATEDIF($A2,'13-week CF Forecast'!$B$1,"y")+1),1)+COLUMN()-7,MONTH($A2),DAY($A2)),TRUE,""),1)),"Repayment 2") -> Repayment 2 | I1: =IFERROR(ROWSDUMMYFUNCTION(AUTOFILL(CONCATENATE("Repayment ",SLICE(H1," ",2)+1),IFS($F2="bi-weekly",$A2+CEILING(('13-week CF Forecast'!$B$1-$A2)/14,1)*14+14*(COLUMN()-7),$F2="weekly",$A2+CEILING(('13-week CF Forecast'!$B$1-$A2)/7,1)*7+7*(COLUMN()-7),$F2="monthly",DATE(YEAR($A2),MONTH($A2)+CEILING(DATEDIF($A2,'13-week CF Forecast'!$B$1,"m")+1,1)+COLUMN()-7,DAY($A2)),$F2="quarterly",DATE(YEAR($A2),MONTH($A2)+3*CEILING((DATEDIF($A2,'13-week CF Forecast'!$B$1,"m")+1)/3,1)+(COLUMN()-7)*3,DAY($A2)),$F2="yearly",DATE(YEAR($A2)+CEILING((DATEDIF($A2,'13-week CF Forecast'!$B$1,"y")+1),1)+COLUMN()-7,MONTH($A2),DAY($A2)),TRUE,""),1)),"Repayment 3") -> Repayment 3 | J1: =IFERROR(ROWSDUMMYFUNCTION(AUTOFILL(CONCATENATE("Repayment ",SLICE(I1," ",2)+1),IFS($F2="bi-weekly",$A2+CEILING(('13-week CF Forecast'!$B$1-$A2)/14,1)*14+14*(COLUMN()-7),$F2="weekly",$A2+CEILING(('13-week CF Forecast'!$B$1-$A2)/7,1)*7+7*(COLUMN()-7),$F2="monthly",DATE(YEAR($A2),MONTH($A2)+CEILING(DATEDIF($A2,'13-week CF Forecast'!$B$1,"m")+1,1)+COLUMN()-7,DAY($A2)),$F2="quarterly",DATE(YEAR($A2),MONTH($A2)+3*CEILING((DATEDIF($A2,'13-week CF Forecast'!$B$1,"m")+1)/3,1)+(COLUMN()-7)*3,DAY($A2)),$F2="yearly",DATE(YEAR($A2)+CEILING((DATEDIF($A2,'13-week CF Forecast'!$B$1,"y")+1),1)+COLUMN()-7,MONTH($A2),DAY($A2)),TRUE,""),1)),"Repayment 4") -> Repayment 4 | K1: =IFERROR(ROWSDUMMYFUNCTION(AUTOFILL(CONCATENATE("Repayment ",SLICE(J1," ",2)+1),IFS($F2="bi-weekly",$A2+CEILING(('13-week CF Forecast'!$B$1-$A2)/14,1)*14+14*(COLUMN()-7),$F2="weekly",$A2+CEILING(('13-week CF Forecast'!$B$1-$A2)/7,1)*7+7*(COLUMN()-7),$F2="monthly",DATE(YEAR($A2),MONTH($A2)+CEILING(DATEDIF($A2,'13-week CF Forecast'!$B$1,"m")+1,1)+COLUMN()-7,DAY($A2)),$F2="quarterly",DATE(YEAR($A2),MONTH($A2)+3*CEILING((DATEDIF($A2,'13-week CF Forecast'!$B$1,"m")+1)/3,1)+(COLUMN()-7)*3,DAY($A2)),$F2="yearly",DATE(YEAR($A2)+CEILING((DATEDIF($A2,'13-week CF Forecast'!$B$1,"y")+1),1)+COLUMN()-7,MONTH($A2),DAY($A2)),TRUE,""),1)),"Repayment 5") -> Repayment 5 | L1: =IFERROR(ROWSDUMMYFUNCTION(AUTOFILL(CONCATENATE("Repayment ",SLICE(K1," ",2)+1),IFS($F2="bi-weekly",$A2+CEILING(('13-week CF Forecast'!$B$1-$A2)/14,1)*14+14*(COLUMN()-7),$F2="weekly",$A2+CEILING(('13-week CF Forecast'!$B$1-$A2)/7,1)*7+7*(COLUMN()-7),$F2="monthly",DATE(YEAR($A2),MONTH($A2)+CEILING(DATEDIF($A2,'13-week CF Forecast'!$B$1,"m")+1,1)+COLUMN()-7,DAY($A2)),$F2="quarterly",DATE(YEAR($A2),MONTH($A2)+3*CEILING((DATEDIF($A2,'13-week CF Forecast'!$B$1,"m")+1)/3,1)+(COLUMN()-7)*3,DAY($A2)),$F2="yearly",DATE(YEAR($A2)+CEILING((DATEDIF($A2,'13-week CF Forecast'!$B$1,"y")+1),1)+COLUMN()-7,MONTH($A2),DAY($A2)),TRUE,""),1)),"Repayment 6") -> Repayment 6 | M1: =IFERROR(ROWSDUMMYFUNCTION(AUTOFILL(CONCATENATE("Repayment ",SLICE(L1," ",2)+1),IFS($F2="bi-weekly",$A2+CEILING(('13-week CF Forecast'!$B$1-$A2)/14,1)*14+14*(COLUMN()-7),$F2="weekly",$A2+CEILING(('13-week CF Forecast'!$B$1-$A2)/7,1)*7+7*(COLUMN()-7),$F2="monthly",DATE(YEAR($A2),MONTH($A2)+CEILING(DATEDIF($A2,'13-week CF Forecast'!$B$1,"m")+1,1)+COLUMN()-7,DAY($A2)),$F2="quarterly",DATE(YEAR($A2),MONTH($A2)+3*CEILING((DATEDIF($A2,'13-week CF Forecast'!$B$1,"m")+1)/3,1)+(COLUMN()-7)*3,DAY($A2)),$F2="yearly",DATE(YEAR($A2)+CEILING((DATEDIF($A2,'13-week CF Forecast'!$B$1,"y")+1),1)+COLUMN()-7,MONTH($A2),DAY($A2)),TRUE,""),1)),"Repayment 7") -> Repayment 7 | N1: =IFERROR(ROWSDUMMYFUNCTION(AUTOFILL(CONCATENATE("Repayment ",SLICE(M1," ",2)+1),IFS($F2="bi-weekly",$A2+CEILING(('13-week CF Forecast'!$B$1-$A2)/14,1)*14+14*(COLUMN()-7),$F2="weekly",$A2+CEILING(('13-week CF Forecast'!$B$1-$A2)/7,1)*7+7*(COLUMN()-7),$F2="monthly",DATE(YEAR($A2),MONTH($A2)+CEILING(DATEDIF($A2,'13-week CF Forecast'!$B$1,"m")+1,1)+COLUMN()-7,DAY($A2)),$F2="quarterly",DATE(YEAR($A2),MONTH($A2)+3*CEILING((DATEDIF($A2,'13-week CF Forecast'!$B$1,"m")+1)/3,1)+(COLUMN()-7)*3,DAY($A2)),$F2="yearly",DATE(YEAR($A2)+CEILING((DATEDIF($A2,'13-week CF Forecast'!$B$1,"y")+1),1)+COLUMN()-7,MONTH($A2),DAY($A2)),TRUE,""),1)),"Repayment 8") -> Repayment 8 | O1: =IFERROR(ROWSDUMMYFUNCTION(AUTOFILL(CONCATENATE("Repayment ",SLICE(N1," ",2)+1),IFS($F2="bi-weekly",$A2+CEILING(('13-week CF Forecast'!$B$1-$A2)/14,1)*14+14*(COLUMN()-7),$F2="weekly",$A2+CEILING(('13-week CF Forecast'!$B$1-$A2)/7,1)*7+7*(COLUMN()-7),$F2="monthly",DATE(YEAR($A2),MONTH($A2)+CEILING(DATEDIF($A2,'13-week CF Forecast'!$B$1,"m")+1,1)+COLUMN()-7,DAY($A2)),$F2="quarterly",DATE(YEAR($A2),MONTH($A2)+3*CEILING((DATEDIF($A2,'13-week CF Forecast'!$B$1,"m")+1)/3,1)+(COLUMN()-7)*3,DAY($A2)),$F2="yearly",DATE(YEAR($A2)+CEILING((DATEDIF($A2,'13-week CF Forecast'!$B$1,"y")+1),1)+COLUMN()-7,MONTH($A2),DAY($A2)),TRUE,""),1)),"Repayment 9") -> Repayment 9 | P1: =IFERROR(ROWSDUMMYFUNCTION(AUTOFILL(CONCATENATE("Repayment ",SLICE(O1," ",2)+1),IFS($F2="bi-weekly",$A2+CEILING(('13-week CF Forecast'!$B$1-$A2)/14,1)*14+14*(COLUMN()-7),$F2="weekly",$A2+CEILING(('13-week CF Forecast'!$B$1-$A2)/7,1)*7+7*(COLUMN()-7),$F2="monthly",DATE(YEAR($A2),MONTH($A2)+CEILING(DATEDIF($A2,'13-week CF Forecast'!$B$1,"m")+1,1)+COLUMN()-7,DAY($A2)),$F2="quarterly",DATE(YEAR($A2),MONTH($A2)+3*CEILING((DATEDIF($A2,'13-week CF Forecast'!$B$1,"m")+1)/3,1)+(COLUMN()-7)*3,DAY($A2)),$F2="yearly",DATE(YEAR($A2)+CEILING((DATEDIF($A2,'13-week CF Forecast'!$B$1,"y")+1),1)+COLUMN()-7,MONTH($A2),DAY($A2)),TRUE,""),1)),"Repayment 10") -> Repayment 10 | Q1: =IFERROR(ROWSDUMMYFUNCTION(AUTOFILL(CONCATENATE("Repayment ",SLICE(P1," ",2)+1),IFS($F2="bi-weekly",$A2+CEILING(('13-week CF Forecast'!$B$1-$A2)/14,1)*14+14*(COLUMN()-7),$F2="weekly",$A2+CEILING(('13-week CF Forecast'!$B$1-$A2)/7,1)*7+7*(COLUMN()-7),$F2="monthly",DATE(YEAR($A2),MONTH($A2)+CEILING(DATEDIF($A2,'13-week CF Forecast'!$B$1,"m")+1,1)+COLUMN()-7,DAY($A2)),$F2="quarterly",DATE(YEAR($A2),MONTH($A2)+3*CEILING((DATEDIF($A2,'13-week CF Forecast'!$B$1,"m")+1)/3,1)+(COLUMN()-7)*3,DAY($A2)),$F2="yearly",DATE(YEAR($A2)+CEILING((DATEDIF($A2,'13-week CF Forecast'!$B$1,"y")+1),1)+COLUMN()-7,MONTH($A2),DAY($A2)),TRUE,""),1)),"Repayment 11") -> Repayment 11 | R1: =IFERROR(ROWSDUMMYFUNCTION(AUTOFILL(CONCATENATE("Repayment ",SLICE(Q1," ",2)+1),IFS($F2="bi-weekly",$A2+CEILING(('13-week CF Forecast'!$B$1-$A2)/14,1)*14+14*(COLUMN()-7),$F2="weekly",$A2+CEILING(('13-week CF Forecast'!$B$1-$A2)/7,1)*7+7*(COLUMN()-7),$F2="monthly",DATE(YEAR($A2),MONTH($A2)+CEILING(DATEDIF($A2,'13-week CF Forecast'!$B$1,"m")+1,1)+COLUMN()-7,DAY($A2)),$F2="quarterly",DATE(YEAR($A2),MONTH($A2)+3*CEILING((DATEDIF($A2,'13-week CF Forecast'!$B$1,"m")+1)/3,1)+(COLUMN()-7)*3,DAY($A2)),$F2="yearly",DATE(YEAR($A2)+CEILING((DATEDIF($A2,'13-week CF Forecast'!$B$1,"y")+1),1)+COLUMN()-7,MONTH($A2),DAY($A2)),TRUE,""),1)),"Repayment 12") -> Repayment 12 | S1: =IFERROR(ROWSDUMMYFUNCTION(AUTOFILL(CONCATENATE("Repayment ",SLICE(R1," ",2)+1),IFS($F2="bi-weekly",$A2+CEILING(('13-week CF Forecast'!$B$1-$A2)/14,1)*14+14*(COLUMN()-7),$F2="weekly",$A2+CEILING(('13-week CF Forecast'!$B$1-$A2)/7,1)*7+7*(COLUMN()-7),$F2="monthly",DATE(YEAR($A2),MONTH($A2)+CEILING(DATEDIF($A2,'13-week CF Forecast'!$B$1,"m")+1,1)+COLUMN()-7,DAY($A2)),$F2="quarterly",DATE(YEAR($A2),MONTH($A2)+3*CEILING((DATEDIF($A2,'13-week CF Forecast'!$B$1,"m")+1)/3,1)+(COLUMN()-7)*3,DAY($A2)),$F2="yearly",DATE(YEAR($A2)+CEILING((DATEDIF($A2,'13-week CF Forecast'!$B$1,"y")+1),1)+COLUMN()-7,MONTH($A2),DAY($A2)),TRUE,""),1)),"Repayment 13") -> Repayment 13 | T1: =IFERROR(ROWSDUMMYFUNCTION(AUTOFILL("Repayment Schedule",UNNEST(PAIR2JSON('Recurring Transactions'!$A$1,'Recurring Transactions'!A2,'Recurring Transactions'!$B$1,'Recurring Transactions'!B2,'Recurring Transactions'!$C$1,'Recurring Transactions'!C2,'Recurring Transactions'!$D$1,'Recurring Transactions'!D2,'Recurring Transactions'!$E$1,'Recurring Transactions'!E2,'Recurring Transactions'!$F$1,'Recurring Transactions'!F2,"Payment schedule",VALUE(RANGE2JSON('Recurring Transactions'!F2,'Recurring Transactions'!G2:S2)))),1)),"Repayment Schedule") -> Repayment Schedule | U1: Payment Method
A2: 45658 | B2: Rent | C2: Rent | D2: 10056 | E2: Overhead Expenditures | F2: monthly | G2: =IFS($F2="bi-weekly",$A2+CEILING(('13-week CF Forecast'!$B$1-$A2)/14,1)*14+14*(COLUMN()-7),$F2="weekly",$A2+CEILING(('13-week CF Forecast'!$B$1-$A2)/7,1)*7+7*(COLUMN()-7),$F2="monthly",DATE(YEAR($A2),MONTH($A2)+CEILING(DATEDIF($A2,'13-week CF Forecast'!$B$1,"m")+1,1)+COLUMN()-7,DAY($A2)),$F2="quarterly",DATE(YEAR($A2),MONTH($A2)+3*CEILING((DATEDIF($A2,'13-week CF Forecast'!$B$1,"m")+1)/3,1)+(COLUMN()-7)*3,DAY($A2)),$F2="yearly",DATE(YEAR($A2)+CEILING((DATEDIF($A2,'13-week CF Forecast'!$B$1,"y")+1),1)+COLUMN()-7,MONTH($A2),DAY($A2)),TRUE,"") -> 45839 | H2: =IFS($F2="bi-weekly",$A2+CEILING(('13-week CF Forecast'!$B$1-$A2)/14,1)*14+14*(COLUMN()-7),$F2="weekly",$A2+CEILING(('13-week CF Forecast'!$B$1-$A2)/7,1)*7+7*(COLUMN()-7),$F2="monthly",DATE(YEAR($A2),MONTH($A2)+CEILING(DATEDIF($A2,'13-week CF Forecast'!$B$1,"m")+1,1)+COLUMN()-7,DAY($A2)),$F2="quarterly",DATE(YEAR($A2),MONTH($A2)+3*CEILING((DATEDIF($A2,'13-week CF Forecast'!$B$1,"m")+1)/3,1)+(COLUMN()-7)*3,DAY($A2)),$F2="yearly",DATE(YEAR($A2)+CEILING((DATEDIF($A2,'13-week CF Forecast'!$B$1,"y")+1),1)+COLUMN()-7,MONTH($A2),DAY($A2)),TRUE,"") -> 45870 | I2: =IFS($F2="bi-weekly",$A2+CEILING(('13-week CF Forecast'!$B$1-$A2)/14,1)*14+14*(COLUMN()-7),$F2="weekly",$A2+CEILING(('13-week CF Forecast'!$B$1-$A2)/7,1)*7+7*(COLUMN()-7),$F2="monthly",DATE(YEAR($A2),MONTH($A2)+CEILING(DATEDIF($A2,'13-week CF Forecast'!$B$1,"m")+1,1)+COLUMN()-7,DAY($A2)),$F2="quarterly",DATE(YEAR($A2),MONTH($A2)+3*CEILING((DATEDIF($A2,'13-week CF Forecast'!$B$1,"m")+1)/3,1)+(COLUMN()-7)*3,DAY($A2)),$F2="yearly",DATE(YEAR($A2)+CEILING((DATEDIF($A2,'13-week CF Forecast'!$B$1,"y")+1),1)+COLUMN()-7,MONTH($A2),DAY($A2)),TRUE,"") -> 45901 | J2: =IFS($F2="bi-weekly",$A2+CEILING(('13-week CF Forecast'!$B$1-$A2)/14,1)*14+14*(COLUMN()-7),$F2="weekly",$A2+CEILING(('13-week CF Forecast'!$B$1-$A2)/7,1)*7+7*(COLUMN()-7),$F2="monthly",DATE(YEAR($A2),MONTH($A2)+CEILING(DATEDIF($A2,'13-week CF Forecast'!$B$1,"m")+1,1)+COLUMN()-7,DAY($A2)),$F2="quarterly",DATE(YEAR($A2),MONTH($A2)+3*CEILING((DATEDIF($A2,'13-week CF Forecast'!$B$1,"m")+1)/3,1)+(COLUMN()-7)*3,DAY($A2)),$F2="yearly",DATE(YEAR($A2)+CEILING((DATEDIF($A2,'13-week CF Forecast'!$B$1,"y")+1),1)+COLUMN()-7,MONTH($A2),DAY($A2)),TRUE,"") -> 45931 | K2: =IFS($F2="bi-weekly",$A2+CEILING(('13-week CF Forecast'!$B$1-$A2)/14,1)*14+14*(COLUMN()-7),$F2="weekly",$A2+CEILING(('13-week CF Forecast'!$B$1-$A2)/7,1)*7+7*(COLUMN()-7),$F2="monthly",DATE(YEAR($A2),MONTH($A2)+CEILING(DATEDIF($A2,'13-week CF Forecast'!$B$1,"m")+1,1)+COLUMN()-7,DAY($A2)),$F2="quarterly",DATE(YEAR($A2),MONTH($A2)+3*CEILING((DATEDIF($A2,'13-week CF Forecast'!$B$1,"m")+1)/3,1)+(COLUMN()-7)*3,DAY($A2)),$F2="yearly",DATE(YEAR($A2)+CEILING((DATEDIF($A2,'13-week CF Forecast'!$B$1,"y")+1),1)+COLUMN()-7,MONTH($A2),DAY($A2)),TRUE,"") -> 45962 | L2: =IFS($F2="bi-weekly",$A2+CEILING(('13-week CF Forecast'!$B$1-$A2)/14,1)*14+14*(COLUMN()-7),$F2="weekly",$A2+CEILING(('13-week CF Forecast'!$B$1-$A2)/7,1)*7+7*(COLUMN()-7),$F2="monthly",DATE(YEAR($A2),MONTH($A2)+CEILING(DATEDIF($A2,'13-week CF Forecast'!$B$1,"m")+1,1)+COLUMN()-7,DAY($A2)),$F2="quarterly",DATE(YEAR($A2),MONTH($A2)+3*CEILING((DATEDIF($A2,'13-week CF Forecast'!$B$1,"m")+1)/3,1)+(COLUMN()-7)*3,DAY($A2)),$F2="yearly",DATE(YEAR($A2)+CEILING((DATEDIF($A2,'13-week CF Forecast'!$B$1,"y")+1),1)+COLUMN()-7,MONTH($A2),DAY($A2)),TRUE,"") -> 45992 | M2: =IFS($F2="bi-weekly",$A2+CEILING(('13-week CF Forecast'!$B$1-$A2)/14,1)*14+14*(COLUMN()-7),$F2="weekly",$A2+CEILING(('13-week CF Forecast'!$B$1-$A2)/7,1)*7+7*(COLUMN()-7),$F2="monthly",DATE(YEAR($A2),MONTH($A2)+CEILING(DATEDIF($A2,'13-week CF Forecast'!$B$1,"m")+1,1)+COLUMN()-7,DAY($A2)),$F2="quarterly",DATE(YEAR($A2),MONTH($A2)+3*CEILING((DATEDIF($A2,'13-week CF Forecast'!$B$1,"m")+1)/3,1)+(COLUMN()-7)*3,DAY($A2)),$F2="yearly",DATE(YEAR($A2)+CEILING((DATEDIF($A2,'13-week CF Forecast'!$B$1,"y")+1),1)+COLUMN()-7,MONTH($A2),DAY($A2)),TRUE,"") -> 46023 | N2: =IFS($F2="bi-weekly",$A2+CEILING(('13-week CF Forecast'!$B$1-$A2)/14,1)*14+14*(COLUMN()-7),$F2="weekly",$A2+CEILING(('13-week CF Forecast'!$B$1-$A2)/7,1)*7+7*(COLUMN()-7),$F2="monthly",DATE(YEAR($A2),MONTH($A2)+CEILING(DATEDIF($A2,'13-week CF Forecast'!$B$1,"m")+1,1)+COLUMN()-7,DAY($A2)),$F2="quarterly",DATE(YEAR($A2),MONTH($A2)+3*CEILING((DATEDIF($A2,'13-week CF Forecast'!$B$1,"m")+1)/3,1)+(COLUMN()-7)*3,DAY($A2)),$F2="yearly",DATE(YEAR($A2)+CEILING((DATEDIF($A2,'13-week CF Forecast'!$B$1,"y")+1),1)+COLUMN()-7,MONTH($A2),DAY($A2)),TRUE,"") -> 46054 | ... S2: =IFS($F2="bi-weekly",$A2+CEILING(('13-week CF Forecast'!$B$1-$A2)/14,1)*14+14*(COLUMN()-7),$F2="weekly",$A2+CEILING(('13-week CF Forecast'!$B$1-$A2)/7,1)*7+7*(COLUMN()-7),$F2="monthly",DATE(YEAR($A2),MONTH($A2)+CEILING(DATEDIF($A2,'13-week CF Forecast'!$B$1,"m")+1,1)+COLUMN()-7,DAY($A2)),$F2="quarterly",DATE(YEAR($A2),MONTH($A2)+3*CEILING((DATEDIF($A2,'13-week CF Forecast'!$B$1,"m")+1)/3,1)+(COLUMN()-7)*3,DAY($A2)),$F2="yearly",DATE(YEAR($A2)+CEILING((DATEDIF($A2,'13-week CF Forecast'!$B$1,"y")+1),1)+COLUMN()-7,MONTH($A2),DAY($A2)),TRUE,"") -> 46204 | T2: =IFERROR(ROWSDUMMYFUNCTION(UNNEST(PAIR2JSON('Recurring Transactions'!$A$1,'Recurring Transactions'!A2,'Recurring Transactions'!$B$1,'Recurring Transactions'!B2,'Recurring Transactions'!$C$1,'Recurring Transactions'!C2,'Recurring Transactions'!$D$1,'Recurring Transactions'!D2,'Recurring Transactions'!$E$1,'Recurring Transactions'!E2,'Recurring Transactions'!$F$1,'Recurring Transactions'!F2,"Payment schedule",VALUE(RANGE2JSON('Recurring Transactions'!F2,'Recurring Transactions'!G2:S2))))),"[{""First payment date"":""2025-01-01"",""Counterparty"":""Rent"",""Description"":""Rent"",""Amount"":""$10056"",""Category"":""Overhead Expenditures"",""Frequency"":""monthly"",""Payment schedule_0"":""2025-07-01""},{""First payment date"":""2025-01-01"",""Counterparty"":""Rent"",""Descript"&"ion"":""Rent"",""Amount"":""$10056"",""Category"":""Overhead Expenditures"",""Frequency"":""monthly"",""Payment schedule_0"":""2025-08-01""},{""First payment date"":""2025-01-01"",""Counterparty"":""Rent"",""Description"":""Rent"",""Amount"":""$10056"",""Category"":""Overhead Expenditures"",""F"&"requency"":""monthly"",""Payment schedule_0"":""2025-09-01""},{""First payment date"":""2025-01-01"",""Counterparty"":""Rent"",""Description"":""Rent"",""Amount"":""$10056"",""Category"":""Overhead Expenditures"",""Frequency"":""monthly"",""Payment schedule_0"":""2025-10-01""},{""First paym"&"ent date"":""2025-01-01"",""Counterparty"":""Rent"",""Description"":""Rent"",""Amount"":""$10056"",""Category"":""Overhead Expenditures"",""Frequency"":""monthly"",""Payment schedule_0"":""2025-11-01""},{""First payment date"":""2025-01-01"",""Counterparty"":""Rent"",""Description"":""Rent"","""&"Amount"":""$10056"",""Category"":""Overhead Expenditures"",""Frequency"":""monthly"",""Payment schedule_0"":""2025-12-01""},{""First payment date"":""2025-01-01"",""Counterparty"":""Rent"",""Description"":""Rent"",""Amount"":""$10056"",""Category"":""Overhead Expenditures"",""Frequency"":""mo"&"nthly"",""Payment schedule_0"":""2026-01-01""},{""First payment date"":""2025-01-01"",""Counterparty"":""Rent"",""Description"":""Rent"",""Amount"":""$10056"",""Category"":""Overhead Expenditures"",""Frequency"":""monthly"",""Payment schedule_0"":""2026-02-01""},{""First payment date"":""20"&"25-01-01"",""Counterparty"":""Rent"",""Description"":""Rent"",""Amount"":""$10056"",""Category"":""Overhead Expenditures"",""Frequency"":""monthly"",""Payment schedule_0"":""2026-03-01""},{""First payment date"":""2025-01-01"",""Counterparty"":""Rent"",""Description"":""Rent"",""Amount"":""$100"&"56"",""Category"":""Overhead Expenditures"",""Frequency"":""monthly"",""Payment schedule_0"":""2026-04-01""},{""First payment date"":""2025-01-01"",""Counterparty"":""Rent"",""Description"":""Rent"",""Amount"":""$10056"",""Category"":""Overhead Expenditures"",""Frequency"":""monthly"",""Payme"&"nt schedule_0"":""2026-05-01""},{""First payment date"":""2025-01-01"",""Counterparty"":""Rent"",""Description"":""Rent"",""Amount"":""$10056"",""Category"":""Overhead Expenditures"",""Frequency"":""monthly"",""Payment schedule_0"":""2026-06-01""},{""First payment date"":""2025-01-01"",""Co"&"unterparty"":""Rent"",""Description"":""Rent"",""Amount"":""$10056"",""Category"":""Overhead Expenditures"",""Frequency"":""monthly"",""Payment schedule_0"":""2026-07-01""}]") -> [{"First payment date":"2025-01-01","Counterparty":"Rent","Description":"Rent","Amount":"$10056","Category":"Overhead Expenditures","Frequency":"monthly","Payment schedule_0":"2025-07-01"},{"First payment date":"2025-01-01","Counterparty":"Rent","Description":"Rent","Amount":"$10056","Category":"Overhead Expenditures","Frequency":"monthly","Payment schedule_0":"2025-08-01"},{"First payment date":"2025-01-01","Counterparty":"Rent","Description":"Rent","Amount":"$10056","Category":"Overhead Expenditures","Frequency":"monthly","Payment schedule_0":"2025-09-01"},{"First payment date":"2025-01-01","Counterparty":"Rent","Description":"Rent","Amount":"$10056","Category":"Overhead Expenditures","Frequency":"monthly","Payment schedule_0":"2025-10-01"},{"First payment date":"2025-01-01","Counterparty":"Rent","Description":"Rent","Amount":"$10056","Category":"Overhead Expenditures","Frequency":"monthly","Payment schedule_0":"2025-11-01"},{"First payment date":"2025-01-01","Counterparty":"Rent","Description":"Rent","Amount":"$10056","Category":"Overhead Expenditures","Frequency":"monthly","Payment schedule_0":"2025-12-01"},{"First payment date":"2025-01-01","Counterparty":"Rent","Description":"Rent","Amount":"$10056","Category":"Overhead Expenditures","Frequency":"monthly","Payment schedule_0":"2026-01-01"},{"First payment date":"2025-01-01","Counterparty":"Rent","Description":"Rent","Amount":"$10056","Category":"Overhead Expenditures","Frequency":"monthly","Payment schedule_0":"2026-02-01"},{"First payment date":"2025-01-01","Counterparty":"Rent","Description":"Rent","Amount":"$10056","Category":"Overhead Expenditures","Frequency":"monthly","Payment schedule_0":"2026-03-01"},{"First payment date":"2025-01-01","Counterparty":"Rent","Description":"Rent","Amount":"$10056","Category":"Overhead Expenditures","Frequency":"monthly","Payment schedule_0":"2026-04-01"},{"First payment date":"2025-01-01","Counterparty":"Rent","Description":"Rent","Amount":"$10056","Category":"Overhead Expenditures","Frequency":"monthly","Payment schedule_0":"2026-05-01"},{"First payment date":"2025-01-01","Counterparty":"Rent","Description":"Rent","Amount":"$10056","Category":"Overhead Expenditures","Frequency":"monthly","Payment schedule_0":"2026-06-01"},{"First payment date":"2025-01-01","Counterparty":"Rent","Description":"Rent","Amount":"$10056","Category":"Overhead Expenditures","Frequency":"monthly","Payment schedule_0":"2026-07-01"}] | U2: Staychill
A3: 45658 | B3: Sublease | C3: Sublease | D3: 3056.37 | E3: Overhead Expenditures | F3: monthly | G3: =IFS($F3="bi-weekly",$A3+CEILING(('13-week CF Forecast'!$B$1-$A3)/14,1)*14+14*(COLUMN()-7),$F3="weekly",$A3+CEILING(('13-week CF Forecast'!$B$1-$A3)/7,1)*7+7*(COLUMN()-7),$F3="monthly",DATE(YEAR($A3),MONTH($A3)+CEILING(DATEDIF($A3,'13-week CF Forecast'!$B$1,"m")+1,1)+COLUMN()-7,DAY($A3)),$F3="quarterly",DATE(YEAR($A3),MONTH($A3)+3*CEILING((DATEDIF($A3,'13-week CF Forecast'!$B$1,"m")+1)/3,1)+(COLUMN()-7)*3,DAY($A3)),$F3="yearly",DATE(YEAR($A3)+CEILING((DATEDIF($A3,'13-week CF Forecast'!$B$1,"y")+1),1)+COLUMN()-7,MONTH($A3),DAY($A3)),TRUE,"") -> 45839 | H3: =IFS($F3="bi-weekly",$A3+CEILING(('13-week CF Forecast'!$B$1-$A3)/14,1)*14+14*(COLUMN()-7),$F3="weekly",$A3+CEILING(('13-week CF Forecast'!$B$1-$A3)/7,1)*7+7*(COLUMN()-7),$F3="monthly",DATE(YEAR($A3),MONTH($A3)+CEILING(DATEDIF($A3,'13-week CF Forecast'!$B$1,"m")+1,1)+COLUMN()-7,DAY($A3)),$F3="quarterly",DATE(YEAR($A3),MONTH($A3)+3*CEILING((DATEDIF($A3,'13-week CF Forecast'!$B$1,"m")+1)/3,1)+(COLUMN()-7)*3,DAY($A3)),$F3="yearly",DATE(YEAR($A3)+CEILING((DATEDIF($A3,'13-week CF Forecast'!$B$1,"y")+1),1)+COLUMN()-7,MONTH($A3),DAY($A3)),TRUE,"") -> 45870 | I3: =IFS($F3="bi-weekly",$A3+CEILING(('13-week CF Forecast'!$B$1-$A3)/14,1)*14+14*(COLUMN()-7),$F3="weekly",$A3+CEILING(('13-week CF Forecast'!$B$1-$A3)/7,1)*7+7*(COLUMN()-7),$F3="monthly",DATE(YEAR($A3),MONTH($A3)+CEILING(DATEDIF($A3,'13-week CF Forecast'!$B$1,"m")+1,1)+COLUMN()-7,DAY($A3)),$F3="quarterly",DATE(YEAR($A3),MONTH($A3)+3*CEILING((DATEDIF($A3,'13-week CF Forecast'!$B$1,"m")+1)/3,1)+(COLUMN()-7)*3,DAY($A3)),$F3="yearly",DATE(YEAR($A3)+CEILING((DATEDIF($A3,'13-week CF Forecast'!$B$1,"y")+1),1)+COLUMN()-7,MONTH($A3),DAY($A3)),TRUE,"") -> 45901 | J3: =IFS($F3="bi-weekly",$A3+CEILING(('13-week CF Forecast'!$B$1-$A3)/14,1)*14+14*(COLUMN()-7),$F3="weekly",$A3+CEILING(('13-week CF Forecast'!$B$1-$A3)/7,1)*7+7*(COLUMN()-7),$F3="monthly",DATE(YEAR($A3),MONTH($A3)+CEILING(DATEDIF($A3,'13-week CF Forecast'!$B$1,"m")+1,1)+COLUMN()-7,DAY($A3)),$F3="quarterly",DATE(YEAR($A3),MONTH($A3)+3*CEILING((DATEDIF($A3,'13-week CF Forecast'!$B$1,"m")+1)/3,1)+(COLUMN()-7)*3,DAY($A3)),$F3="yearly",DATE(YEAR($A3)+CEILING((DATEDIF($A3,'13-week CF Forecast'!$B$1,"y")+1),1)+COLUMN()-7,MONTH($A3),DAY($A3)),TRUE,"") -> 45931 | K3: =IFS($F3="bi-weekly",$A3+CEILING(('13-week CF Forecast'!$B$1-$A3)/14,1)*14+14*(COLUMN()-7),$F3="weekly",$A3+CEILING(('13-week CF Forecast'!$B$1-$A3)/7,1)*7+7*(COLUMN()-7),$F3="monthly",DATE(YEAR($A3),MONTH($A3)+CEILING(DATEDIF($A3,'13-week CF Forecast'!$B$1,"m")+1,1)+COLUMN()-7,DAY($A3)),$F3="quarterly",DATE(YEAR($A3),MONTH($A3)+3*CEILING((DATEDIF($A3,'13-week CF Forecast'!$B$1,"m")+1)/3,1)+(COLUMN()-7)*3,DAY($A3)),$F3="yearly",DATE(YEAR($A3)+CEILING((DATEDIF($A3,'13-week CF Forecast'!$B$1,"y")+1),1)+COLUMN()-7,MONTH($A3),DAY($A3)),TRUE,"") -> 45962 | L3: =IFS($F3="bi-weekly",$A3+CEILING(('13-week CF Forecast'!$B$1-$A3)/14,1)*14+14*(COLUMN()-7),$F3="weekly",$A3+CEILING(('13-week CF Forecast'!$B$1-$A3)/7,1)*7+7*(COLUMN()-7),$F3="monthly",DATE(YEAR($A3),MONTH($A3)+CEILING(DATEDIF($A3,'13-week CF Forecast'!$B$1,"m")+1,1)+COLUMN()-7,DAY($A3)),$F3="quarterly",DATE(YEAR($A3),MONTH($A3)+3*CEILING((DATEDIF($A3,'13-week CF Forecast'!$B$1,"m")+1)/3,1)+(COLUMN()-7)*3,DAY($A3)),$F3="yearly",DATE(YEAR($A3)+CEILING((DATEDIF($A3,'13-week CF Forecast'!$B$1,"y")+1),1)+COLUMN()-7,MONTH($A3),DAY($A3)),TRUE,"") -> 45992 | M3: =IFS($F3="bi-weekly",$A3+CEILING(('13-week CF Forecast'!$B$1-$A3)/14,1)*14+14*(COLUMN()-7),$F3="weekly",$A3+CEILING(('13-week CF Forecast'!$B$1-$A3)/7,1)*7+7*(COLUMN()-7),$F3="monthly",DATE(YEAR($A3),MONTH($A3)+CEILING(DATEDIF($A3,'13-week CF Forecast'!$B$1,"m")+1,1)+COLUMN()-7,DAY($A3)),$F3="quarterly",DATE(YEAR($A3),MONTH($A3)+3*CEILING((DATEDIF($A3,'13-week CF Forecast'!$B$1,"m")+1)/3,1)+(COLUMN()-7)*3,DAY($A3)),$F3="yearly",DATE(YEAR($A3)+CEILING((DATEDIF($A3,'13-week CF Forecast'!$B$1,"y")+1),1)+COLUMN()-7,MONTH($A3),DAY($A3)),TRUE,"") -> 46023 | N3: =IFS($F3="bi-weekly",$A3+CEILING(('13-week CF Forecast'!$B$1-$A3)/14,1)*14+14*(COLUMN()-7),$F3="weekly",$A3+CEILING(('13-week CF Forecast'!$B$1-$A3)/7,1)*7+7*(COLUMN()-7),$F3="monthly",DATE(YEAR($A3),MONTH($A3)+CEILING(DATEDIF($A3,'13-week CF Forecast'!$B$1,"m")+1,1)+COLUMN()-7,DAY($A3)),$F3="quarterly",DATE(YEAR($A3),MONTH($A3)+3*CEILING((DATEDIF($A3,'13-week CF Forecast'!$B$1,"m")+1)/3,1)+(COLUMN()-7)*3,DAY($A3)),$F3="yearly",DATE(YEAR($A3)+CEILING((DATEDIF($A3,'13-week CF Forecast'!$B$1,"y")+1),1)+COLUMN()-7,MONTH($A3),DAY($A3)),TRUE,"") -> 46054 | ... S3: =IFS($F3="bi-weekly",$A3+CEILING(('13-week CF Forecast'!$B$1-$A3)/14,1)*14+14*(COLUMN()-7),$F3="weekly",$A3+CEILING(('13-week CF Forecast'!$B$1-$A3)/7,1)*7+7*(COLUMN()-7),$F3="monthly",DATE(YEAR($A3),MONTH($A3)+CEILING(DATEDIF($A3,'13-week CF Forecast'!$B$1,"m")+1,1)+COLUMN()-7,DAY($A3)),$F3="quarterly",DATE(YEAR($A3),MONTH($A3)+3*CEILING((DATEDIF($A3,'13-week CF Forecast'!$B$1,"m")+1)/3,1)+(COLUMN()-7)*3,DAY($A3)),$F3="yearly",DATE(YEAR($A3)+CEILING((DATEDIF($A3,'13-week CF Forecast'!$B$1,"y")+1),1)+COLUMN()-7,MONTH($A3),DAY($A3)),TRUE,"") -> 46204 | T3: =IFERROR(ROWSDUMMYFUNCTION(UNNEST(PAIR2JSON('Recurring Transactions'!$A$1,'Recurring Transactions'!A3,'Recurring Transactions'!$B$1,'Recurring Transactions'!B3,'Recurring Transactions'!$C$1,'Recurring Transactions'!C3,'Recurring Transactions'!$D$1,'Recurring Transactions'!D3,'Recurring Transactions'!$E$1,'Recurring Transactions'!E3,'Recurring Transactions'!$F$1,'Recurring Transactions'!F3,"Payment schedule",VALUE(RANGE2JSON('Recurring Transactions'!F3,'Recurring Transactions'!G3:S3))))),"[{""First payment date"":""2025-01-01"",""Counterparty"":""Sublease"",""Description"":""Sublease"",""Amount"":""$3056.37"",""Category"":""Overhead Expenditures"",""Frequency"":""monthly"",""Payment schedule_0"":""2025-07-01""},{""First payment date"":""2025-01-01"",""Counterparty"":""Suble"&"ase"",""Description"":""Sublease"",""Amount"":""$3056.37"",""Category"":""Overhead Expenditures"",""Frequency"":""monthly"",""Payment schedule_0"":""2025-08-01""},{""First payment date"":""2025-01-01"",""Counterparty"":""Sublease"",""Description"":""Sublease"",""Amount"":""$3056.37"",""Catego"&"ry"":""Overhead Expenditures"",""Frequency"":""monthly"",""Payment schedule_0"":""2025-09-01""},{""First payment date"":""2025-01-01"",""Counterparty"":""Sublease"",""Description"":""Sublease"",""Amount"":""$3056.37"",""Category"":""Overhead Expenditures"",""Frequency"":""monthly"",""Paymen"&"t schedule_0"":""2025-10-01""},{""First payment date"":""2025-01-01"",""Counterparty"":""Sublease"",""Description"":""Sublease"",""Amount"":""$3056.37"",""Category"":""Overhead Expenditures"",""Frequency"":""monthly"",""Payment schedule_0"":""2025-11-01""},{""First payment date"":""2025-0"&"1-01"",""Counterparty"":""Sublease"",""Description"":""Sublease"",""Amount"":""$3056.37"",""Category"":""Overhead Expenditures"",""Frequency"":""monthly"",""Payment schedule_0"":""2025-12-01""},{""First payment date"":""2025-01-01"",""Counterparty"":""Sublease"",""Description"":""Sublease"","&"""Amount"":""$3056.37"",""Category"":""Overhead Expenditures"",""Frequency"":""monthly"",""Payment schedule_0"":""2026-01-01""},{""First payment date"":""2025-01-01"",""Counterparty"":""Sublease"",""Description"":""Sublease"",""Amount"":""$3056.37"",""Category"":""Overhead Expenditures"",""F"&"requency"":""monthly"",""Payment schedule_0"":""2026-02-01""},{""First payment date"":""2025-01-01"",""Counterparty"":""Sublease"",""Description"":""Sublease"",""Amount"":""$3056.37"",""Category"":""Overhead Expenditures"",""Frequency"":""monthly"",""Payment schedule_0"":""2026-03-01""},{"""&"First payment date"":""2025-01-01"",""Counterparty"":""Sublease"",""Description"":""Sublease"",""Amount"":""$3056.37"",""Category"":""Overhead Expenditures"",""Frequency"":""monthly"",""Payment schedule_0"":""2026-04-01""},{""First payment date"":""2025-01-01"",""Counterparty"":""Sublease"&""",""Description"":""Sublease"",""Amount"":""$3056.37"",""Category"":""Overhead Expenditures"",""Frequency"":""monthly"",""Payment schedule_0"":""2026-05-01""},{""First payment date"":""2025-01-01"",""Counterparty"":""Sublease"",""Description"":""Sublease"",""Amount"":""$3056.37"",""Category"""&":""Overhead Expenditures"",""Frequency"":""monthly"",""Payment schedule_0"":""2026-06-01""},{""First payment date"":""2025-01-01"",""Counterparty"":""Sublease"",""Description"":""Sublease"",""Amount"":""$3056.37"",""Category"":""Overhead Expenditures"",""Frequency"":""monthly"",""Payment s"&"chedule_0"":""2026-07-01""}]") -> [{"First payment date":"2025-01-01","Counterparty":"Sublease","Description":"Sublease","Amount":"$3056.37","Category":"Overhead Expenditures","Frequency":"monthly","Payment schedule_0":"2025-07-01"},{"First payment date":"2025-01-01","Counterparty":"Sublease","Description":"Sublease","Amount":"$3056.37","Category":"Overhead Expenditures","Frequency":"monthly","Payment schedule_0":"2025-08-01"},{"First payment date":"2025-01-01","Counterparty":"Sublease","Description":"Sublease","Amount":"$3056.37","Category":"Overhead Expenditures","Frequency":"monthly","Payment schedule_0":"2025-09-01"},{"First payment date":"2025-01-01","Counterparty":"Sublease","Description":"Sublease","Amount":"$3056.37","Category":"Overhead Expenditures","Frequency":"monthly","Payment schedule_0":"2025-10-01"},{"First payment date":"2025-01-01","Counterparty":"Sublease","Description":"Sublease","Amount":"$3056.37","Category":"Overhead Expenditures","Frequency":"monthly","Payment schedule_0":"2025-11-01"},{"First payment date":"2025-01-01","Counterparty":"Sublease","Description":"Sublease","Amount":"$3056.37","Category":"Overhead Expenditures","Frequency":"monthly","Payment schedule_0":"2025-12-01"},{"First payment date":"2025-01-01","Counterparty":"Sublease","Description":"Sublease","Amount":"$3056.37","Category":"Overhead Expenditures","Frequency":"monthly","Payment schedule_0":"2026-01-01"},{"First payment date":"2025-01-01","Counterparty":"Sublease","Description":"Sublease","Amount":"$3056.37","Category":"Overhead Expenditures","Frequency":"monthly","Payment schedule_0":"2026-02-01"},{"First payment date":"2025-01-01","Counterparty":"Sublease","Description":"Sublease","Amount":"$3056.37","Category":"Overhead Expenditures","Frequency":"monthly","Payment schedule_0":"2026-03-01"},{"First payment date":"2025-01-01","Counterparty":"Sublease","Description":"Sublease","Amount":"$3056.37","Category":"Overhead Expenditures","Frequency":"monthly","Payment schedule_0":"2026-04-01"},{"First payment date":"2025-01-01","Counterparty":"Sublease","Description":"Sublease","Amount":"$3056.37","Category":"Overhead Expenditures","Frequency":"monthly","Payment schedule_0":"2026-05-01"},{"First payment date":"2025-01-01","Counterparty":"Sublease","Description":"Sublease","Amount":"$3056.37","Category":"Overhead Expenditures","Frequency":"monthly","Payment schedule_0":"2026-06-01"},{"First payment date":"2025-01-01","Counterparty":"Sublease","Description":"Sublease","Amount":"$3056.37","Category":"Overhead Expenditures","Frequency":"monthly","Payment schedule_0":"2026-07-01"}] | U3: Staychill
A4: 45658 | B4: Dalton | C4: Dalton | D4: 5000 | E4: Overhead Expenditures | F4: monthly | G4: =IFS($F4="bi-weekly",$A4+CEILING(('13-week CF Forecast'!$B$1-$A4)/14,1)*14+14*(COLUMN()-7),$F4="weekly",$A4+CEILING(('13-week CF Forecast'!$B$1-$A4)/7,1)*7+7*(COLUMN()-7),$F4="monthly",DATE(YEAR($A4),MONTH($A4)+CEILING(DATEDIF($A4,'13-week CF Forecast'!$B$1,"m")+1,1)+COLUMN()-7,DAY($A4)),$F4="quarterly",DATE(YEAR($A4),MONTH($A4)+3*CEILING((DATEDIF($A4,'13-week CF Forecast'!$B$1,"m")+1)/3,1)+(COLUMN()-7)*3,DAY($A4)),$F4="yearly",DATE(YEAR($A4)+CEILING((DATEDIF($A4,'13-week CF Forecast'!$B$1,"y")+1),1)+COLUMN()-7,MONTH($A4),DAY($A4)),TRUE,"") -> 45839 | H4: =IFS($F4="bi-weekly",$A4+CEILING(('13-week CF Forecast'!$B$1-$A4)/14,1)*14+14*(COLUMN()-7),$F4="weekly",$A4+CEILING(('13-week CF Forecast'!$B$1-$A4)/7,1)*7+7*(COLUMN()-7),$F4="monthly",DATE(YEAR($A4),MONTH($A4)+CEILING(DATEDIF($A4,'13-week CF Forecast'!$B$1,"m")+1,1)+COLUMN()-7,DAY($A4)),$F4="quarterly",DATE(YEAR($A4),MONTH($A4)+3*CEILING((DATEDIF($A4,'13-week CF Forecast'!$B$1,"m")+1)/3,1)+(COLUMN()-7)*3,DAY($A4)),$F4="yearly",DATE(YEAR($A4)+CEILING((DATEDIF($A4,'13-week CF Forecast'!$B$1,"y")+1),1)+COLUMN()-7,MONTH($A4),DAY($A4)),TRUE,"") -> 45870 | I4: =IFS($F4="bi-weekly",$A4+CEILING(('13-week CF Forecast'!$B$1-$A4)/14,1)*14+14*(COLUMN()-7),$F4="weekly",$A4+CEILING(('13-week CF Forecast'!$B$1-$A4)/7,1)*7+7*(COLUMN()-7),$F4="monthly",DATE(YEAR($A4),MONTH($A4)+CEILING(DATEDIF($A4,'13-week CF Forecast'!$B$1,"m")+1,1)+COLUMN()-7,DAY($A4)),$F4="quarterly",DATE(YEAR($A4),MONTH($A4)+3*CEILING((DATEDIF($A4,'13-week CF Forecast'!$B$1,"m")+1)/3,1)+(COLUMN()-7)*3,DAY($A4)),$F4="yearly",DATE(YEAR($A4)+CEILING((DATEDIF($A4,'13-week CF Forecast'!$B$1,"y")+1),1)+COLUMN()-7,MONTH($A4),DAY($A4)),TRUE,"") -> 45901 | J4: =IFS($F4="bi-weekly",$A4+CEILING(('13-week CF Forecast'!$B$1-$A4)/14,1)*14+14*(COLUMN()-7),$F4="weekly",$A4+CEILING(('13-week CF Forecast'!$B$1-$A4)/7,1)*7+7*(COLUMN()-7),$F4="monthly",DATE(YEAR($A4),MONTH($A4)+CEILING(DATEDIF($A4,'13-week CF Forecast'!$B$1,"m")+1,1)+COLUMN()-7,DAY($A4)),$F4="quarterly",DATE(YEAR($A4),MONTH($A4)+3*CEILING((DATEDIF($A4,'13-week CF Forecast'!$B$1,"m")+1)/3,1)+(COLUMN()-7)*3,DAY($A4)),$F4="yearly",DATE(YEAR($A4)+CEILING((DATEDIF($A4,'13-week CF Forecast'!$B$1,"y")+1),1)+COLUMN()-7,MONTH($A4),DAY($A4)),TRUE,"") -> 45931 | K4: =IFS($F4="bi-weekly",$A4+CEILING(('13-week CF Forecast'!$B$1-$A4)/14,1)*14+14*(COLUMN()-7),$F4="weekly",$A4+CEILING(('13-week CF Forecast'!$B$1-$A4)/7,1)*7+7*(COLUMN()-7),$F4="monthly",DATE(YEAR($A4),MONTH($A4)+CEILING(DATEDIF($A4,'13-week CF Forecast'!$B$1,"m")+1,1)+COLUMN()-7,DAY($A4)),$F4="quarterly",DATE(YEAR($A4),MONTH($A4)+3*CEILING((DATEDIF($A4,'13-week CF Forecast'!$B$1,"m")+1)/3,1)+(COLUMN()-7)*3,DAY($A4)),$F4="yearly",DATE(YEAR($A4)+CEILING((DATEDIF($A4,'13-week CF Forecast'!$B$1,"y")+1),1)+COLUMN()-7,MONTH($A4),DAY($A4)),TRUE,"") -> 45962 | L4: =IFS($F4="bi-weekly",$A4+CEILING(('13-week CF Forecast'!$B$1-$A4)/14,1)*14+14*(COLUMN()-7),$F4="weekly",$A4+CEILING(('13-week CF Forecast'!$B$1-$A4)/7,1)*7+7*(COLUMN()-7),$F4="monthly",DATE(YEAR($A4),MONTH($A4)+CEILING(DATEDIF($A4,'13-week CF Forecast'!$B$1,"m")+1,1)+COLUMN()-7,DAY($A4)),$F4="quarterly",DATE(YEAR($A4),MONTH($A4)+3*CEILING((DATEDIF($A4,'13-week CF Forecast'!$B$1,"m")+1)/3,1)+(COLUMN()-7)*3,DAY($A4)),$F4="yearly",DATE(YEAR($A4)+CEILING((DATEDIF($A4,'13-week CF Forecast'!$B$1,"y")+1),1)+COLUMN()-7,MONTH($A4),DAY($A4)),TRUE,"") -> 45992 | M4: =IFS($F4="bi-weekly",$A4+CEILING(('13-week CF Forecast'!$B$1-$A4)/14,1)*14+14*(COLUMN()-7),$F4="weekly",$A4+CEILING(('13-week CF Forecast'!$B$1-$A4)/7,1)*7+7*(COLUMN()-7),$F4="monthly",DATE(YEAR($A4),MONTH($A4)+CEILING(DATEDIF($A4,'13-week CF Forecast'!$B$1,"m")+1,1)+COLUMN()-7,DAY($A4)),$F4="quarterly",DATE(YEAR($A4),MONTH($A4)+3*CEILING((DATEDIF($A4,'13-week CF Forecast'!$B$1,"m")+1)/3,1)+(COLUMN()-7)*3,DAY($A4)),$F4="yearly",DATE(YEAR($A4)+CEILING((DATEDIF($A4,'13-week CF Forecast'!$B$1,"y")+1),1)+COLUMN()-7,MONTH($A4),DAY($A4)),TRUE,"") -> 46023 | N4: =IFS($F4="bi-weekly",$A4+CEILING(('13-week CF Forecast'!$B$1-$A4)/14,1)*14+14*(COLUMN()-7),$F4="weekly",$A4+CEILING(('13-week CF Forecast'!$B$1-$A4)/7,1)*7+7*(COLUMN()-7),$F4="monthly",DATE(YEAR($A4),MONTH($A4)+CEILING(DATEDIF($A4,'13-week CF Forecast'!$B$1,"m")+1,1)+COLUMN()-7,DAY($A4)),$F4="quarterly",DATE(YEAR($A4),MONTH($A4)+3*CEILING((DATEDIF($A4,'13-week CF Forecast'!$B$1,"m")+1)/3,1)+(COLUMN()-7)*3,DAY($A4)),$F4="yearly",DATE(YEAR($A4)+CEILING((DATEDIF($A4,'13-week CF Forecast'!$B$1,"y")+1),1)+COLUMN()-7,MONTH($A4),DAY($A4)),TRUE,"") -> 46054 | ... S4: =IFS($F4="bi-weekly",$A4+CEILING(('13-week CF Forecast'!$B$1-$A4)/14,1)*14+14*(COLUMN()-7),$F4="weekly",$A4+CEILING(('13-week CF Forecast'!$B$1-$A4)/7,1)*7+7*(COLUMN()-7),$F4="monthly",DATE(YEAR($A4),MONTH($A4)+CEILING(DATEDIF($A4,'13-week CF Forecast'!$B$1,"m")+1,1)+COLUMN()-7,DAY($A4)),$F4="quarterly",DATE(YEAR($A4),MONTH($A4)+3*CEILING((DATEDIF($A4,'13-week CF Forecast'!$B$1,"m")+1)/3,1)+(COLUMN()-7)*3,DAY($A4)),$F4="yearly",DATE(YEAR($A4)+CEILING((DATEDIF($A4,'13-week CF Forecast'!$B$1,"y")+1),1)+COLUMN()-7,MONTH($A4),DAY($A4)),TRUE,"") -> 46204 | T4: =IFERROR(ROWSDUMMYFUNCTION(UNNEST(PAIR2JSON('Recurring Transactions'!$A$1,'Recurring Transactions'!A4,'Recurring Transactions'!$B$1,'Recurring Transactions'!B4,'Recurring Transactions'!$C$1,'Recurring Transactions'!C4,'Recurring Transactions'!$D$1,'Recurring Transactions'!D4,'Recurring Transactions'!$E$1,'Recurring Transactions'!E4,'Recurring Transactions'!$F$1,'Recurring Transactions'!F4,"Payment schedule",VALUE(RANGE2JSON('Recurring Transactions'!F4,'Recurring Transactions'!G4:S4))))),"[{""First payment date"":""2025-01-01"",""Counterparty"":""Dalton"",""Description"":""Dalton"",""Amount"":""$5000"",""Category"":""Overhead Expenditures"",""Frequency"":""monthly"",""Payment schedule_0"":""2025-07-01""},{""First payment date"":""2025-01-01"",""Counterparty"":""Dalton"",""Des"&"cription"":""Dalton"",""Amount"":""$5000"",""Category"":""Overhead Expenditures"",""Frequency"":""monthly"",""Payment schedule_0"":""2025-08-01""},{""First payment date"":""2025-01-01"",""Counterparty"":""Dalton"",""Description"":""Dalton"",""Amount"":""$5000"",""Category"":""Overhead Expendi"&"tures"",""Frequency"":""monthly"",""Payment schedule_0"":""2025-09-01""},{""First payment date"":""2025-01-01"",""Counterparty"":""Dalton"",""Description"":""Dalton"",""Amount"":""$5000"",""Category"":""Overhead Expenditures"",""Frequency"":""monthly"",""Payment schedule_0"":""2025-10-01""},"&"{""First payment date"":""2025-01-01"",""Counterparty"":""Dalton"",""Description"":""Dalton"",""Amount"":""$5000"",""Category"":""Overhead Expenditures"",""Frequency"":""monthly"",""Payment schedule_0"":""2025-11-01""},{""First payment date"":""2025-01-01"",""Counterparty"":""Dalton"",""Desc"&"ription"":""Dalton"",""Amount"":""$5000"",""Category"":""Overhead Expenditures"",""Frequency"":""monthly"",""Payment schedule_0"":""2025-12-01""},{""First payment date"":""2025-01-01"",""Counterparty"":""Dalton"",""Description"":""Dalton"",""Amount"":""$5000"",""Category"":""Overhead Expendit"&"ures"",""Frequency"":""monthly"",""Payment schedule_0"":""2026-01-01""},{""First payment date"":""2025-01-01"",""Counterparty"":""Dalton"",""Description"":""Dalton"",""Amount"":""$5000"",""Category"":""Overhead Expenditures"",""Frequency"":""monthly"",""Payment schedule_0"":""2026-02-01""},{"&"""First payment date"":""2025-01-01"",""Counterparty"":""Dalton"",""Description"":""Dalton"",""Amount"":""$5000"",""Category"":""Overhead Expenditures"",""Frequency"":""monthly"",""Payment schedule_0"":""2026-03-01""},{""First payment date"":""2025-01-01"",""Counterparty"":""Dalton"",""Descr"&"iption"":""Dalton"",""Amount"":""$5000"",""Category"":""Overhead Expenditures"",""Frequency"":""monthly"",""Payment schedule_0"":""2026-04-01""},{""First payment date"":""2025-01-01"",""Counterparty"":""Dalton"",""Description"":""Dalton"",""Amount"":""$5000"",""Category"":""Overhead Expenditu"&"res"",""Frequency"":""monthly"",""Payment schedule_0"":""2026-05-01""},{""First payment date"":""2025-01-01"",""Counterparty"":""Dalton"",""Description"":""Dalton"",""Amount"":""$5000"",""Category"":""Overhead Expenditures"",""Frequency"":""monthly"",""Payment schedule_0"":""2026-06-01""},{"""&"First payment date"":""2025-01-01"",""Counterparty"":""Dalton"",""Description"":""Dalton"",""Amount"":""$5000"",""Category"":""Overhead Expenditures"",""Frequency"":""monthly"",""Payment schedule_0"":""2026-07-01""}]") -> [{"First payment date":"2025-01-01","Counterparty":"Dalton","Description":"Dalton","Amount":"$5000","Category":"Overhead Expenditures","Frequency":"monthly","Payment schedule_0":"2025-07-01"},{"First payment date":"2025-01-01","Counterparty":"Dalton","Description":"Dalton","Amount":"$5000","Category":"Overhead Expenditures","Frequency":"monthly","Payment schedule_0":"2025-08-01"},{"First payment date":"2025-01-01","Counterparty":"Dalton","Description":"Dalton","Amount":"$5000","Category":"Overhead Expenditures","Frequency":"monthly","Payment schedule_0":"2025-09-01"},{"First payment date":"2025-01-01","Counterparty":"Dalton","Description":"Dalton","Amount":"$5000","Category":"Overhead Expenditures","Frequency":"monthly","Payment schedule_0":"2025-10-01"},{"First payment date":"2025-01-01","Counterparty":"Dalton","Description":"Dalton","Amount":"$5000","Category":"Overhead Expenditures","Frequency":"monthly","Payment schedule_0":"2025-11-01"},{"First payment date":"2025-01-01","Counterparty":"Dalton","Description":"Dalton","Amount":"$5000","Category":"Overhead Expenditures","Frequency":"monthly","Payment schedule_0":"2025-12-01"},{"First payment date":"2025-01-01","Counterparty":"Dalton","Description":"Dalton","Amount":"$5000","Category":"Overhead Expenditures","Frequency":"monthly","Payment schedule_0":"2026-01-01"},{"First payment date":"2025-01-01","Counterparty":"Dalton","Description":"Dalton","Amount":"$5000","Category":"Overhead Expenditures","Frequency":"monthly","Payment schedule_0":"2026-02-01"},{"First payment date":"2025-01-01","Counterparty":"Dalton","Description":"Dalton","Amount":"$5000","Category":"Overhead Expenditures","Frequency":"monthly","Payment schedule_0":"2026-03-01"},{"First payment date":"2025-01-01","Counterparty":"Dalton","Description":"Dalton","Amount":"$5000","Category":"Overhead Expenditures","Frequency":"monthly","Payment schedule_0":"2026-04-01"},{"First payment date":"2025-01-01","Counterparty":"Dalton","Description":"Dalton","Amount":"$5000","Category":"Overhead Expenditures","Frequency":"monthly","Payment schedule_0":"2026-05-01"},{"First payment date":"2025-01-01","Counterparty":"Dalton","Description":"Dalton","Amount":"$5000","Category":"Overhead Expenditures","Frequency":"monthly","Payment schedule_0":"2026-06-01"},{"First payment date":"2025-01-01","Counterparty":"Dalton","Description":"Dalton","Amount":"$5000","Category":"Overhead Expenditures","Frequency":"monthly","Payment schedule_0":"2026-07-01"}] | U4: Chase Inc
A5: 45658 | B5: Carrigan | C5: Carrigan | D5: 3500 | E5: Sales&Marketing Expenditures | F5: monthly | G5: =IFS($F5="bi-weekly",$A5+CEILING(('13-week CF Forecast'!$B$1-$A5)/14,1)*14+14*(COLUMN()-7),$F5="weekly",$A5+CEILING(('13-week CF Forecast'!$B$1-$A5)/7,1)*7+7*(COLUMN()-7),$F5="monthly",DATE(YEAR($A5),MONTH($A5)+CEILING(DATEDIF($A5,'13-week CF Forecast'!$B$1,"m")+1,1)+COLUMN()-7,DAY($A5)),$F5="quarterly",DATE(YEAR($A5),MONTH($A5)+3*CEILING((DATEDIF($A5,'13-week CF Forecast'!$B$1,"m")+1)/3,1)+(COLUMN()-7)*3,DAY($A5)),$F5="yearly",DATE(YEAR($A5)+CEILING((DATEDIF($A5,'13-week CF Forecast'!$B$1,"y")+1),1)+COLUMN()-7,MONTH($A5),DAY($A5)),TRUE,"") -> 45839 | H5: =IFS($F5="bi-weekly",$A5+CEILING(('13-week CF Forecast'!$B$1-$A5)/14,1)*14+14*(COLUMN()-7),$F5="weekly",$A5+CEILING(('13-week CF Forecast'!$B$1-$A5)/7,1)*7+7*(COLUMN()-7),$F5="monthly",DATE(YEAR($A5),MONTH($A5)+CEILING(DATEDIF($A5,'13-week CF Forecast'!$B$1,"m")+1,1)+COLUMN()-7,DAY($A5)),$F5="quarterly",DATE(YEAR($A5),MONTH($A5)+3*CEILING((DATEDIF($A5,'13-week CF Forecast'!$B$1,"m")+1)/3,1)+(COLUMN()-7)*3,DAY($A5)),$F5="yearly",DATE(YEAR($A5)+CEILING((DATEDIF($A5,'13-week CF Forecast'!$B$1,"y")+1),1)+COLUMN()-7,MONTH($A5),DAY($A5)),TRUE,"") -> 45870 | I5: =IFS($F5="bi-weekly",$A5+CEILING(('13-week CF Forecast'!$B$1-$A5)/14,1)*14+14*(COLUMN()-7),$F5="weekly",$A5+CEILING(('13-week CF Forecast'!$B$1-$A5)/7,1)*7+7*(COLUMN()-7),$F5="monthly",DATE(YEAR($A5),MONTH($A5)+CEILING(DATEDIF($A5,'13-week CF Forecast'!$B$1,"m")+1,1)+COLUMN()-7,DAY($A5)),$F5="quarterly",DATE(YEAR($A5),MONTH($A5)+3*CEILING((DATEDIF($A5,'13-week CF Forecast'!$B$1,"m")+1)/3,1)+(COLUMN()-7)*3,DAY($A5)),$F5="yearly",DATE(YEAR($A5)+CEILING((DATEDIF($A5,'13-week CF Forecast'!$B$1,"y")+1),1)+COLUMN()-7,MONTH($A5),DAY($A5)),TRUE,"") -> 45901 | J5: =IFS($F5="bi-weekly",$A5+CEILING(('13-week CF Forecast'!$B$1-$A5)/14,1)*14+14*(COLUMN()-7),$F5="weekly",$A5+CEILING(('13-week CF Forecast'!$B$1-$A5)/7,1)*7+7*(COLUMN()-7),$F5="monthly",DATE(YEAR($A5),MONTH($A5)+CEILING(DATEDIF($A5,'13-week CF Forecast'!$B$1,"m")+1,1)+COLUMN()-7,DAY($A5)),$F5="quarterly",DATE(YEAR($A5),MONTH($A5)+3*CEILING((DATEDIF($A5,'13-week CF Forecast'!$B$1,"m")+1)/3,1)+(COLUMN()-7)*3,DAY($A5)),$F5="yearly",DATE(YEAR($A5)+CEILING((DATEDIF($A5,'13-week CF Forecast'!$B$1,"y")+1),1)+COLUMN()-7,MONTH($A5),DAY($A5)),TRUE,"") -> 45931 | K5: =IFS($F5="bi-weekly",$A5+CEILING(('13-week CF Forecast'!$B$1-$A5)/14,1)*14+14*(COLUMN()-7),$F5="weekly",$A5+CEILING(('13-week CF Forecast'!$B$1-$A5)/7,1)*7+7*(COLUMN()-7),$F5="monthly",DATE(YEAR($A5),MONTH($A5)+CEILING(DATEDIF($A5,'13-week CF Forecast'!$B$1,"m")+1,1)+COLUMN()-7,DAY($A5)),$F5="quarterly",DATE(YEAR($A5),MONTH($A5)+3*CEILING((DATEDIF($A5,'13-week CF Forecast'!$B$1,"m")+1)/3,1)+(COLUMN()-7)*3,DAY($A5)),$F5="yearly",DATE(YEAR($A5)+CEILING((DATEDIF($A5,'13-week CF Forecast'!$B$1,"y")+1),1)+COLUMN()-7,MONTH($A5),DAY($A5)),TRUE,"") -> 45962 | L5: =IFS($F5="bi-weekly",$A5+CEILING(('13-week CF Forecast'!$B$1-$A5)/14,1)*14+14*(COLUMN()-7),$F5="weekly",$A5+CEILING(('13-week CF Forecast'!$B$1-$A5)/7,1)*7+7*(COLUMN()-7),$F5="monthly",DATE(YEAR($A5),MONTH($A5)+CEILING(DATEDIF($A5,'13-week CF Forecast'!$B$1,"m")+1,1)+COLUMN()-7,DAY($A5)),$F5="quarterly",DATE(YEAR($A5),MONTH($A5)+3*CEILING((DATEDIF($A5,'13-week CF Forecast'!$B$1,"m")+1)/3,1)+(COLUMN()-7)*3,DAY($A5)),$F5="yearly",DATE(YEAR($A5)+CEILING((DATEDIF($A5,'13-week CF Forecast'!$B$1,"y")+1),1)+COLUMN()-7,MONTH($A5),DAY($A5)),TRUE,"") -> 45992 | M5: =IFS($F5="bi-weekly",$A5+CEILING(('13-week CF Forecast'!$B$1-$A5)/14,1)*14+14*(COLUMN()-7),$F5="weekly",$A5+CEILING(('13-week CF Forecast'!$B$1-$A5)/7,1)*7+7*(COLUMN()-7),$F5="monthly",DATE(YEAR($A5),MONTH($A5)+CEILING(DATEDIF($A5,'13-week CF Forecast'!$B$1,"m")+1,1)+COLUMN()-7,DAY($A5)),$F5="quarterly",DATE(YEAR($A5),MONTH($A5)+3*CEILING((DATEDIF($A5,'13-week CF Forecast'!$B$1,"m")+1)/3,1)+(COLUMN()-7)*3,DAY($A5)),$F5="yearly",DATE(YEAR($A5)+CEILING((DATEDIF($A5,'13-week CF Forecast'!$B$1,"y")+1),1)+COLUMN()-7,MONTH($A5),DAY($A5)),TRUE,"") -> 46023 | N5: =IFS($F5="bi-weekly",$A5+CEILING(('13-week CF Forecast'!$B$1-$A5)/14,1)*14+14*(COLUMN()-7),$F5="weekly",$A5+CEILING(('13-week CF Forecast'!$B$1-$A5)/7,1)*7+7*(COLUMN()-7),$F5="monthly",DATE(YEAR($A5),MONTH($A5)+CEILING(DATEDIF($A5,'13-week CF Forecast'!$B$1,"m")+1,1)+COLUMN()-7,DAY($A5)),$F5="quarterly",DATE(YEAR($A5),MONTH($A5)+3*CEILING((DATEDIF($A5,'13-week CF Forecast'!$B$1,"m")+1)/3,1)+(COLUMN()-7)*3,DAY($A5)),$F5="yearly",DATE(YEAR($A5)+CEILING((DATEDIF($A5,'13-week CF Forecast'!$B$1,"y")+1),1)+COLUMN()-7,MONTH($A5),DAY($A5)),TRUE,"") -> 46054 | ... S5: =IFS($F5="bi-weekly",$A5+CEILING(('13-week CF Forecast'!$B$1-$A5)/14,1)*14+14*(COLUMN()-7),$F5="weekly",$A5+CEILING(('13-week CF Forecast'!$B$1-$A5)/7,1)*7+7*(COLUMN()-7),$F5="monthly",DATE(YEAR($A5),MONTH($A5)+CEILING(DATEDIF($A5,'13-week CF Forecast'!$B$1,"m")+1,1)+COLUMN()-7,DAY($A5)),$F5="quarterly",DATE(YEAR($A5),MONTH($A5)+3*CEILING((DATEDIF($A5,'13-week CF Forecast'!$B$1,"m")+1)/3,1)+(COLUMN()-7)*3,DAY($A5)),$F5="yearly",DATE(YEAR($A5)+CEILING((DATEDIF($A5,'13-week CF Forecast'!$B$1,"y")+1),1)+COLUMN()-7,MONTH($A5),DAY($A5)),TRUE,"") -> 46204 | T5: =IFERROR(ROWSDUMMYFUNCTION(UNNEST(PAIR2JSON('Recurring Transactions'!$A$1,'Recurring Transactions'!A5,'Recurring Transactions'!$B$1,'Recurring Transactions'!B5,'Recurring Transactions'!$C$1,'Recurring Transactions'!C5,'Recurring Transactions'!$D$1,'Recurring Transactions'!D5,'Recurring Transactions'!$E$1,'Recurring Transactions'!E5,'Recurring Transactions'!$F$1,'Recurring Transactions'!F5,"Payment schedule",VALUE(RANGE2JSON('Recurring Transactions'!F5,'Recurring Transactions'!G5:S5))))),"[{""First payment date"":""2025-01-01"",""Counterparty"":""Carrigan"",""Description"":""Carrigan"",""Amount"":""$3500"",""Category"":""Sales&Marketing Expenditures"",""Frequency"":""monthly"",""Payment schedule_0"":""2025-07-01""},{""First payment date"":""2025-01-01"",""Counterparty"":""C"&"arrigan"",""Description"":""Carrigan"",""Amount"":""$3500"",""Category"":""Sales&Marketing Expenditures"",""Frequency"":""monthly"",""Payment schedule_0"":""2025-08-01""},{""First payment date"":""2025-01-01"",""Counterparty"":""Carrigan"",""Description"":""Carrigan"",""Amount"":""$3500"",""C"&"ategory"":""Sales&Marketing Expenditures"",""Frequency"":""monthly"",""Payment schedule_0"":""2025-09-01""},{""First payment date"":""2025-01-01"",""Counterparty"":""Carrigan"",""Description"":""Carrigan"",""Amount"":""$3500"",""Category"":""Sales&Marketing Expenditures"",""Frequency"":"""&"monthly"",""Payment schedule_0"":""2025-10-01""},{""First payment date"":""2025-01-01"",""Counterparty"":""Carrigan"",""Description"":""Carrigan"",""Amount"":""$3500"",""Category"":""Sales&Marketing Expenditures"",""Frequency"":""monthly"",""Payment schedule_0"":""2025-11-01""},{""First p"&"ayment date"":""2025-01-01"",""Counterparty"":""Carrigan"",""Description"":""Carrigan"",""Amount"":""$3500"",""Category"":""Sales&Marketing Expenditures"",""Frequency"":""monthly"",""Payment schedule_0"":""2025-12-01""},{""First payment date"":""2025-01-01"",""Counterparty"":""Carrigan"","""&"Description"":""Carrigan"",""Amount"":""$3500"",""Category"":""Sales&Marketing Expenditures"",""Frequency"":""monthly"",""Payment schedule_0"":""2026-01-01""},{""First payment date"":""2025-01-01"",""Counterparty"":""Carrigan"",""Description"":""Carrigan"",""Amount"":""$3500"",""Category"":"""&"Sales&Marketing Expenditures"",""Frequency"":""monthly"",""Payment schedule_0"":""2026-02-01""},{""First payment date"":""2025-01-01"",""Counterparty"":""Carrigan"",""Description"":""Carrigan"",""Amount"":""$3500"",""Category"":""Sales&Marketing Expenditures"",""Frequency"":""monthly"","""&"Payment schedule_0"":""2026-03-01""},{""First payment date"":""2025-01-01"",""Counterparty"":""Carrigan"",""Description"":""Carrigan"",""Amount"":""$3500"",""Category"":""Sales&Marketing Expenditures"",""Frequency"":""monthly"",""Payment schedule_0"":""2026-04-01""},{""First payment dat"&"e"":""2025-01-01"",""Counterparty"":""Carrigan"",""Description"":""Carrigan"",""Amount"":""$3500"",""Category"":""Sales&Marketing Expenditures"",""Frequency"":""monthly"",""Payment schedule_0"":""2026-05-01""},{""First payment date"":""2025-01-01"",""Counterparty"":""Carrigan"",""Descriptio"&"n"":""Carrigan"",""Amount"":""$3500"",""Category"":""Sales&Marketing Expenditures"",""Frequency"":""monthly"",""Payment schedule_0"":""2026-06-01""},{""First payment date"":""2025-01-01"",""Counterparty"":""Carrigan"",""Description"":""Carrigan"",""Amount"":""$3500"",""Category"":""Sales&Mark"&"eting Expenditures"",""Frequency"":""monthly"",""Payment schedule_0"":""2026-07-01""}]") -> [{"First payment date":"2025-01-01","Counterparty":"Carrigan","Description":"Carrigan","Amount":"$3500","Category":"Sales&Marketing Expenditures","Frequency":"monthly","Payment schedule_0":"2025-07-01"},{"First payment date":"2025-01-01","Counterparty":"Carrigan","Description":"Carrigan","Amount":"$3500","Category":"Sales&Marketing Expenditures","Frequency":"monthly","Payment schedule_0":"2025-08-01"},{"First payment date":"2025-01-01","Counterparty":"Carrigan","Description":"Carrigan","Amount":"$3500","Category":"Sales&Marketing Expenditures","Frequency":"monthly","Payment schedule_0":"2025-09-01"},{"First payment date":"2025-01-01","Counterparty":"Carrigan","Description":"Carrigan","Amount":"$3500","Category":"Sales&Marketing Expenditures","Frequency":"monthly","Payment schedule_0":"2025-10-01"},{"First payment date":"2025-01-01","Counterparty":"Carrigan","Description":"Carrigan","Amount":"$3500","Category":"Sales&Marketing Expenditures","Frequency":"monthly","Payment schedule_0":"2025-11-01"},{"First payment date":"2025-01-01","Counterparty":"Carrigan","Description":"Carrigan","Amount":"$3500","Category":"Sales&Marketing Expenditures","Frequency":"monthly","Payment schedule_0":"2025-12-01"},{"First payment date":"2025-01-01","Counterparty":"Carrigan","Description":"Carrigan","Amount":"$3500","Category":"Sales&Marketing Expenditures","Frequency":"monthly","Payment schedule_0":"2026-01-01"},{"First payment date":"2025-01-01","Counterparty":"Carrigan","Description":"Carrigan","Amount":"$3500","Category":"Sales&Marketing Expenditures","Frequency":"monthly","Payment schedule_0":"2026-02-01"},{"First payment date":"2025-01-01","Counterparty":"Carrigan","Description":"Carrigan","Amount":"$3500","Category":"Sales&Marketing Expenditures","Frequency":"monthly","Payment schedule_0":"2026-03-01"},{"First payment date":"2025-01-01","Counterparty":"Carrigan","Description":"Carrigan","Amount":"$3500","Category":"Sales&Marketing Expenditures","Frequency":"monthly","Payment schedule_0":"2026-04-01"},{"First payment date":"2025-01-01","Counterparty":"Carrigan","Description":"Carrigan","Amount":"$3500","Category":"Sales&Marketing Expenditures","Frequency":"monthly","Payment schedule_0":"2026-05-01"},{"First payment date":"2025-01-01","Counterparty":"Carrigan","Description":"Carrigan","Amount":"$3500","Category":"Sales&Marketing Expenditures","Frequency":"monthly","Payment schedule_0":"2026-06-01"},{"First payment date":"2025-01-01","Counterparty":"Carrigan","Description":"Carrigan","Amount":"$3500","Category":"Sales&Marketing Expenditures","Frequency":"monthly","Payment schedule_0":"2026-07-01"}] | U5: Chase Inc
A6: 45658 | B6: Swade | C6: Swade | D6: 4000 | E6: Sales&Marketing Expenditures | F6: monthly | G6: =IFS($F6="bi-weekly",$A6+CEILING(('13-week CF Forecast'!$B$1-$A6)/14,1)*14+14*(COLUMN()-7),$F6="weekly",$A6+CEILING(('13-week CF Forecast'!$B$1-$A6)/7,1)*7+7*(COLUMN()-7),$F6="monthly",DATE(YEAR($A6),MONTH($A6)+CEILING(DATEDIF($A6,'13-week CF Forecast'!$B$1,"m")+1,1)+COLUMN()-7,DAY($A6)),$F6="quarterly",DATE(YEAR($A6),MONTH($A6)+3*CEILING((DATEDIF($A6,'13-week CF Forecast'!$B$1,"m")+1)/3,1)+(COLUMN()-7)*3,DAY($A6)),$F6="yearly",DATE(YEAR($A6)+CEILING((DATEDIF($A6,'13-week CF Forecast'!$B$1,"y")+1),1)+COLUMN()-7,MONTH($A6),DAY($A6)),TRUE,"") -> 45839 | H6: =IFS($F6="bi-weekly",$A6+CEILING(('13-week CF Forecast'!$B$1-$A6)/14,1)*14+14*(COLUMN()-7),$F6="weekly",$A6+CEILING(('13-week CF Forecast'!$B$1-$A6)/7,1)*7+7*(COLUMN()-7),$F6="monthly",DATE(YEAR($A6),MONTH($A6)+CEILING(DATEDIF($A6,'13-week CF Forecast'!$B$1,"m")+1,1)+COLUMN()-7,DAY($A6)),$F6="quarterly",DATE(YEAR($A6),MONTH($A6)+3*CEILING((DATEDIF($A6,'13-week CF Forecast'!$B$1,"m")+1)/3,1)+(COLUMN()-7)*3,DAY($A6)),$F6="yearly",DATE(YEAR($A6)+CEILING((DATEDIF($A6,'13-week CF Forecast'!$B$1,"y")+1),1)+COLUMN()-7,MONTH($A6),DAY($A6)),TRUE,"") -> 45870 | I6: =IFS($F6="bi-weekly",$A6+CEILING(('13-week CF Forecast'!$B$1-$A6)/14,1)*14+14*(COLUMN()-7),$F6="weekly",$A6+CEILING(('13-week CF Forecast'!$B$1-$A6)/7,1)*7+7*(COLUMN()-7),$F6="monthly",DATE(YEAR($A6),MONTH($A6)+CEILING(DATEDIF($A6,'13-week CF Forecast'!$B$1,"m")+1,1)+COLUMN()-7,DAY($A6)),$F6="quarterly",DATE(YEAR($A6),MONTH($A6)+3*CEILING((DATEDIF($A6,'13-week CF Forecast'!$B$1,"m")+1)/3,1)+(COLUMN()-7)*3,DAY($A6)),$F6="yearly",DATE(YEAR($A6)+CEILING((DATEDIF($A6,'13-week CF Forecast'!$B$1,"y")+1),1)+COLUMN()-7,MONTH($A6),DAY($A6)),TRUE,"") -> 45901 | J6: =IFS($F6="bi-weekly",$A6+CEILING(('13-week CF Forecast'!$B$1-$A6)/14,1)*14+14*(COLUMN()-7),$F6="weekly",$A6+CEILING(('13-week CF Forecast'!$B$1-$A6)/7,1)*7+7*(COLUMN()-7),$F6="monthly",DATE(YEAR($A6),MONTH($A6)+CEILING(DATEDIF($A6,'13-week CF Forecast'!$B$1,"m")+1,1)+COLUMN()-7,DAY($A6)),$F6="quarterly",DATE(YEAR($A6),MONTH($A6)+3*CEILING((DATEDIF($A6,'13-week CF Forecast'!$B$1,"m")+1)/3,1)+(COLUMN()-7)*3,DAY($A6)),$F6="yearly",DATE(YEAR($A6)+CEILING((DATEDIF($A6,'13-week CF Forecast'!$B$1,"y")+1),1)+COLUMN()-7,MONTH($A6),DAY($A6)),TRUE,"") -> 45931 | K6: =IFS($F6="bi-weekly",$A6+CEILING(('13-week CF Forecast'!$B$1-$A6)/14,1)*14+14*(COLUMN()-7),$F6="weekly",$A6+CEILING(('13-week CF Forecast'!$B$1-$A6)/7,1)*7+7*(COLUMN()-7),$F6="monthly",DATE(YEAR($A6),MONTH($A6)+CEILING(DATEDIF($A6,'13-week CF Forecast'!$B$1,"m")+1,1)+COLUMN()-7,DAY($A6)),$F6="quarterly",DATE(YEAR($A6),MONTH($A6)+3*CEILING((DATEDIF($A6,'13-week CF Forecast'!$B$1,"m")+1)/3,1)+(COLUMN()-7)*3,DAY($A6)),$F6="yearly",DATE(YEAR($A6)+CEILING((DATEDIF($A6,'13-week CF Forecast'!$B$1,"y")+1),1)+COLUMN()-7,MONTH($A6),DAY($A6)),TRUE,"") -> 45962 | L6: =IFS($F6="bi-weekly",$A6+CEILING(('13-week CF Forecast'!$B$1-$A6)/14,1)*14+14*(COLUMN()-7),$F6="weekly",$A6+CEILING(('13-week CF Forecast'!$B$1-$A6)/7,1)*7+7*(COLUMN()-7),$F6="monthly",DATE(YEAR($A6),MONTH($A6)+CEILING(DATEDIF($A6,'13-week CF Forecast'!$B$1,"m")+1,1)+COLUMN()-7,DAY($A6)),$F6="quarterly",DATE(YEAR($A6),MONTH($A6)+3*CEILING((DATEDIF($A6,'13-week CF Forecast'!$B$1,"m")+1)/3,1)+(COLUMN()-7)*3,DAY($A6)),$F6="yearly",DATE(YEAR($A6)+CEILING((DATEDIF($A6,'13-week CF Forecast'!$B$1,"y")+1),1)+COLUMN()-7,MONTH($A6),DAY($A6)),TRUE,"") -> 45992 | M6: =IFS($F6="bi-weekly",$A6+CEILING(('13-week CF Forecast'!$B$1-$A6)/14,1)*14+14*(COLUMN()-7),$F6="weekly",$A6+CEILING(('13-week CF Forecast'!$B$1-$A6)/7,1)*7+7*(COLUMN()-7),$F6="monthly",DATE(YEAR($A6),MONTH($A6)+CEILING(DATEDIF($A6,'13-week CF Forecast'!$B$1,"m")+1,1)+COLUMN()-7,DAY($A6)),$F6="quarterly",DATE(YEAR($A6),MONTH($A6)+3*CEILING((DATEDIF($A6,'13-week CF Forecast'!$B$1,"m")+1)/3,1)+(COLUMN()-7)*3,DAY($A6)),$F6="yearly",DATE(YEAR($A6)+CEILING((DATEDIF($A6,'13-week CF Forecast'!$B$1,"y")+1),1)+COLUMN()-7,MONTH($A6),DAY($A6)),TRUE,"") -> 46023 | N6: =IFS($F6="bi-weekly",$A6+CEILING(('13-week CF Forecast'!$B$1-$A6)/14,1)*14+14*(COLUMN()-7),$F6="weekly",$A6+CEILING(('13-week CF Forecast'!$B$1-$A6)/7,1)*7+7*(COLUMN()-7),$F6="monthly",DATE(YEAR($A6),MONTH($A6)+CEILING(DATEDIF($A6,'13-week CF Forecast'!$B$1,"m")+1,1)+COLUMN()-7,DAY($A6)),$F6="quarterly",DATE(YEAR($A6),MONTH($A6)+3*CEILING((DATEDIF($A6,'13-week CF Forecast'!$B$1,"m")+1)/3,1)+(COLUMN()-7)*3,DAY($A6)),$F6="yearly",DATE(YEAR($A6)+CEILING((DATEDIF($A6,'13-week CF Forecast'!$B$1,"y")+1),1)+COLUMN()-7,MONTH($A6),DAY($A6)),TRUE,"") -> 46054 | ... S6: =IFS($F6="bi-weekly",$A6+CEILING(('13-week CF Forecast'!$B$1-$A6)/14,1)*14+14*(COLUMN()-7),$F6="weekly",$A6+CEILING(('13-week CF Forecast'!$B$1-$A6)/7,1)*7+7*(COLUMN()-7),$F6="monthly",DATE(YEAR($A6),MONTH($A6)+CEILING(DATEDIF($A6,'13-week CF Forecast'!$B$1,"m")+1,1)+COLUMN()-7,DAY($A6)),$F6="quarterly",DATE(YEAR($A6),MONTH($A6)+3*CEILING((DATEDIF($A6,'13-week CF Forecast'!$B$1,"m")+1)/3,1)+(COLUMN()-7)*3,DAY($A6)),$F6="yearly",DATE(YEAR($A6)+CEILING((DATEDIF($A6,'13-week CF Forecast'!$B$1,"y")+1),1)+COLUMN()-7,MONTH($A6),DAY($A6)),TRUE,"") -> 46204 | T6: =IFERROR(ROWSDUMMYFUNCTION(UNNEST(PAIR2JSON('Recurring Transactions'!$A$1,'Recurring Transactions'!A6,'Recurring Transactions'!$B$1,'Recurring Transactions'!B6,'Recurring Transactions'!$C$1,'Recurring Transactions'!C6,'Recurring Transactions'!$D$1,'Recurring Transactions'!D6,'Recurring Transactions'!$E$1,'Recurring Transactions'!E6,'Recurring Transactions'!$F$1,'Recurring Transactions'!F6,"Payment schedule",VALUE(RANGE2JSON('Recurring Transactions'!F6,'Recurring Transactions'!G6:S6))))),"[{""First payment date"":""2025-01-01"",""Counterparty"":""Swade"",""Description"":""Swade"",""Amount"":""$4000"",""Category"":""Sales&Marketing Expenditures"",""Frequency"":""monthly"",""Payment schedule_0"":""2025-07-01""},{""First payment date"":""2025-01-01"",""Counterparty"":""Swade"","&"""Description"":""Swade"",""Amount"":""$4000"",""Category"":""Sales&Marketing Expenditures"",""Frequency"":""monthly"",""Payment schedule_0"":""2025-08-01""},{""First payment date"":""2025-01-01"",""Counterparty"":""Swade"",""Description"":""Swade"",""Amount"":""$4000"",""Category"":""Sales&Ma"&"rketing Expenditures"",""Frequency"":""monthly"",""Payment schedule_0"":""2025-09-01""},{""First payment date"":""2025-01-01"",""Counterparty"":""Swade"",""Description"":""Swade"",""Amount"":""$4000"",""Category"":""Sales&Marketing Expenditures"",""Frequency"":""monthly"",""Payment schedu"&"le_0"":""2025-10-01""},{""First payment date"":""2025-01-01"",""Counterparty"":""Swade"",""Description"":""Swade"",""Amount"":""$4000"",""Category"":""Sales&Marketing Expenditures"",""Frequency"":""monthly"",""Payment schedule_0"":""2025-11-01""},{""First payment date"":""2025-01-01"",""Cou"&"nterparty"":""Swade"",""Description"":""Swade"",""Amount"":""$4000"",""Category"":""Sales&Marketing Expenditures"",""Frequency"":""monthly"",""Payment schedule_0"":""2025-12-01""},{""First payment date"":""2025-01-01"",""Counterparty"":""Swade"",""Description"":""Swade"",""Amount"":""$4000"","""&"Category"":""Sales&Marketing Expenditures"",""Frequency"":""monthly"",""Payment schedule_0"":""2026-01-01""},{""First payment date"":""2025-01-01"",""Counterparty"":""Swade"",""Description"":""Swade"",""Amount"":""$4000"",""Category"":""Sales&Marketing Expenditures"",""Frequency"":""month"&"ly"",""Payment schedule_0"":""2026-02-01""},{""First payment date"":""2025-01-01"",""Counterparty"":""Swade"",""Description"":""Swade"",""Amount"":""$4000"",""Category"":""Sales&Marketing Expenditures"",""Frequency"":""monthly"",""Payment schedule_0"":""2026-03-01""},{""First payment date"&""":""2025-01-01"",""Counterparty"":""Swade"",""Description"":""Swade"",""Amount"":""$4000"",""Category"":""Sales&Marketing Expenditures"",""Frequency"":""monthly"",""Payment schedule_0"":""2026-04-01""},{""First payment date"":""2025-01-01"",""Counterparty"":""Swade"",""Description"":""Swade"""&",""Amount"":""$4000"",""Category"":""Sales&Marketing Expenditures"",""Frequency"":""monthly"",""Payment schedule_0"":""2026-05-01""},{""First payment date"":""2025-01-01"",""Counterparty"":""Swade"",""Description"":""Swade"",""Amount"":""$4000"",""Category"":""Sales&Marketing Expenditures"""&",""Frequency"":""monthly"",""Payment schedule_0"":""2026-06-01""},{""First payment date"":""2025-01-01"",""Counterparty"":""Swade"",""Description"":""Swade"",""Amount"":""$4000"",""Category"":""Sales&Marketing Expenditures"",""Frequency"":""monthly"",""Payment schedule_0"":""2026-07-01""}]") -> [{"First payment date":"2025-01-01","Counterparty":"Swade","Description":"Swade","Amount":"$4000","Category":"Sales&Marketing Expenditures","Frequency":"monthly","Payment schedule_0":"2025-07-01"},{"First payment date":"2025-01-01","Counterparty":"Swade","Description":"Swade","Amount":"$4000","Category":"Sales&Marketing Expenditures","Frequency":"monthly","Payment schedule_0":"2025-08-01"},{"First payment date":"2025-01-01","Counterparty":"Swade","Description":"Swade","Amount":"$4000","Category":"Sales&Marketing Expenditures","Frequency":"monthly","Payment schedule_0":"2025-09-01"},{"First payment date":"2025-01-01","Counterparty":"Swade","Description":"Swade","Amount":"$4000","Category":"Sales&Marketing Expenditures","Frequency":"monthly","Payment schedule_0":"2025-10-01"},{"First payment date":"2025-01-01","Counterparty":"Swade","Description":"Swade","Amount":"$4000","Category":"Sales&Marketing Expenditures","Frequency":"monthly","Payment schedule_0":"2025-11-01"},{"First payment date":"2025-01-01","Counterparty":"Swade","Description":"Swade","Amount":"$4000","Category":"Sales&Marketing Expenditures","Frequency":"monthly","Payment schedule_0":"2025-12-01"},{"First payment date":"2025-01-01","Counterparty":"Swade","Description":"Swade","Amount":"$4000","Category":"Sales&Marketing Expenditures","Frequency":"monthly","Payment schedule_0":"2026-01-01"},{"First payment date":"2025-01-01","Counterparty":"Swade","Description":"Swade","Amount":"$4000","Category":"Sales&Marketing Expenditures","Frequency":"monthly","Payment schedule_0":"2026-02-01"},{"First payment date":"2025-01-01","Counterparty":"Swade","Description":"Swade","Amount":"$4000","Category":"Sales&Marketing Expenditures","Frequency":"monthly","Payment schedule_0":"2026-03-01"},{"First payment date":"2025-01-01","Counterparty":"Swade","Description":"Swade","Amount":"$4000","Category":"Sales&Marketing Expenditures","Frequency":"monthly","Payment schedule_0":"2026-04-01"},{"First payment date":"2025-01-01","Counterparty":"Swade","Description":"Swade","Amount":"$4000","Category":"Sales&Marketing Expenditures","Frequency":"monthly","Payment schedule_0":"2026-05-01"},{"First payment date":"2025-01-01","Counterparty":"Swade","Description":"Swade","Amount":"$4000","Category":"Sales&Marketing Expenditures","Frequency":"monthly","Payment schedule_0":"2026-06-01"},{"First payment date":"2025-01-01","Counterparty":"Swade","Description":"Swade","Amount":"$4000","Category":"Sales&Marketing Expenditures","Frequency":"monthly","Payment schedule_0":"2026-07-01"}] | U6: Chase Inc
A7: 45658 | B7: Digicom | C7: Digicom | D7: 7000 | E7: Sales&Marketing Expenditures | F7: monthly | G7: =IFS($F7="bi-weekly",$A7+CEILING(('13-week CF Forecast'!$B$1-$A7)/14,1)*14+14*(COLUMN()-7),$F7="weekly",$A7+CEILING(('13-week CF Forecast'!$B$1-$A7)/7,1)*7+7*(COLUMN()-7),$F7="monthly",DATE(YEAR($A7),MONTH($A7)+CEILING(DATEDIF($A7,'13-week CF Forecast'!$B$1,"m")+1,1)+COLUMN()-7,DAY($A7)),$F7="quarterly",DATE(YEAR($A7),MONTH($A7)+3*CEILING((DATEDIF($A7,'13-week CF Forecast'!$B$1,"m")+1)/3,1)+(COLUMN()-7)*3,DAY($A7)),$F7="yearly",DATE(YEAR($A7)+CEILING((DATEDIF($A7,'13-week CF Forecast'!$B$1,"y")+1),1)+COLUMN()-7,MONTH($A7),DAY($A7)),TRUE,"") -> 45839 | H7: =IFS($F7="bi-weekly",$A7+CEILING(('13-week CF Forecast'!$B$1-$A7)/14,1)*14+14*(COLUMN()-7),$F7="weekly",$A7+CEILING(('13-week CF Forecast'!$B$1-$A7)/7,1)*7+7*(COLUMN()-7),$F7="monthly",DATE(YEAR($A7),MONTH($A7)+CEILING(DATEDIF($A7,'13-week CF Forecast'!$B$1,"m")+1,1)+COLUMN()-7,DAY($A7)),$F7="quarterly",DATE(YEAR($A7),MONTH($A7)+3*CEILING((DATEDIF($A7,'13-week CF Forecast'!$B$1,"m")+1)/3,1)+(COLUMN()-7)*3,DAY($A7)),$F7="yearly",DATE(YEAR($A7)+CEILING((DATEDIF($A7,'13-week CF Forecast'!$B$1,"y")+1),1)+COLUMN()-7,MONTH($A7),DAY($A7)),TRUE,"") -> 45870 | I7: =IFS($F7="bi-weekly",$A7+CEILING(('13-week CF Forecast'!$B$1-$A7)/14,1)*14+14*(COLUMN()-7),$F7="weekly",$A7+CEILING(('13-week CF Forecast'!$B$1-$A7)/7,1)*7+7*(COLUMN()-7),$F7="monthly",DATE(YEAR($A7),MONTH($A7)+CEILING(DATEDIF($A7,'13-week CF Forecast'!$B$1,"m")+1,1)+COLUMN()-7,DAY($A7)),$F7="quarterly",DATE(YEAR($A7),MONTH($A7)+3*CEILING((DATEDIF($A7,'13-week CF Forecast'!$B$1,"m")+1)/3,1)+(COLUMN()-7)*3,DAY($A7)),$F7="yearly",DATE(YEAR($A7)+CEILING((DATEDIF($A7,'13-week CF Forecast'!$B$1,"y")+1),1)+COLUMN()-7,MONTH($A7),DAY($A7)),TRUE,"") -> 45901 | J7: =IFS($F7="bi-weekly",$A7+CEILING(('13-week CF Forecast'!$B$1-$A7)/14,1)*14+14*(COLUMN()-7),$F7="weekly",$A7+CEILING(('13-week CF Forecast'!$B$1-$A7)/7,1)*7+7*(COLUMN()-7),$F7="monthly",DATE(YEAR($A7),MONTH($A7)+CEILING(DATEDIF($A7,'13-week CF Forecast'!$B$1,"m")+1,1)+COLUMN()-7,DAY($A7)),$F7="quarterly",DATE(YEAR($A7),MONTH($A7)+3*CEILING((DATEDIF($A7,'13-week CF Forecast'!$B$1,"m")+1)/3,1)+(COLUMN()-7)*3,DAY($A7)),$F7="yearly",DATE(YEAR($A7)+CEILING((DATEDIF($A7,'13-week CF Forecast'!$B$1,"y")+1),1)+COLUMN()-7,MONTH($A7),DAY($A7)),TRUE,"") -> 45931 | K7: =IFS($F7="bi-weekly",$A7+CEILING(('13-week CF Forecast'!$B$1-$A7)/14,1)*14+14*(COLUMN()-7),$F7="weekly",$A7+CEILING(('13-week CF Forecast'!$B$1-$A7)/7,1)*7+7*(COLUMN()-7),$F7="monthly",DATE(YEAR($A7),MONTH($A7)+CEILING(DATEDIF($A7,'13-week CF Forecast'!$B$1,"m")+1,1)+COLUMN()-7,DAY($A7)),$F7="quarterly",DATE(YEAR($A7),MONTH($A7)+3*CEILING((DATEDIF($A7,'13-week CF Forecast'!$B$1,"m")+1)/3,1)+(COLUMN()-7)*3,DAY($A7)),$F7="yearly",DATE(YEAR($A7)+CEILING((DATEDIF($A7,'13-week CF Forecast'!$B$1,"y")+1),1)+COLUMN()-7,MONTH($A7),DAY($A7)),TRUE,"") -> 45962 | L7: =IFS($F7="bi-weekly",$A7+CEILING(('13-week CF Forecast'!$B$1-$A7)/14,1)*14+14*(COLUMN()-7),$F7="weekly",$A7+CEILING(('13-week CF Forecast'!$B$1-$A7)/7,1)*7+7*(COLUMN()-7),$F7="monthly",DATE(YEAR($A7),MONTH($A7)+CEILING(DATEDIF($A7,'13-week CF Forecast'!$B$1,"m")+1,1)+COLUMN()-7,DAY($A7)),$F7="quarterly",DATE(YEAR($A7),MONTH($A7)+3*CEILING((DATEDIF($A7,'13-week CF Forecast'!$B$1,"m")+1)/3,1)+(COLUMN()-7)*3,DAY($A7)),$F7="yearly",DATE(YEAR($A7)+CEILING((DATEDIF($A7,'13-week CF Forecast'!$B$1,"y")+1),1)+COLUMN()-7,MONTH($A7),DAY($A7)),TRUE,"") -> 45992 | M7: =IFS($F7="bi-weekly",$A7+CEILING(('13-week CF Forecast'!$B$1-$A7)/14,1)*14+14*(COLUMN()-7),$F7="weekly",$A7+CEILING(('13-week CF Forecast'!$B$1-$A7)/7,1)*7+7*(COLUMN()-7),$F7="monthly",DATE(YEAR($A7),MONTH($A7)+CEILING(DATEDIF($A7,'13-week CF Forecast'!$B$1,"m")+1,1)+COLUMN()-7,DAY($A7)),$F7="quarterly",DATE(YEAR($A7),MONTH($A7)+3*CEILING((DATEDIF($A7,'13-week CF Forecast'!$B$1,"m")+1)/3,1)+(COLUMN()-7)*3,DAY($A7)),$F7="yearly",DATE(YEAR($A7)+CEILING((DATEDIF($A7,'13-week CF Forecast'!$B$1,"y")+1),1)+COLUMN()-7,MONTH($A7),DAY($A7)),TRUE,"") -> 46023 | N7: =IFS($F7="bi-weekly",$A7+CEILING(('13-week CF Forecast'!$B$1-$A7)/14,1)*14+14*(COLUMN()-7),$F7="weekly",$A7+CEILING(('13-week CF Forecast'!$B$1-$A7)/7,1)*7+7*(COLUMN()-7),$F7="monthly",DATE(YEAR($A7),MONTH($A7)+CEILING(DATEDIF($A7,'13-week CF Forecast'!$B$1,"m")+1,1)+COLUMN()-7,DAY($A7)),$F7="quarterly",DATE(YEAR($A7),MONTH($A7)+3*CEILING((DATEDIF($A7,'13-week CF Forecast'!$B$1,"m")+1)/3,1)+(COLUMN()-7)*3,DAY($A7)),$F7="yearly",DATE(YEAR($A7)+CEILING((DATEDIF($A7,'13-week CF Forecast'!$B$1,"y")+1),1)+COLUMN()-7,MONTH($A7),DAY($A7)),TRUE,"") -> 46054 | ... S7: =IFS($F7="bi-weekly",$A7+CEILING(('13-week CF Forecast'!$B$1-$A7)/14,1)*14+14*(COLUMN()-7),$F7="weekly",$A7+CEILING(('13-week CF Forecast'!$B$1-$A7)/7,1)*7+7*(COLUMN()-7),$F7="monthly",DATE(YEAR($A7),MONTH($A7)+CEILING(DATEDIF($A7,'13-week CF Forecast'!$B$1,"m")+1,1)+COLUMN()-7,DAY($A7)),$F7="quarterly",DATE(YEAR($A7),MONTH($A7)+3*CEILING((DATEDIF($A7,'13-week CF Forecast'!$B$1,"m")+1)/3,1)+(COLUMN()-7)*3,DAY($A7)),$F7="yearly",DATE(YEAR($A7)+CEILING((DATEDIF($A7,'13-week CF Forecast'!$B$1,"y")+1),1)+COLUMN()-7,MONTH($A7),DAY($A7)),TRUE,"") -> 46204 | T7: =IFERROR(ROWSDUMMYFUNCTION(UNNEST(PAIR2JSON('Recurring Transactions'!$A$1,'Recurring Transactions'!A7,'Recurring Transactions'!$B$1,'Recurring Transactions'!B7,'Recurring Transactions'!$C$1,'Recurring Transactions'!C7,'Recurring Transactions'!$D$1,'Recurring Transactions'!D7,'Recurring Transactions'!$E$1,'Recurring Transactions'!E7,'Recurring Transactions'!$F$1,'Recurring Transactions'!F7,"Payment schedule",VALUE(RANGE2JSON('Recurring Transactions'!F7,'Recurring Transactions'!G7:S7))))),"[{""First payment date"":""2025-01-01"",""Counterparty"":""Digicom"",""Description"":""Digicom"",""Amount"":""$7000"",""Category"":""Sales&Marketing Expenditures"",""Frequency"":""monthly"",""Payment schedule_0"":""2025-07-01""},{""First payment date"":""2025-01-01"",""Counterparty"":""Dig"&"icom"",""Description"":""Digicom"",""Amount"":""$7000"",""Category"":""Sales&Marketing Expenditures"",""Frequency"":""monthly"",""Payment schedule_0"":""2025-08-01""},{""First payment date"":""2025-01-01"",""Counterparty"":""Digicom"",""Description"":""Digicom"",""Amount"":""$7000"",""Categor"&"y"":""Sales&Marketing Expenditures"",""Frequency"":""monthly"",""Payment schedule_0"":""2025-09-01""},{""First payment date"":""2025-01-01"",""Counterparty"":""Digicom"",""Description"":""Digicom"",""Amount"":""$7000"",""Category"":""Sales&Marketing Expenditures"",""Frequency"":""monthly"""&",""Payment schedule_0"":""2025-10-01""},{""First payment date"":""2025-01-01"",""Counterparty"":""Digicom"",""Description"":""Digicom"",""Amount"":""$7000"",""Category"":""Sales&Marketing Expenditures"",""Frequency"":""monthly"",""Payment schedule_0"":""2025-11-01""},{""First payment dat"&"e"":""2025-01-01"",""Counterparty"":""Digicom"",""Description"":""Digicom"",""Amount"":""$7000"",""Category"":""Sales&Marketing Expenditures"",""Frequency"":""monthly"",""Payment schedule_0"":""2025-12-01""},{""First payment date"":""2025-01-01"",""Counterparty"":""Digicom"",""Description"":"&"""Digicom"",""Amount"":""$7000"",""Category"":""Sales&Marketing Expenditures"",""Frequency"":""monthly"",""Payment schedule_0"":""2026-01-01""},{""First payment date"":""2025-01-01"",""Counterparty"":""Digicom"",""Description"":""Digicom"",""Amount"":""$7000"",""Category"":""Sales&Marketing "&"Expenditures"",""Frequency"":""monthly"",""Payment schedule_0"":""2026-02-01""},{""First payment date"":""2025-01-01"",""Counterparty"":""Digicom"",""Description"":""Digicom"",""Amount"":""$7000"",""Category"":""Sales&Marketing Expenditures"",""Frequency"":""monthly"",""Payment schedule_0"&""":""2026-03-01""},{""First payment date"":""2025-01-01"",""Counterparty"":""Digicom"",""Description"":""Digicom"",""Amount"":""$7000"",""Category"":""Sales&Marketing Expenditures"",""Frequency"":""monthly"",""Payment schedule_0"":""2026-04-01""},{""First payment date"":""2025-01-01"",""Cou"&"nterparty"":""Digicom"",""Description"":""Digicom"",""Amount"":""$7000"",""Category"":""Sales&Marketing Expenditures"",""Frequency"":""monthly"",""Payment schedule_0"":""2026-05-01""},{""First payment date"":""2025-01-01"",""Counterparty"":""Digicom"",""Description"":""Digicom"",""Amount"":"""&"$7000"",""Category"":""Sales&Marketing Expenditures"",""Frequency"":""monthly"",""Payment schedule_0"":""2026-06-01""},{""First payment date"":""2025-01-01"",""Counterparty"":""Digicom"",""Description"":""Digicom"",""Amount"":""$7000"",""Category"":""Sales&Marketing Expenditures"",""Frequ"&"ency"":""monthly"",""Payment schedule_0"":""2026-07-01""}]") -> [{"First payment date":"2025-01-01","Counterparty":"Digicom","Description":"Digicom","Amount":"$7000","Category":"Sales&Marketing Expenditures","Frequency":"monthly","Payment schedule_0":"2025-07-01"},{"First payment date":"2025-01-01","Counterparty":"Digicom","Description":"Digicom","Amount":"$7000","Category":"Sales&Marketing Expenditures","Frequency":"monthly","Payment schedule_0":"2025-08-01"},{"First payment date":"2025-01-01","Counterparty":"Digicom","Description":"Digicom","Amount":"$7000","Category":"Sales&Marketing Expenditures","Frequency":"monthly","Payment schedule_0":"2025-09-01"},{"First payment date":"2025-01-01","Counterparty":"Digicom","Description":"Digicom","Amount":"$7000","Category":"Sales&Marketing Expenditures","Frequency":"monthly","Payment schedule_0":"2025-10-01"},{"First payment date":"2025-01-01","Counterparty":"Digicom","Description":"Digicom","Amount":"$7000","Category":"Sales&Marketing Expenditures","Frequency":"monthly","Payment schedule_0":"2025-11-01"},{"First payment date":"2025-01-01","Counterparty":"Digicom","Description":"Digicom","Amount":"$7000","Category":"Sales&Marketing Expenditures","Frequency":"monthly","Payment schedule_0":"2025-12-01"},{"First payment date":"2025-01-01","Counterparty":"Digicom","Description":"Digicom","Amount":"$7000","Category":"Sales&Marketing Expenditures","Frequency":"monthly","Payment schedule_0":"2026-01-01"},{"First payment date":"2025-01-01","Counterparty":"Digicom","Description":"Digicom","Amount":"$7000","Category":"Sales&Marketing Expenditures","Frequency":"monthly","Payment schedule_0":"2026-02-01"},{"First payment date":"2025-01-01","Counterparty":"Digicom","Description":"Digicom","Amount":"$7000","Category":"Sales&Marketing Expenditures","Frequency":"monthly","Payment schedule_0":"2026-03-01"},{"First payment date":"2025-01-01","Counterparty":"Digicom","Description":"Digicom","Amount":"$7000","Category":"Sales&Marketing Expenditures","Frequency":"monthly","Payment schedule_0":"2026-04-01"},{"First payment date":"2025-01-01","Counterparty":"Digicom","Description":"Digicom","Amount":"$7000","Category":"Sales&Marketing Expenditures","Frequency":"monthly","Payment schedule_0":"2026-05-01"},{"First payment date":"2025-01-01","Counterparty":"Digicom","Description":"Digicom","Amount":"$7000","Category":"Sales&Marketing Expenditures","Frequency":"monthly","Payment schedule_0":"2026-06-01"},{"First payment date":"2025-01-01","Counterparty":"Digicom","Description":"Digicom","Amount":"$7000","Category":"Sales&Marketing Expenditures","Frequency":"monthly","Payment schedule_0":"2026-07-01"}] | U7: Staychill
A8: 45658 | B8: Logical Position | C8: Logical Position | D8: 500 | E8: Sales&Marketing Expenditures | F8: monthly | G8: =IFS($F8="bi-weekly",$A8+CEILING(('13-week CF Forecast'!$B$1-$A8)/14,1)*14+14*(COLUMN()-7),$F8="weekly",$A8+CEILING(('13-week CF Forecast'!$B$1-$A8)/7,1)*7+7*(COLUMN()-7),$F8="monthly",DATE(YEAR($A8),MONTH($A8)+CEILING(DATEDIF($A8,'13-week CF Forecast'!$B$1,"m")+1,1)+COLUMN()-7,DAY($A8)),$F8="quarterly",DATE(YEAR($A8),MONTH($A8)+3*CEILING((DATEDIF($A8,'13-week CF Forecast'!$B$1,"m")+1)/3,1)+(COLUMN()-7)*3,DAY($A8)),$F8="yearly",DATE(YEAR($A8)+CEILING((DATEDIF($A8,'13-week CF Forecast'!$B$1,"y")+1),1)+COLUMN()-7,MONTH($A8),DAY($A8)),TRUE,"") -> 45839 | H8: =IFS($F8="bi-weekly",$A8+CEILING(('13-week CF Forecast'!$B$1-$A8)/14,1)*14+14*(COLUMN()-7),$F8="weekly",$A8+CEILING(('13-week CF Forecast'!$B$1-$A8)/7,1)*7+7*(COLUMN()-7),$F8="monthly",DATE(YEAR($A8),MONTH($A8)+CEILING(DATEDIF($A8,'13-week CF Forecast'!$B$1,"m")+1,1)+COLUMN()-7,DAY($A8)),$F8="quarterly",DATE(YEAR($A8),MONTH($A8)+3*CEILING((DATEDIF($A8,'13-week CF Forecast'!$B$1,"m")+1)/3,1)+(COLUMN()-7)*3,DAY($A8)),$F8="yearly",DATE(YEAR($A8)+CEILING((DATEDIF($A8,'13-week CF Forecast'!$B$1,"y")+1),1)+COLUMN()-7,MONTH($A8),DAY($A8)),TRUE,"") -> 45870 | I8: =IFS($F8="bi-weekly",$A8+CEILING(('13-week CF Forecast'!$B$1-$A8)/14,1)*14+14*(COLUMN()-7),$F8="weekly",$A8+CEILING(('13-week CF Forecast'!$B$1-$A8)/7,1)*7+7*(COLUMN()-7),$F8="monthly",DATE(YEAR($A8),MONTH($A8)+CEILING(DATEDIF($A8,'13-week CF Forecast'!$B$1,"m")+1,1)+COLUMN()-7,DAY($A8)),$F8="quarterly",DATE(YEAR($A8),MONTH($A8)+3*CEILING((DATEDIF($A8,'13-week CF Forecast'!$B$1,"m")+1)/3,1)+(COLUMN()-7)*3,DAY($A8)),$F8="yearly",DATE(YEAR($A8)+CEILING((DATEDIF($A8,'13-week CF Forecast'!$B$1,"y")+1),1)+COLUMN()-7,MONTH($A8),DAY($A8)),TRUE,"") -> 45901 | J8: =IFS($F8="bi-weekly",$A8+CEILING(('13-week CF Forecast'!$B$1-$A8)/14,1)*14+14*(COLUMN()-7),$F8="weekly",$A8+CEILING(('13-week CF Forecast'!$B$1-$A8)/7,1)*7+7*(COLUMN()-7),$F8="monthly",DATE(YEAR($A8),MONTH($A8)+CEILING(DATEDIF($A8,'13-week CF Forecast'!$B$1,"m")+1,1)+COLUMN()-7,DAY($A8)),$F8="quarterly",DATE(YEAR($A8),MONTH($A8)+3*CEILING((DATEDIF($A8,'13-week CF Forecast'!$B$1,"m")+1)/3,1)+(COLUMN()-7)*3,DAY($A8)),$F8="yearly",DATE(YEAR($A8)+CEILING((DATEDIF($A8,'13-week CF Forecast'!$B$1,"y")+1),1)+COLUMN()-7,MONTH($A8),DAY($A8)),TRUE,"") -> 45931 | K8: =IFS($F8="bi-weekly",$A8+CEILING(('13-week CF Forecast'!$B$1-$A8)/14,1)*14+14*(COLUMN()-7),$F8="weekly",$A8+CEILING(('13-week CF Forecast'!$B$1-$A8)/7,1)*7+7*(COLUMN()-7),$F8="monthly",DATE(YEAR($A8),MONTH($A8)+CEILING(DATEDIF($A8,'13-week CF Forecast'!$B$1,"m")+1,1)+COLUMN()-7,DAY($A8)),$F8="quarterly",DATE(YEAR($A8),MONTH($A8)+3*CEILING((DATEDIF($A8,'13-week CF Forecast'!$B$1,"m")+1)/3,1)+(COLUMN()-7)*3,DAY($A8)),$F8="yearly",DATE(YEAR($A8)+CEILING((DATEDIF($A8,'13-week CF Forecast'!$B$1,"y")+1),1)+COLUMN()-7,MONTH($A8),DAY($A8)),TRUE,"") -> 45962 | L8: =IFS($F8="bi-weekly",$A8+CEILING(('13-week CF Forecast'!$B$1-$A8)/14,1)*14+14*(COLUMN()-7),$F8="weekly",$A8+CEILING(('13-week CF Forecast'!$B$1-$A8)/7,1)*7+7*(COLUMN()-7),$F8="monthly",DATE(YEAR($A8),MONTH($A8)+CEILING(DATEDIF($A8,'13-week CF Forecast'!$B$1,"m")+1,1)+COLUMN()-7,DAY($A8)),$F8="quarterly",DATE(YEAR($A8),MONTH($A8)+3*CEILING((DATEDIF($A8,'13-week CF Forecast'!$B$1,"m")+1)/3,1)+(COLUMN()-7)*3,DAY($A8)),$F8="yearly",DATE(YEAR($A8)+CEILING((DATEDIF($A8,'13-week CF Forecast'!$B$1,"y")+1),1)+COLUMN()-7,MONTH($A8),DAY($A8)),TRUE,"") -> 45992 | M8: =IFS($F8="bi-weekly",$A8+CEILING(('13-week CF Forecast'!$B$1-$A8)/14,1)*14+14*(COLUMN()-7),$F8="weekly",$A8+CEILING(('13-week CF Forecast'!$B$1-$A8)/7,1)*7+7*(COLUMN()-7),$F8="monthly",DATE(YEAR($A8),MONTH($A8)+CEILING(DATEDIF($A8,'13-week CF Forecast'!$B$1,"m")+1,1)+COLUMN()-7,DAY($A8)),$F8="quarterly",DATE(YEAR($A8),MONTH($A8)+3*CEILING((DATEDIF($A8,'13-week CF Forecast'!$B$1,"m")+1)/3,1)+(COLUMN()-7)*3,DAY($A8)),$F8="yearly",DATE(YEAR($A8)+CEILING((DATEDIF($A8,'13-week CF Forecast'!$B$1,"y")+1),1)+COLUMN()-7,MONTH($A8),DAY($A8)),TRUE,"") -> 46023 | N8: =IFS($F8="bi-weekly",$A8+CEILING(('13-week CF Forecast'!$B$1-$A8)/14,1)*14+14*(COLUMN()-7),$F8="weekly",$A8+CEILING(('13-week CF Forecast'!$B$1-$A8)/7,1)*7+7*(COLUMN()-7),$F8="monthly",DATE(YEAR($A8),MONTH($A8)+CEILING(DATEDIF($A8,'13-week CF Forecast'!$B$1,"m")+1,1)+COLUMN()-7,DAY($A8)),$F8="quarterly",DATE(YEAR($A8),MONTH($A8)+3*CEILING((DATEDIF($A8,'13-week CF Forecast'!$B$1,"m")+1)/3,1)+(COLUMN()-7)*3,DAY($A8)),$F8="yearly",DATE(YEAR($A8)+CEILING((DATEDIF($A8,'13-week CF Forecast'!$B$1,"y")+1),1)+COLUMN()-7,MONTH($A8),DAY($A8)),TRUE,"") -> 46054 | ... S8: =IFS($F8="bi-weekly",$A8+CEILING(('13-week CF Forecast'!$B$1-$A8)/14,1)*14+14*(COLUMN()-7),$F8="weekly",$A8+CEILING(('13-week CF Forecast'!$B$1-$A8)/7,1)*7+7*(COLUMN()-7),$F8="monthly",DATE(YEAR($A8),MONTH($A8)+CEILING(DATEDIF($A8,'13-week CF Forecast'!$B$1,"m")+1,1)+COLUMN()-7,DAY($A8)),$F8="quarterly",DATE(YEAR($A8),MONTH($A8)+3*CEILING((DATEDIF($A8,'13-week CF Forecast'!$B$1,"m")+1)/3,1)+(COLUMN()-7)*3,DAY($A8)),$F8="yearly",DATE(YEAR($A8)+CEILING((DATEDIF($A8,'13-week CF Forecast'!$B$1,"y")+1),1)+COLUMN()-7,MONTH($A8),DAY($A8)),TRUE,"") -> 46204 | T8: =IFERROR(ROWSDUMMYFUNCTION(UNNEST(PAIR2JSON('Recurring Transactions'!$A$1,'Recurring Transactions'!A8,'Recurring Transactions'!$B$1,'Recurring Transactions'!B8,'Recurring Transactions'!$C$1,'Recurring Transactions'!C8,'Recurring Transactions'!$D$1,'Recurring Transactions'!D8,'Recurring Transactions'!$E$1,'Recurring Transactions'!E8,'Recurring Transactions'!$F$1,'Recurring Transactions'!F8,"Payment schedule",VALUE(RANGE2JSON('Recurring Transactions'!F8,'Recurring Transactions'!G8:S8))))),"[{""First payment date"":""2025-01-01"",""Counterparty"":""Logical Position"",""Description"":""Logical Position"",""Amount"":""$500"",""Category"":""Sales&Marketing Expenditures"",""Frequency"":""monthly"",""Payment schedule_0"":""2025-07-01""},{""First payment date"":""2025-01-01"",""C"&"ounterparty"":""Logical Position"",""Description"":""Logical Position"",""Amount"":""$500"",""Category"":""Sales&Marketing Expenditures"",""Frequency"":""monthly"",""Payment schedule_0"":""2025-08-01""},{""First payment date"":""2025-01-01"",""Counterparty"":""Logical Position"",""Descr"&"iption"":""Logical Position"",""Amount"":""$500"",""Category"":""Sales&Marketing Expenditures"",""Frequency"":""monthly"",""Payment schedule_0"":""2025-09-01""},{""First payment date"":""2025-01-01"",""Counterparty"":""Logical Position"",""Description"":""Logical Position"",""Amount"":""$"&"500"",""Category"":""Sales&Marketing Expenditures"",""Frequency"":""monthly"",""Payment schedule_0"":""2025-10-01""},{""First payment date"":""2025-01-01"",""Counterparty"":""Logical Position"",""Description"":""Logical Position"",""Amount"":""$500"",""Category"":""Sales&Marketing Expen"&"ditures"",""Frequency"":""monthly"",""Payment schedule_0"":""2025-11-01""},{""First payment date"":""2025-01-01"",""Counterparty"":""Logical Position"",""Description"":""Logical Position"",""Amount"":""$500"",""Category"":""Sales&Marketing Expenditures"",""Frequency"":""monthly"",""Paymen"&"t schedule_0"":""2025-12-01""},{""First payment date"":""2025-01-01"",""Counterparty"":""Logical Position"",""Description"":""Logical Position"",""Amount"":""$500"",""Category"":""Sales&Marketing Expenditures"",""Frequency"":""monthly"",""Payment schedule_0"":""2026-01-01""},{""First pa"&"yment date"":""2025-01-01"",""Counterparty"":""Logical Position"",""Description"":""Logical Position"",""Amount"":""$500"",""Category"":""Sales&Marketing Expenditures"",""Frequency"":""monthly"",""Payment schedule_0"":""2026-02-01""},{""First payment date"":""2025-01-01"",""Counterparty"&""":""Logical Position"",""Description"":""Logical Position"",""Amount"":""$500"",""Category"":""Sales&Marketing Expenditures"",""Frequency"":""monthly"",""Payment schedule_0"":""2026-03-01""},{""First payment date"":""2025-01-01"",""Counterparty"":""Logical Position"",""Description"":""Lo"&"gical Position"",""Amount"":""$500"",""Category"":""Sales&Marketing Expenditures"",""Frequency"":""monthly"",""Payment schedule_0"":""2026-04-01""},{""First payment date"":""2025-01-01"",""Counterparty"":""Logical Position"",""Description"":""Logical Position"",""Amount"":""$500"",""Categ"&"ory"":""Sales&Marketing Expenditures"",""Frequency"":""monthly"",""Payment schedule_0"":""2026-05-01""},{""First payment date"":""2025-01-01"",""Counterparty"":""Logical Position"",""Description"":""Logical Position"",""Amount"":""$500"",""Category"":""Sales&Marketing Expenditures"",""F"&"requency"":""monthly"",""Payment schedule_0"":""2026-06-01""},{""First payment date"":""2025-01-01"",""Counterparty"":""Logical Position"",""Description"":""Logical Position"",""Amount"":""$500"",""Category"":""Sales&Marketing Expenditures"",""Frequency"":""monthly"",""Payment schedule_"&"0"":""2026-07-01""}]") -> [{"First payment date":"2025-01-01","Counterparty":"Logical Position","Description":"Logical Position","Amount":"$500","Category":"Sales&Marketing Expenditures","Frequency":"monthly","Payment schedule_0":"2025-07-01"},{"First payment date":"2025-01-01","Counterparty":"Logical Position","Description":"Logical Position","Amount":"$500","Category":"Sales&Marketing Expenditures","Frequency":"monthly","Payment schedule_0":"2025-08-01"},{"First payment date":"2025-01-01","Counterparty":"Logical Position","Description":"Logical Position","Amount":"$500","Category":"Sales&Marketing Expenditures","Frequency":"monthly","Payment schedule_0":"2025-09-01"},{"First payment date":"2025-01-01","Counterparty":"Logical Position","Description":"Logical Position","Amount":"$500","Category":"Sales&Marketing Expenditures","Frequency":"monthly","Payment schedule_0":"2025-10-01"},{"First payment date":"2025-01-01","Counterparty":"Logical Position","Description":"Logical Position","Amount":"$500","Category":"Sales&Marketing Expenditures","Frequency":"monthly","Payment schedule_0":"2025-11-01"},{"First payment date":"2025-01-01","Counterparty":"Logical Position","Description":"Logical Position","Amount":"$500","Category":"Sales&Marketing Expenditures","Frequency":"monthly","Payment schedule_0":"2025-12-01"},{"First payment date":"2025-01-01","Counterparty":"Logical Position","Description":"Logical Position","Amount":"$500","Category":"Sales&Marketing Expenditures","Frequency":"monthly","Payment schedule_0":"2026-01-01"},{"First payment date":"2025-01-01","Counterparty":"Logical Position","Description":"Logical Position","Amount":"$500","Category":"Sales&Marketing Expenditures","Frequency":"monthly","Payment schedule_0":"2026-02-01"},{"First payment date":"2025-01-01","Counterparty":"Logical Position","Description":"Logical Position","Amount":"$500","Category":"Sales&Marketing Expenditures","Frequency":"monthly","Payment schedule_0":"2026-03-01"},{"First payment date":"2025-01-01","Counterparty":"Logical Position","Description":"Logical Position","Amount":"$500","Category":"Sales&Marketing Expenditures","Frequency":"monthly","Payment schedule_0":"2026-04-01"},{"First payment date":"2025-01-01","Counterparty":"Logical Position","Description":"Logical Position","Amount":"$500","Category":"Sales&Marketing Expenditures","Frequency":"monthly","Payment schedule_0":"2026-05-01"},{"First payment date":"2025-01-01","Counterparty":"Logical Position","Description":"Logical Position","Amount":"$500","Category":"Sales&Marketing Expenditures","Frequency":"monthly","Payment schedule_0":"2026-06-01"},{"First payment date":"2025-01-01","Counterparty":"Logical Position","Description":"Logical Position","Amount":"$500","Category":"Sales&Marketing Expenditures","Frequency":"monthly","Payment schedule_0":"2026-07-01"}] | U8: Chase Inc
A9: 45658 | B9: Shopify | C9: Shopify | D9: 2000 | E9: Software | F9: monthly | G9: =IFS($F9="bi-weekly",$A9+CEILING(('13-week CF Forecast'!$B$1-$A9)/14,1)*14+14*(COLUMN()-7),$F9="weekly",$A9+CEILING(('13-week CF Forecast'!$B$1-$A9)/7,1)*7+7*(COLUMN()-7),$F9="monthly",DATE(YEAR($A9),MONTH($A9)+CEILING(DATEDIF($A9,'13-week CF Forecast'!$B$1,"m")+1,1)+COLUMN()-7,DAY($A9)),$F9="quarterly",DATE(YEAR($A9),MONTH($A9)+3*CEILING((DATEDIF($A9,'13-week CF Forecast'!$B$1,"m")+1)/3,1)+(COLUMN()-7)*3,DAY($A9)),$F9="yearly",DATE(YEAR($A9)+CEILING((DATEDIF($A9,'13-week CF Forecast'!$B$1,"y")+1),1)+COLUMN()-7,MONTH($A9),DAY($A9)),TRUE,"") -> 45839 | H9: =IFS($F9="bi-weekly",$A9+CEILING(('13-week CF Forecast'!$B$1-$A9)/14,1)*14+14*(COLUMN()-7),$F9="weekly",$A9+CEILING(('13-week CF Forecast'!$B$1-$A9)/7,1)*7+7*(COLUMN()-7),$F9="monthly",DATE(YEAR($A9),MONTH($A9)+CEILING(DATEDIF($A9,'13-week CF Forecast'!$B$1,"m")+1,1)+COLUMN()-7,DAY($A9)),$F9="quarterly",DATE(YEAR($A9),MONTH($A9)+3*CEILING((DATEDIF($A9,'13-week CF Forecast'!$B$1,"m")+1)/3,1)+(COLUMN()-7)*3,DAY($A9)),$F9="yearly",DATE(YEAR($A9)+CEILING((DATEDIF($A9,'13-week CF Forecast'!$B$1,"y")+1),1)+COLUMN()-7,MONTH($A9),DAY($A9)),TRUE,"") -> 45870 | I9: =IFS($F9="bi-weekly",$A9+CEILING(('13-week CF Forecast'!$B$1-$A9)/14,1)*14+14*(COLUMN()-7),$F9="weekly",$A9+CEILING(('13-week CF Forecast'!$B$1-$A9)/7,1)*7+7*(COLUMN()-7),$F9="monthly",DATE(YEAR($A9),MONTH($A9)+CEILING(DATEDIF($A9,'13-week CF Forecast'!$B$1,"m")+1,1)+COLUMN()-7,DAY($A9)),$F9="quarterly",DATE(YEAR($A9),MONTH($A9)+3*CEILING((DATEDIF($A9,'13-week CF Forecast'!$B$1,"m")+1)/3,1)+(COLUMN()-7)*3,DAY($A9)),$F9="yearly",DATE(YEAR($A9)+CEILING((DATEDIF($A9,'13-week CF Forecast'!$B$1,"y")+1),1)+COLUMN()-7,MONTH($A9),DAY($A9)),TRUE,"") -> 45901 | J9: =IFS($F9="bi-weekly",$A9+CEILING(('13-week CF Forecast'!$B$1-$A9)/14,1)*14+14*(COLUMN()-7),$F9="weekly",$A9+CEILING(('13-week CF Forecast'!$B$1-$A9)/7,1)*7+7*(COLUMN()-7),$F9="monthly",DATE(YEAR($A9),MONTH($A9)+CEILING(DATEDIF($A9,'13-week CF Forecast'!$B$1,"m")+1,1)+COLUMN()-7,DAY($A9)),$F9="quarterly",DATE(YEAR($A9),MONTH($A9)+3*CEILING((DATEDIF($A9,'13-week CF Forecast'!$B$1,"m")+1)/3,1)+(COLUMN()-7)*3,DAY($A9)),$F9="yearly",DATE(YEAR($A9)+CEILING((DATEDIF($A9,'13-week CF Forecast'!$B$1,"y")+1),1)+COLUMN()-7,MONTH($A9),DAY($A9)),TRUE,"") -> 45931 | K9: =IFS($F9="bi-weekly",$A9+CEILING(('13-week CF Forecast'!$B$1-$A9)/14,1)*14+14*(COLUMN()-7),$F9="weekly",$A9+CEILING(('13-week CF Forecast'!$B$1-$A9)/7,1)*7+7*(COLUMN()-7),$F9="monthly",DATE(YEAR($A9),MONTH($A9)+CEILING(DATEDIF($A9,'13-week CF Forecast'!$B$1,"m")+1,1)+COLUMN()-7,DAY($A9)),$F9="quarterly",DATE(YEAR($A9),MONTH($A9)+3*CEILING((DATEDIF($A9,'13-week CF Forecast'!$B$1,"m")+1)/3,1)+(COLUMN()-7)*3,DAY($A9)),$F9="yearly",DATE(YEAR($A9)+CEILING((DATEDIF($A9,'13-week CF Forecast'!$B$1,"y")+1),1)+COLUMN()-7,MONTH($A9),DAY($A9)),TRUE,"") -> 45962 | L9: =IFS($F9="bi-weekly",$A9+CEILING(('13-week CF Forecast'!$B$1-$A9)/14,1)*14+14*(COLUMN()-7),$F9="weekly",$A9+CEILING(('13-week CF Forecast'!$B$1-$A9)/7,1)*7+7*(COLUMN()-7),$F9="monthly",DATE(YEAR($A9),MONTH($A9)+CEILING(DATEDIF($A9,'13-week CF Forecast'!$B$1,"m")+1,1)+COLUMN()-7,DAY($A9)),$F9="quarterly",DATE(YEAR($A9),MONTH($A9)+3*CEILING((DATEDIF($A9,'13-week CF Forecast'!$B$1,"m")+1)/3,1)+(COLUMN()-7)*3,DAY($A9)),$F9="yearly",DATE(YEAR($A9)+CEILING((DATEDIF($A9,'13-week CF Forecast'!$B$1,"y")+1),1)+COLUMN()-7,MONTH($A9),DAY($A9)),TRUE,"") -> 45992 | M9: =IFS($F9="bi-weekly",$A9+CEILING(('13-week CF Forecast'!$B$1-$A9)/14,1)*14+14*(COLUMN()-7),$F9="weekly",$A9+CEILING(('13-week CF Forecast'!$B$1-$A9)/7,1)*7+7*(COLUMN()-7),$F9="monthly",DATE(YEAR($A9),MONTH($A9)+CEILING(DATEDIF($A9,'13-week CF Forecast'!$B$1,"m")+1,1)+COLUMN()-7,DAY($A9)),$F9="quarterly",DATE(YEAR($A9),MONTH($A9)+3*CEILING((DATEDIF($A9,'13-week CF Forecast'!$B$1,"m")+1)/3,1)+(COLUMN()-7)*3,DAY($A9)),$F9="yearly",DATE(YEAR($A9)+CEILING((DATEDIF($A9,'13-week CF Forecast'!$B$1,"y")+1),1)+COLUMN()-7,MONTH($A9),DAY($A9)),TRUE,"") -> 46023 | N9: =IFS($F9="bi-weekly",$A9+CEILING(('13-week CF Forecast'!$B$1-$A9)/14,1)*14+14*(COLUMN()-7),$F9="weekly",$A9+CEILING(('13-week CF Forecast'!$B$1-$A9)/7,1)*7+7*(COLUMN()-7),$F9="monthly",DATE(YEAR($A9),MONTH($A9)+CEILING(DATEDIF($A9,'13-week CF Forecast'!$B$1,"m")+1,1)+COLUMN()-7,DAY($A9)),$F9="quarterly",DATE(YEAR($A9),MONTH($A9)+3*CEILING((DATEDIF($A9,'13-week CF Forecast'!$B$1,"m")+1)/3,1)+(COLUMN()-7)*3,DAY($A9)),$F9="yearly",DATE(YEAR($A9)+CEILING((DATEDIF($A9,'13-week CF Forecast'!$B$1,"y")+1),1)+COLUMN()-7,MONTH($A9),DAY($A9)),TRUE,"") -> 46054 | ... S9: =IFS($F9="bi-weekly",$A9+CEILING(('13-week CF Forecast'!$B$1-$A9)/14,1)*14+14*(COLUMN()-7),$F9="weekly",$A9+CEILING(('13-week CF Forecast'!$B$1-$A9)/7,1)*7+7*(COLUMN()-7),$F9="monthly",DATE(YEAR($A9),MONTH($A9)+CEILING(DATEDIF($A9,'13-week CF Forecast'!$B$1,"m")+1,1)+COLUMN()-7,DAY($A9)),$F9="quarterly",DATE(YEAR($A9),MONTH($A9)+3*CEILING((DATEDIF($A9,'13-week CF Forecast'!$B$1,"m")+1)/3,1)+(COLUMN()-7)*3,DAY($A9)),$F9="yearly",DATE(YEAR($A9)+CEILING((DATEDIF($A9,'13-week CF Forecast'!$B$1,"y")+1),1)+COLUMN()-7,MONTH($A9),DAY($A9)),TRUE,"") -> 46204 | T9: =IFERROR(ROWSDUMMYFUNCTION(UNNEST(PAIR2JSON('Recurring Transactions'!$A$1,'Recurring Transactions'!A9,'Recurring Transactions'!$B$1,'Recurring Transactions'!B9,'Recurring Transactions'!$C$1,'Recurring Transactions'!C9,'Recurring Transactions'!$D$1,'Recurring Transactions'!D9,'Recurring Transactions'!$E$1,'Recurring Transactions'!E9,'Recurring Transactions'!$F$1,'Recurring Transactions'!F9,"Payment schedule",VALUE(RANGE2JSON('Recurring Transactions'!F9,'Recurring Transactions'!G9:S9))))),"[{""First payment date"":""2025-01-01"",""Counterparty"":""Shopify"",""Description"":""Shopify"",""Amount"":""$2000"",""Category"":""Software"",""Frequency"":""monthly"",""Payment schedule_0"":""2025-07-01""},{""First payment date"":""2025-01-01"",""Counterparty"":""Shopify"",""Description"":"&"""Shopify"",""Amount"":""$2000"",""Category"":""Software"",""Frequency"":""monthly"",""Payment schedule_0"":""2025-08-01""},{""First payment date"":""2025-01-01"",""Counterparty"":""Shopify"",""Description"":""Shopify"",""Amount"":""$2000"",""Category"":""Software"",""Frequency"":""monthly"",""Pay"&"ment schedule_0"":""2025-09-01""},{""First payment date"":""2025-01-01"",""Counterparty"":""Shopify"",""Description"":""Shopify"",""Amount"":""$2000"",""Category"":""Software"",""Frequency"":""monthly"",""Payment schedule_0"":""2025-10-01""},{""First payment date"":""2025-01-01"",""Counterp"&"arty"":""Shopify"",""Description"":""Shopify"",""Amount"":""$2000"",""Category"":""Software"",""Frequency"":""monthly"",""Payment schedule_0"":""2025-11-01""},{""First payment date"":""2025-01-01"",""Counterparty"":""Shopify"",""Description"":""Shopify"",""Amount"":""$2000"",""Category"":""Softwa"&"re"",""Frequency"":""monthly"",""Payment schedule_0"":""2025-12-01""},{""First payment date"":""2025-01-01"",""Counterparty"":""Shopify"",""Description"":""Shopify"",""Amount"":""$2000"",""Category"":""Software"",""Frequency"":""monthly"",""Payment schedule_0"":""2026-01-01""},{""First paymen"&"t date"":""2025-01-01"",""Counterparty"":""Shopify"",""Description"":""Shopify"",""Amount"":""$2000"",""Category"":""Software"",""Frequency"":""monthly"",""Payment schedule_0"":""2026-02-01""},{""First payment date"":""2025-01-01"",""Counterparty"":""Shopify"",""Description"":""Shopify"",""Amou"&"nt"":""$2000"",""Category"":""Software"",""Frequency"":""monthly"",""Payment schedule_0"":""2026-03-01""},{""First payment date"":""2025-01-01"",""Counterparty"":""Shopify"",""Description"":""Shopify"",""Amount"":""$2000"",""Category"":""Software"",""Frequency"":""monthly"",""Payment schedule_0"&""":""2026-04-01""},{""First payment date"":""2025-01-01"",""Counterparty"":""Shopify"",""Description"":""Shopify"",""Amount"":""$2000"",""Category"":""Software"",""Frequency"":""monthly"",""Payment schedule_0"":""2026-05-01""},{""First payment date"":""2025-01-01"",""Counterparty"":""Shopify"""&",""Description"":""Shopify"",""Amount"":""$2000"",""Category"":""Software"",""Frequency"":""monthly"",""Payment schedule_0"":""2026-06-01""},{""First payment date"":""2025-01-01"",""Counterparty"":""Shopify"",""Description"":""Shopify"",""Amount"":""$2000"",""Category"":""Software"",""Frequency"""&":""monthly"",""Payment schedule_0"":""2026-07-01""}]") -> [{"First payment date":"2025-01-01","Counterparty":"Shopify","Description":"Shopify","Amount":"$2000","Category":"Software","Frequency":"monthly","Payment schedule_0":"2025-07-01"},{"First payment date":"2025-01-01","Counterparty":"Shopify","Description":"Shopify","Amount":"$2000","Category":"Software","Frequency":"monthly","Payment schedule_0":"2025-08-01"},{"First payment date":"2025-01-01","Counterparty":"Shopify","Description":"Shopify","Amount":"$2000","Category":"Software","Frequency":"monthly","Payment schedule_0":"2025-09-01"},{"First payment date":"2025-01-01","Counterparty":"Shopify","Description":"Shopify","Amount":"$2000","Category":"Software","Frequency":"monthly","Payment schedule_0":"2025-10-01"},{"First payment date":"2025-01-01","Counterparty":"Shopify","Description":"Shopify","Amount":"$2000","Category":"Software","Frequency":"monthly","Payment schedule_0":"2025-11-01"},{"First payment date":"2025-01-01","Counterparty":"Shopify","Description":"Shopify","Amount":"$2000","Category":"Software","Frequency":"monthly","Payment schedule_0":"2025-12-01"},{"First payment date":"2025-01-01","Counterparty":"Shopify","Description":"Shopify","Amount":"$2000","Category":"Software","Frequency":"monthly","Payment schedule_0":"2026-01-01"},{"First payment date":"2025-01-01","Counterparty":"Shopify","Description":"Shopify","Amount":"$2000","Category":"Software","Frequency":"monthly","Payment schedule_0":"2026-02-01"},{"First payment date":"2025-01-01","Counterparty":"Shopify","Description":"Shopify","Amount":"$2000","Category":"Software","Frequency":"monthly","Payment schedule_0":"2026-03-01"},{"First payment date":"2025-01-01","Counterparty":"Shopify","Description":"Shopify","Amount":"$2000","Category":"Software","Frequency":"monthly","Payment schedule_0":"2026-04-01"},{"First payment date":"2025-01-01","Counterparty":"Shopify","Description":"Shopify","Amount":"$2000","Category":"Software","Frequency":"monthly","Payment schedule_0":"2026-05-01"},{"First payment date":"2025-01-01","Counterparty":"Shopify","Description":"Shopify","Amount":"$2000","Category":"Software","Frequency":"monthly","Payment schedule_0":"2026-06-01"},{"First payment date":"2025-01-01","Counterparty":"Shopify","Description":"Shopify","Amount":"$2000","Category":"Software","Frequency":"monthly","Payment schedule_0":"2026-07-01"}] | U9: Staychill
A10: 45658 | B10: Melissa | C10: Melissa | D10: 3000 | E10: Sales&Marketing Expenditures | F10: monthly | G10: =IFS($F10="bi-weekly",$A10+CEILING(('13-week CF Forecast'!$B$1-$A10)/14,1)*14+14*(COLUMN()-7),$F10="weekly",$A10+CEILING(('13-week CF Forecast'!$B$1-$A10)/7,1)*7+7*(COLUMN()-7),$F10="monthly",DATE(YEAR($A10),MONTH($A10)+CEILING(DATEDIF($A10,'13-week CF Forecast'!$B$1,"m")+1,1)+COLUMN()-7,DAY($A10)),$F10="quarterly",DATE(YEAR($A10),MONTH($A10)+3*CEILING((DATEDIF($A10,'13-week CF Forecast'!$B$1,"m")+1)/3,1)+(COLUMN()-7)*3,DAY($A10)),$F10="yearly",DATE(YEAR($A10)+CEILING((DATEDIF($A10,'13-week CF Forecast'!$B$1,"y")+1),1)+COLUMN()-7,MONTH($A10),DAY($A10)),TRUE,"") -> 45839 | H10: =IFS($F10="bi-weekly",$A10+CEILING(('13-week CF Forecast'!$B$1-$A10)/14,1)*14+14*(COLUMN()-7),$F10="weekly",$A10+CEILING(('13-week CF Forecast'!$B$1-$A10)/7,1)*7+7*(COLUMN()-7),$F10="monthly",DATE(YEAR($A10),MONTH($A10)+CEILING(DATEDIF($A10,'13-week CF Forecast'!$B$1,"m")+1,1)+COLUMN()-7,DAY($A10)),$F10="quarterly",DATE(YEAR($A10),MONTH($A10)+3*CEILING((DATEDIF($A10,'13-week CF Forecast'!$B$1,"m")+1)/3,1)+(COLUMN()-7)*3,DAY($A10)),$F10="yearly",DATE(YEAR($A10)+CEILING((DATEDIF($A10,'13-week CF Forecast'!$B$1,"y")+1),1)+COLUMN()-7,MONTH($A10),DAY($A10)),TRUE,"") -> 45870 | I10: =IFS($F10="bi-weekly",$A10+CEILING(('13-week CF Forecast'!$B$1-$A10)/14,1)*14+14*(COLUMN()-7),$F10="weekly",$A10+CEILING(('13-week CF Forecast'!$B$1-$A10)/7,1)*7+7*(COLUMN()-7),$F10="monthly",DATE(YEAR($A10),MONTH($A10)+CEILING(DATEDIF($A10,'13-week CF Forecast'!$B$1,"m")+1,1)+COLUMN()-7,DAY($A10)),$F10="quarterly",DATE(YEAR($A10),MONTH($A10)+3*CEILING((DATEDIF($A10,'13-week CF Forecast'!$B$1,"m")+1)/3,1)+(COLUMN()-7)*3,DAY($A10)),$F10="yearly",DATE(YEAR($A10)+CEILING((DATEDIF($A10,'13-week CF Forecast'!$B$1,"y")+1),1)+COLUMN()-7,MONTH($A10),DAY($A10)),TRUE,"") -> 45901 | J10: =IFS($F10="bi-weekly",$A10+CEILING(('13-week CF Forecast'!$B$1-$A10)/14,1)*14+14*(COLUMN()-7),$F10="weekly",$A10+CEILING(('13-week CF Forecast'!$B$1-$A10)/7,1)*7+7*(COLUMN()-7),$F10="monthly",DATE(YEAR($A10),MONTH($A10)+CEILING(DATEDIF($A10,'13-week CF Forecast'!$B$1,"m")+1,1)+COLUMN()-7,DAY($A10)),$F10="quarterly",DATE(YEAR($A10),MONTH($A10)+3*CEILING((DATEDIF($A10,'13-week CF Forecast'!$B$1,"m")+1)/3,1)+(COLUMN()-7)*3,DAY($A10)),$F10="yearly",DATE(YEAR($A10)+CEILING((DATEDIF($A10,'13-week CF Forecast'!$B$1,"y")+1),1)+COLUMN()-7,MONTH($A10),DAY($A10)),TRUE,"") -> 45931 | K10: =IFS($F10="bi-weekly",$A10+CEILING(('13-week CF Forecast'!$B$1-$A10)/14,1)*14+14*(COLUMN()-7),$F10="weekly",$A10+CEILING(('13-week CF Forecast'!$B$1-$A10)/7,1)*7+7*(COLUMN()-7),$F10="monthly",DATE(YEAR($A10),MONTH($A10)+CEILING(DATEDIF($A10,'13-week CF Forecast'!$B$1,"m")+1,1)+COLUMN()-7,DAY($A10)),$F10="quarterly",DATE(YEAR($A10),MONTH($A10)+3*CEILING((DATEDIF($A10,'13-week CF Forecast'!$B$1,"m")+1)/3,1)+(COLUMN()-7)*3,DAY($A10)),$F10="yearly",DATE(YEAR($A10)+CEILING((DATEDIF($A10,'13-week CF Forecast'!$B$1,"y")+1),1)+COLUMN()-7,MONTH($A10),DAY($A10)),TRUE,"") -> 45962 | L10: =IFS($F10="bi-weekly",$A10+CEILING(('13-week CF Forecast'!$B$1-$A10)/14,1)*14+14*(COLUMN()-7),$F10="weekly",$A10+CEILING(('13-week CF Forecast'!$B$1-$A10)/7,1)*7+7*(COLUMN()-7),$F10="monthly",DATE(YEAR($A10),MONTH($A10)+CEILING(DATEDIF($A10,'13-week CF Forecast'!$B$1,"m")+1,1)+COLUMN()-7,DAY($A10)),$F10="quarterly",DATE(YEAR($A10),MONTH($A10)+3*CEILING((DATEDIF($A10,'13-week CF Forecast'!$B$1,"m")+1)/3,1)+(COLUMN()-7)*3,DAY($A10)),$F10="yearly",DATE(YEAR($A10)+CEILING((DATEDIF($A10,'13-week CF Forecast'!$B$1,"y")+1),1)+COLUMN()-7,MONTH($A10),DAY($A10)),TRUE,"") -> 45992 | M10: =IFS($F10="bi-weekly",$A10+CEILING(('13-week CF Forecast'!$B$1-$A10)/14,1)*14+14*(COLUMN()-7),$F10="weekly",$A10+CEILING(('13-week CF Forecast'!$B$1-$A10)/7,1)*7+7*(COLUMN()-7),$F10="monthly",DATE(YEAR($A10),MONTH($A10)+CEILING(DATEDIF($A10,'13-week CF Forecast'!$B$1,"m")+1,1)+COLUMN()-7,DAY($A10)),$F10="quarterly",DATE(YEAR($A10),MONTH($A10)+3*CEILING((DATEDIF($A10,'13-week CF Forecast'!$B$1,"m")+1)/3,1)+(COLUMN()-7)*3,DAY($A10)),$F10="yearly",DATE(YEAR($A10)+CEILING((DATEDIF($A10,'13-week CF Forecast'!$B$1,"y")+1),1)+COLUMN()-7,MONTH($A10),DAY($A10)),TRUE,"") -> 46023 | N10: =IFS($F10="bi-weekly",$A10+CEILING(('13-week CF Forecast'!$B$1-$A10)/14,1)*14+14*(COLUMN()-7),$F10="weekly",$A10+CEILING(('13-week CF Forecast'!$B$1-$A10)/7,1)*7+7*(COLUMN()-7),$F10="monthly",DATE(YEAR($A10),MONTH($A10)+CEILING(DATEDIF($A10,'13-week CF Forecast'!$B$1,"m")+1,1)+COLUMN()-7,DAY($A10)),$F10="quarterly",DATE(YEAR($A10),MONTH($A10)+3*CEILING((DATEDIF($A10,'13-week CF Forecast'!$B$1,"m")+1)/3,1)+(COLUMN()-7)*3,DAY($A10)),$F10="yearly",DATE(YEAR($A10)+CEILING((DATEDIF($A10,'13-week CF Forecast'!$B$1,"y")+1),1)+COLUMN()-7,MONTH($A10),DAY($A10)),TRUE,"") -> 46054 | ... S10: =IFS($F10="bi-weekly",$A10+CEILING(('13-week CF Forecast'!$B$1-$A10)/14,1)*14+14*(COLUMN()-7),$F10="weekly",$A10+CEILING(('13-week CF Forecast'!$B$1-$A10)/7,1)*7+7*(COLUMN()-7),$F10="monthly",DATE(YEAR($A10),MONTH($A10)+CEILING(DATEDIF($A10,'13-week CF Forecast'!$B$1,"m")+1,1)+COLUMN()-7,DAY($A10)),$F10="quarterly",DATE(YEAR($A10),MONTH($A10)+3*CEILING((DATEDIF($A10,'13-week CF Forecast'!$B$1,"m")+1)/3,1)+(COLUMN()-7)*3,DAY($A10)),$F10="yearly",DATE(YEAR($A10)+CEILING((DATEDIF($A10,'13-week CF Forecast'!$B$1,"y")+1),1)+COLUMN()-7,MONTH($A10),DAY($A10)),TRUE,"") -> 46204 | T10: =IFERROR(ROWSDUMMYFUNCTION(UNNEST(PAIR2JSON('Recurring Transactions'!$A$1,'Recurring Transactions'!A10,'Recurring Transactions'!$B$1,'Recurring Transactions'!B10,'Recurring Transactions'!$C$1,'Recurring Transactions'!C10,'Recurring Transactions'!$D$1,'Recurring Transactions'!D10,'Recurring Transactions'!$E$1,'Recurring Transactions'!E10,'Recurring Transactions'!$F$1,'Recurring Transactions'!F10,"Payment schedule",VALUE(RANGE2JSON('Recurring Transactions'!F10,'Recurring Transactions'!G10:S10))))),"[{""First payment date"":""2025-01-01"",""Counterparty"":""Melissa"",""Description"":""Melissa"",""Amount"":""$3000"",""Category"":""Sales&Marketing Expenditures"",""Frequency"":""monthly"",""Payment schedule_0"":""2025-07-01""},{""First payment date"":""2025-01-01"",""Counterparty"":""Mel"&"issa"",""Description"":""Melissa"",""Amount"":""$3000"",""Category"":""Sales&Marketing Expenditures"",""Frequency"":""monthly"",""Payment schedule_0"":""2025-08-01""},{""First payment date"":""2025-01-01"",""Counterparty"":""Melissa"",""Description"":""Melissa"",""Amount"":""$3000"",""Categor"&"y"":""Sales&Marketing Expenditures"",""Frequency"":""monthly"",""Payment schedule_0"":""2025-09-01""},{""First payment date"":""2025-01-01"",""Counterparty"":""Melissa"",""Description"":""Melissa"",""Amount"":""$3000"",""Category"":""Sales&Marketing Expenditures"",""Frequency"":""monthly"""&",""Payment schedule_0"":""2025-10-01""},{""First payment date"":""2025-01-01"",""Counterparty"":""Melissa"",""Description"":""Melissa"",""Amount"":""$3000"",""Category"":""Sales&Marketing Expenditures"",""Frequency"":""monthly"",""Payment schedule_0"":""2025-11-01""},{""First payment dat"&"e"":""2025-01-01"",""Counterparty"":""Melissa"",""Description"":""Melissa"",""Amount"":""$3000"",""Category"":""Sales&Marketing Expenditures"",""Frequency"":""monthly"",""Payment schedule_0"":""2025-12-01""},{""First payment date"":""2025-01-01"",""Counterparty"":""Melissa"",""Description"":"&"""Melissa"",""Amount"":""$3000"",""Category"":""Sales&Marketing Expenditures"",""Frequency"":""monthly"",""Payment schedule_0"":""2026-01-01""},{""First payment date"":""2025-01-01"",""Counterparty"":""Melissa"",""Description"":""Melissa"",""Amount"":""$3000"",""Category"":""Sales&Marketing "&"Expenditures"",""Frequency"":""monthly"",""Payment schedule_0"":""2026-02-01""},{""First payment date"":""2025-01-01"",""Counterparty"":""Melissa"",""Description"":""Melissa"",""Amount"":""$3000"",""Category"":""Sales&Marketing Expenditures"",""Frequency"":""monthly"",""Payment schedule_0"&""":""2026-03-01""},{""First payment date"":""2025-01-01"",""Counterparty"":""Melissa"",""Description"":""Melissa"",""Amount"":""$3000"",""Category"":""Sales&Marketing Expenditures"",""Frequency"":""monthly"",""Payment schedule_0"":""2026-04-01""},{""First payment date"":""2025-01-01"",""Cou"&"nterparty"":""Melissa"",""Description"":""Melissa"",""Amount"":""$3000"",""Category"":""Sales&Marketing Expenditures"",""Frequency"":""monthly"",""Payment schedule_0"":""2026-05-01""},{""First payment date"":""2025-01-01"",""Counterparty"":""Melissa"",""Description"":""Melissa"",""Amount"":"""&"$3000"",""Category"":""Sales&Marketing Expenditures"",""Frequency"":""monthly"",""Payment schedule_0"":""2026-06-01""},{""First payment date"":""2025-01-01"",""Counterparty"":""Melissa"",""Description"":""Melissa"",""Amount"":""$3000"",""Category"":""Sales&Marketing Expenditures"",""Frequ"&"ency"":""monthly"",""Payment schedule_0"":""2026-07-01""}]") -> [{"First payment date":"2025-01-01","Counterparty":"Melissa","Description":"Melissa","Amount":"$3000","Category":"Sales&Marketing Expenditures","Frequency":"monthly","Payment schedule_0":"2025-07-01"},{"First payment date":"2025-01-01","Counterparty":"Melissa","Description":"Melissa","Amount":"$3000","Category":"Sales&Marketing Expenditures","Frequency":"monthly","Payment schedule_0":"2025-08-01"},{"First payment date":"2025-01-01","Counterparty":"Melissa","Description":"Melissa","Amount":"$3000","Category":"Sales&Marketing Expenditures","Frequency":"monthly","Payment schedule_0":"2025-09-01"},{"First payment date":"2025-01-01","Counterparty":"Melissa","Description":"Melissa","Amount":"$3000","Category":"Sales&Marketing Expenditures","Frequency":"monthly","Payment schedule_0":"2025-10-01"},{"First payment date":"2025-01-01","Counterparty":"Melissa","Description":"Melissa","Amount":"$3000","Category":"Sales&Marketing Expenditures","Frequency":"monthly","Payment schedule_0":"2025-11-01"},{"First payment date":"2025-01-01","Counterparty":"Melissa","Description":"Melissa","Amount":"$3000","Category":"Sales&Marketing Expenditures","Frequency":"monthly","Payment schedule_0":"2025-12-01"},{"First payment date":"2025-01-01","Counterparty":"Melissa","Description":"Melissa","Amount":"$3000","Category":"Sales&Marketing Expenditures","Frequency":"monthly","Payment schedule_0":"2026-01-01"},{"First payment date":"2025-01-01","Counterparty":"Melissa","Description":"Melissa","Amount":"$3000","Category":"Sales&Marketing Expenditures","Frequency":"monthly","Payment schedule_0":"2026-02-01"},{"First payment date":"2025-01-01","Counterparty":"Melissa","Description":"Melissa","Amount":"$3000","Category":"Sales&Marketing Expenditures","Frequency":"monthly","Payment schedule_0":"2026-03-01"},{"First payment date":"2025-01-01","Counterparty":"Melissa","Description":"Melissa","Amount":"$3000","Category":"Sales&Marketing Expenditures","Frequency":"monthly","Payment schedule_0":"2026-04-01"},{"First payment date":"2025-01-01","Counterparty":"Melissa","Description":"Melissa","Amount":"$3000","Category":"Sales&Marketing Expenditures","Frequency":"monthly","Payment schedule_0":"2026-05-01"},{"First payment date":"2025-01-01","Counterparty":"Melissa","Description":"Melissa","Amount":"$3000","Category":"Sales&Marketing Expenditures","Frequency":"monthly","Payment schedule_0":"2026-06-01"},{"First payment date":"2025-01-01","Counterparty":"Melissa","Description":"Melissa","Amount":"$3000","Category":"Sales&Marketing Expenditures","Frequency":"monthly","Payment schedule_0":"2026-07-01"}] | U10: Staychill
A11: 45658 | B11: Infoplus | C11: Infoplus | D11: 1145 | E11: Software | F11: monthly | G11: =IFS($F11="bi-weekly",$A11+CEILING(('13-week CF Forecast'!$B$1-$A11)/14,1)*14+14*(COLUMN()-7),$F11="weekly",$A11+CEILING(('13-week CF Forecast'!$B$1-$A11)/7,1)*7+7*(COLUMN()-7),$F11="monthly",DATE(YEAR($A11),MONTH($A11)+CEILING(DATEDIF($A11,'13-week CF Forecast'!$B$1,"m")+1,1)+COLUMN()-7,DAY($A11)),$F11="quarterly",DATE(YEAR($A11),MONTH($A11)+3*CEILING((DATEDIF($A11,'13-week CF Forecast'!$B$1,"m")+1)/3,1)+(COLUMN()-7)*3,DAY($A11)),$F11="yearly",DATE(YEAR($A11)+CEILING((DATEDIF($A11,'13-week CF Forecast'!$B$1,"y")+1),1)+COLUMN()-7,MONTH($A11),DAY($A11)),TRUE,"") -> 45839 | H11: =IFS($F11="bi-weekly",$A11+CEILING(('13-week CF Forecast'!$B$1-$A11)/14,1)*14+14*(COLUMN()-7),$F11="weekly",$A11+CEILING(('13-week CF Forecast'!$B$1-$A11)/7,1)*7+7*(COLUMN()-7),$F11="monthly",DATE(YEAR($A11),MONTH($A11)+CEILING(DATEDIF($A11,'13-week CF Forecast'!$B$1,"m")+1,1)+COLUMN()-7,DAY($A11)),$F11="quarterly",DATE(YEAR($A11),MONTH($A11)+3*CEILING((DATEDIF($A11,'13-week CF Forecast'!$B$1,"m")+1)/3,1)+(COLUMN()-7)*3,DAY($A11)),$F11="yearly",DATE(YEAR($A11)+CEILING((DATEDIF($A11,'13-week CF Forecast'!$B$1,"y")+1),1)+COLUMN()-7,MONTH($A11),DAY($A11)),TRUE,"") -> 45870 | I11: =IFS($F11="bi-weekly",$A11+CEILING(('13-week CF Forecast'!$B$1-$A11)/14,1)*14+14*(COLUMN()-7),$F11="weekly",$A11+CEILING(('13-week CF Forecast'!$B$1-$A11)/7,1)*7+7*(COLUMN()-7),$F11="monthly",DATE(YEAR($A11),MONTH($A11)+CEILING(DATEDIF($A11,'13-week CF Forecast'!$B$1,"m")+1,1)+COLUMN()-7,DAY($A11)),$F11="quarterly",DATE(YEAR($A11),MONTH($A11)+3*CEILING((DATEDIF($A11,'13-week CF Forecast'!$B$1,"m")+1)/3,1)+(COLUMN()-7)*3,DAY($A11)),$F11="yearly",DATE(YEAR($A11)+CEILING((DATEDIF($A11,'13-week CF Forecast'!$B$1,"y")+1),1)+COLUMN()-7,MONTH($A11),DAY($A11)),TRUE,"") -> 45901 | J11: =IFS($F11="bi-weekly",$A11+CEILING(('13-week CF Forecast'!$B$1-$A11)/14,1)*14+14*(COLUMN()-7),$F11="weekly",$A11+CEILING(('13-week CF Forecast'!$B$1-$A11)/7,1)*7+7*(COLUMN()-7),$F11="monthly",DATE(YEAR($A11),MONTH($A11)+CEILING(DATEDIF($A11,'13-week CF Forecast'!$B$1,"m")+1,1)+COLUMN()-7,DAY($A11)),$F11="quarterly",DATE(YEAR($A11),MONTH($A11)+3*CEILING((DATEDIF($A11,'13-week CF Forecast'!$B$1,"m")+1)/3,1)+(COLUMN()-7)*3,DAY($A11)),$F11="yearly",DATE(YEAR($A11)+CEILING((DATEDIF($A11,'13-week CF Forecast'!$B$1,"y")+1),1)+COLUMN()-7,MONTH($A11),DAY($A11)),TRUE,"") -> 45931 | K11: =IFS($F11="bi-weekly",$A11+CEILING(('13-week CF Forecast'!$B$1-$A11)/14,1)*14+14*(COLUMN()-7),$F11="weekly",$A11+CEILING(('13-week CF Forecast'!$B$1-$A11)/7,1)*7+7*(COLUMN()-7),$F11="monthly",DATE(YEAR($A11),MONTH($A11)+CEILING(DATEDIF($A11,'13-week CF Forecast'!$B$1,"m")+1,1)+COLUMN()-7,DAY($A11)),$F11="quarterly",DATE(YEAR($A11),MONTH($A11)+3*CEILING((DATEDIF($A11,'13-week CF Forecast'!$B$1,"m")+1)/3,1)+(COLUMN()-7)*3,DAY($A11)),$F11="yearly",DATE(YEAR($A11)+CEILING((DATEDIF($A11,'13-week CF Forecast'!$B$1,"y")+1),1)+COLUMN()-7,MONTH($A11),DAY($A11)),TRUE,"") -> 45962 | L11: =IFS($F11="bi-weekly",$A11+CEILING(('13-week CF Forecast'!$B$1-$A11)/14,1)*14+14*(COLUMN()-7),$F11="weekly",$A11+CEILING(('13-week CF Forecast'!$B$1-$A11)/7,1)*7+7*(COLUMN()-7),$F11="monthly",DATE(YEAR($A11),MONTH($A11)+CEILING(DATEDIF($A11,'13-week CF Forecast'!$B$1,"m")+1,1)+COLUMN()-7,DAY($A11)),$F11="quarterly",DATE(YEAR($A11),MONTH($A11)+3*CEILING((DATEDIF($A11,'13-week CF Forecast'!$B$1,"m")+1)/3,1)+(COLUMN()-7)*3,DAY($A11)),$F11="yearly",DATE(YEAR($A11)+CEILING((DATEDIF($A11,'13-week CF Forecast'!$B$1,"y")+1),1)+COLUMN()-7,MONTH($A11),DAY($A11)),TRUE,"") -> 45992 | M11: =IFS($F11="bi-weekly",$A11+CEILING(('13-week CF Forecast'!$B$1-$A11)/14,1)*14+14*(COLUMN()-7),$F11="weekly",$A11+CEILING(('13-week CF Forecast'!$B$1-$A11)/7,1)*7+7*(COLUMN()-7),$F11="monthly",DATE(YEAR($A11),MONTH($A11)+CEILING(DATEDIF($A11,'13-week CF Forecast'!$B$1,"m")+1,1)+COLUMN()-7,DAY($A11)),$F11="quarterly",DATE(YEAR($A11),MONTH($A11)+3*CEILING((DATEDIF($A11,'13-week CF Forecast'!$B$1,"m")+1)/3,1)+(COLUMN()-7)*3,DAY($A11)),$F11="yearly",DATE(YEAR($A11)+CEILING((DATEDIF($A11,'13-week CF Forecast'!$B$1,"y")+1),1)+COLUMN()-7,MONTH($A11),DAY($A11)),TRUE,"") -> 46023 | N11: =IFS($F11="bi-weekly",$A11+CEILING(('13-week CF Forecast'!$B$1-$A11)/14,1)*14+14*(COLUMN()-7),$F11="weekly",$A11+CEILING(('13-week CF Forecast'!$B$1-$A11)/7,1)*7+7*(COLUMN()-7),$F11="monthly",DATE(YEAR($A11),MONTH($A11)+CEILING(DATEDIF($A11,'13-week CF Forecast'!$B$1,"m")+1,1)+COLUMN()-7,DAY($A11)),$F11="quarterly",DATE(YEAR($A11),MONTH($A11)+3*CEILING((DATEDIF($A11,'13-week CF Forecast'!$B$1,"m")+1)/3,1)+(COLUMN()-7)*3,DAY($A11)),$F11="yearly",DATE(YEAR($A11)+CEILING((DATEDIF($A11,'13-week CF Forecast'!$B$1,"y")+1),1)+COLUMN()-7,MONTH($A11),DAY($A11)),TRUE,"") -> 46054 | ... S11: =IFS($F11="bi-weekly",$A11+CEILING(('13-week CF Forecast'!$B$1-$A11)/14,1)*14+14*(COLUMN()-7),$F11="weekly",$A11+CEILING(('13-week CF Forecast'!$B$1-$A11)/7,1)*7+7*(COLUMN()-7),$F11="monthly",DATE(YEAR($A11),MONTH($A11)+CEILING(DATEDIF($A11,'13-week CF Forecast'!$B$1,"m")+1,1)+COLUMN()-7,DAY($A11)),$F11="quarterly",DATE(YEAR($A11),MONTH($A11)+3*CEILING((DATEDIF($A11,'13-week CF Forecast'!$B$1,"m")+1)/3,1)+(COLUMN()-7)*3,DAY($A11)),$F11="yearly",DATE(YEAR($A11)+CEILING((DATEDIF($A11,'13-week CF Forecast'!$B$1,"y")+1),1)+COLUMN()-7,MONTH($A11),DAY($A11)),TRUE,"") -> 46204 | T11: =IFERROR(ROWSDUMMYFUNCTION(UNNEST(PAIR2JSON('Recurring Transactions'!$A$1,'Recurring Transactions'!A11,'Recurring Transactions'!$B$1,'Recurring Transactions'!B11,'Recurring Transactions'!$C$1,'Recurring Transactions'!C11,'Recurring Transactions'!$D$1,'Recurring Transactions'!D11,'Recurring Transactions'!$E$1,'Recurring Transactions'!E11,'Recurring Transactions'!$F$1,'Recurring Transactions'!F11,"Payment schedule",VALUE(RANGE2JSON('Recurring Transactions'!F11,'Recurring Transactions'!G11:S11))))),"[{""First payment date"":""2025-01-01"",""Counterparty"":""Infoplus"",""Description"":""Infoplus"",""Amount"":""$1145"",""Category"":""Software"",""Frequency"":""monthly"",""Payment schedule_0"":""2025-07-01""},{""First payment date"":""2025-01-01"",""Counterparty"":""Infoplus"",""Descriptio"&"n"":""Infoplus"",""Amount"":""$1145"",""Category"":""Software"",""Frequency"":""monthly"",""Payment schedule_0"":""2025-08-01""},{""First payment date"":""2025-01-01"",""Counterparty"":""Infoplus"",""Description"":""Infoplus"",""Amount"":""$1145"",""Category"":""Software"",""Frequency"":""monthly"&""",""Payment schedule_0"":""2025-09-01""},{""First payment date"":""2025-01-01"",""Counterparty"":""Infoplus"",""Description"":""Infoplus"",""Amount"":""$1145"",""Category"":""Software"",""Frequency"":""monthly"",""Payment schedule_0"":""2025-10-01""},{""First payment date"":""2025-01-01"","""&"Counterparty"":""Infoplus"",""Description"":""Infoplus"",""Amount"":""$1145"",""Category"":""Software"",""Frequency"":""monthly"",""Payment schedule_0"":""2025-11-01""},{""First payment date"":""2025-01-01"",""Counterparty"":""Infoplus"",""Description"":""Infoplus"",""Amount"":""$1145"",""Categ"&"ory"":""Software"",""Frequency"":""monthly"",""Payment schedule_0"":""2025-12-01""},{""First payment date"":""2025-01-01"",""Counterparty"":""Infoplus"",""Description"":""Infoplus"",""Amount"":""$1145"",""Category"":""Software"",""Frequency"":""monthly"",""Payment schedule_0"":""2026-01-01""},"&"{""First payment date"":""2025-01-01"",""Counterparty"":""Infoplus"",""Description"":""Infoplus"",""Amount"":""$1145"",""Category"":""Software"",""Frequency"":""monthly"",""Payment schedule_0"":""2026-02-01""},{""First payment date"":""2025-01-01"",""Counterparty"":""Infoplus"",""Description"&""":""Infoplus"",""Amount"":""$1145"",""Category"":""Software"",""Frequency"":""monthly"",""Payment schedule_0"":""2026-03-01""},{""First payment date"":""2025-01-01"",""Counterparty"":""Infoplus"",""Description"":""Infoplus"",""Amount"":""$1145"",""Category"":""Software"",""Frequency"":""monthly"""&",""Payment schedule_0"":""2026-04-01""},{""First payment date"":""2025-01-01"",""Counterparty"":""Infoplus"",""Description"":""Infoplus"",""Amount"":""$1145"",""Category"":""Software"",""Frequency"":""monthly"",""Payment schedule_0"":""2026-05-01""},{""First payment date"":""2025-01-01"",""C"&"ounterparty"":""Infoplus"",""Description"":""Infoplus"",""Amount"":""$1145"",""Category"":""Software"",""Frequency"":""monthly"",""Payment schedule_0"":""2026-06-01""},{""First payment date"":""2025-01-01"",""Counterparty"":""Infoplus"",""Description"":""Infoplus"",""Amount"":""$1145"",""Catego"&"ry"":""Software"",""Frequency"":""monthly"",""Payment schedule_0"":""2026-07-01""}]") -> [{"First payment date":"2025-01-01","Counterparty":"Infoplus","Description":"Infoplus","Amount":"$1145","Category":"Software","Frequency":"monthly","Payment schedule_0":"2025-07-01"},{"First payment date":"2025-01-01","Counterparty":"Infoplus","Description":"Infoplus","Amount":"$1145","Category":"Software","Frequency":"monthly","Payment schedule_0":"2025-08-01"},{"First payment date":"2025-01-01","Counterparty":"Infoplus","Description":"Infoplus","Amount":"$1145","Category":"Software","Frequency":"monthly","Payment schedule_0":"2025-09-01"},{"First payment date":"2025-01-01","Counterparty":"Infoplus","Description":"Infoplus","Amount":"$1145","Category":"Software","Frequency":"monthly","Payment schedule_0":"2025-10-01"},{"First payment date":"2025-01-01","Counterparty":"Infoplus","Description":"Infoplus","Amount":"$1145","Category":"Software","Frequency":"monthly","Payment schedule_0":"2025-11-01"},{"First payment date":"2025-01-01","Counterparty":"Infoplus","Description":"Infoplus","Amount":"$1145","Category":"Software","Frequency":"monthly","Payment schedule_0":"2025-12-01"},{"First payment date":"2025-01-01","Counterparty":"Infoplus","Description":"Infoplus","Amount":"$1145","Category":"Software","Frequency":"monthly","Payment schedule_0":"2026-01-01"},{"First payment date":"2025-01-01","Counterparty":"Infoplus","Description":"Infoplus","Amount":"$1145","Category":"Software","Frequency":"monthly","Payment schedule_0":"2026-02-01"},{"First payment date":"2025-01-01","Counterparty":"Infoplus","Description":"Infoplus","Amount":"$1145","Category":"Software","Frequency":"monthly","Payment schedule_0":"2026-03-01"},{"First payment date":"2025-01-01","Counterparty":"Infoplus","Description":"Infoplus","Amount":"$1145","Category":"Software","Frequency":"monthly","Payment schedule_0":"2026-04-01"},{"First payment date":"2025-01-01","Counterparty":"Infoplus","Description":"Infoplus","Amount":"$1145","Category":"Software","Frequency":"monthly","Payment schedule_0":"2026-05-01"},{"First payment date":"2025-01-01","Counterparty":"Infoplus","Description":"Infoplus","Amount":"$1145","Category":"Software","Frequency":"monthly","Payment schedule_0":"2026-06-01"},{"First payment date":"2025-01-01","Counterparty":"Infoplus","Description":"Infoplus","Amount":"$1145","Category":"Software","Frequency":"monthly","Payment schedule_0":"2026-07-01"}] | U11: Staychill
A12: 45658 | B12: Klaviyo | C12: Klaviyo | D12: 1000 | E12: Software | F12: monthly | G12: =IFS($F12="bi-weekly",$A12+CEILING(('13-week CF Forecast'!$B$1-$A12)/14,1)*14+14*(COLUMN()-7),$F12="weekly",$A12+CEILING(('13-week CF Forecast'!$B$1-$A12)/7,1)*7+7*(COLUMN()-7),$F12="monthly",DATE(YEAR($A12),MONTH($A12)+CEILING(DATEDIF($A12,'13-week CF Forecast'!$B$1,"m")+1,1)+COLUMN()-7,DAY($A12)),$F12="quarterly",DATE(YEAR($A12),MONTH($A12)+3*CEILING((DATEDIF($A12,'13-week CF Forecast'!$B$1,"m")+1)/3,1)+(COLUMN()-7)*3,DAY($A12)),$F12="yearly",DATE(YEAR($A12)+CEILING((DATEDIF($A12,'13-week CF Forecast'!$B$1,"y")+1),1)+COLUMN()-7,MONTH($A12),DAY($A12)),TRUE,"") -> 45839 | H12: =IFS($F12="bi-weekly",$A12+CEILING(('13-week CF Forecast'!$B$1-$A12)/14,1)*14+14*(COLUMN()-7),$F12="weekly",$A12+CEILING(('13-week CF Forecast'!$B$1-$A12)/7,1)*7+7*(COLUMN()-7),$F12="monthly",DATE(YEAR($A12),MONTH($A12)+CEILING(DATEDIF($A12,'13-week CF Forecast'!$B$1,"m")+1,1)+COLUMN()-7,DAY($A12)),$F12="quarterly",DATE(YEAR($A12),MONTH($A12)+3*CEILING((DATEDIF($A12,'13-week CF Forecast'!$B$1,"m")+1)/3,1)+(COLUMN()-7)*3,DAY($A12)),$F12="yearly",DATE(YEAR($A12)+CEILING((DATEDIF($A12,'13-week CF Forecast'!$B$1,"y")+1),1)+COLUMN()-7,MONTH($A12),DAY($A12)),TRUE,"") -> 45870 | I12: =IFS($F12="bi-weekly",$A12+CEILING(('13-week CF Forecast'!$B$1-$A12)/14,1)*14+14*(COLUMN()-7),$F12="weekly",$A12+CEILING(('13-week CF Forecast'!$B$1-$A12)/7,1)*7+7*(COLUMN()-7),$F12="monthly",DATE(YEAR($A12),MONTH($A12)+CEILING(DATEDIF($A12,'13-week CF Forecast'!$B$1,"m")+1,1)+COLUMN()-7,DAY($A12)),$F12="quarterly",DATE(YEAR($A12),MONTH($A12)+3*CEILING((DATEDIF($A12,'13-week CF Forecast'!$B$1,"m")+1)/3,1)+(COLUMN()-7)*3,DAY($A12)),$F12="yearly",DATE(YEAR($A12)+CEILING((DATEDIF($A12,'13-week CF Forecast'!$B$1,"y")+1),1)+COLUMN()-7,MONTH($A12),DAY($A12)),TRUE,"") -> 45901 | J12: =IFS($F12="bi-weekly",$A12+CEILING(('13-week CF Forecast'!$B$1-$A12)/14,1)*14+14*(COLUMN()-7),$F12="weekly",$A12+CEILING(('13-week CF Forecast'!$B$1-$A12)/7,1)*7+7*(COLUMN()-7),$F12="monthly",DATE(YEAR($A12),MONTH($A12)+CEILING(DATEDIF($A12,'13-week CF Forecast'!$B$1,"m")+1,1)+COLUMN()-7,DAY($A12)),$F12="quarterly",DATE(YEAR($A12),MONTH($A12)+3*CEILING((DATEDIF($A12,'13-week CF Forecast'!$B$1,"m")+1)/3,1)+(COLUMN()-7)*3,DAY($A12)),$F12="yearly",DATE(YEAR($A12)+CEILING((DATEDIF($A12,'13-week CF Forecast'!$B$1,"y")+1),1)+COLUMN()-7,MONTH($A12),DAY($A12)),TRUE,"") -> 45931 | K12: =IFS($F12="bi-weekly",$A12+CEILING(('13-week CF Forecast'!$B$1-$A12)/14,1)*14+14*(COLUMN()-7),$F12="weekly",$A12+CEILING(('13-week CF Forecast'!$B$1-$A12)/7,1)*7+7*(COLUMN()-7),$F12="monthly",DATE(YEAR($A12),MONTH($A12)+CEILING(DATEDIF($A12,'13-week CF Forecast'!$B$1,"m")+1,1)+COLUMN()-7,DAY($A12)),$F12="quarterly",DATE(YEAR($A12),MONTH($A12)+3*CEILING((DATEDIF($A12,'13-week CF Forecast'!$B$1,"m")+1)/3,1)+(COLUMN()-7)*3,DAY($A12)),$F12="yearly",DATE(YEAR($A12)+CEILING((DATEDIF($A12,'13-week CF Forecast'!$B$1,"y")+1),1)+COLUMN()-7,MONTH($A12),DAY($A12)),TRUE,"") -> 45962 | L12: =IFS($F12="bi-weekly",$A12+CEILING(('13-week CF Forecast'!$B$1-$A12)/14,1)*14+14*(COLUMN()-7),$F12="weekly",$A12+CEILING(('13-week CF Forecast'!$B$1-$A12)/7,1)*7+7*(COLUMN()-7),$F12="monthly",DATE(YEAR($A12),MONTH($A12)+CEILING(DATEDIF($A12,'13-week CF Forecast'!$B$1,"m")+1,1)+COLUMN()-7,DAY($A12)),$F12="quarterly",DATE(YEAR($A12),MONTH($A12)+3*CEILING((DATEDIF($A12,'13-week CF Forecast'!$B$1,"m")+1)/3,1)+(COLUMN()-7)*3,DAY($A12)),$F12="yearly",DATE(YEAR($A12)+CEILING((DATEDIF($A12,'13-week CF Forecast'!$B$1,"y")+1),1)+COLUMN()-7,MONTH($A12),DAY($A12)),TRUE,"") -> 45992 | M12: =IFS($F12="bi-weekly",$A12+CEILING(('13-week CF Forecast'!$B$1-$A12)/14,1)*14+14*(COLUMN()-7),$F12="weekly",$A12+CEILING(('13-week CF Forecast'!$B$1-$A12)/7,1)*7+7*(COLUMN()-7),$F12="monthly",DATE(YEAR($A12),MONTH($A12)+CEILING(DATEDIF($A12,'13-week CF Forecast'!$B$1,"m")+1,1)+COLUMN()-7,DAY($A12)),$F12="quarterly",DATE(YEAR($A12),MONTH($A12)+3*CEILING((DATEDIF($A12,'13-week CF Forecast'!$B$1,"m")+1)/3,1)+(COLUMN()-7)*3,DAY($A12)),$F12="yearly",DATE(YEAR($A12)+CEILING((DATEDIF($A12,'13-week CF Forecast'!$B$1,"y")+1),1)+COLUMN()-7,MONTH($A12),DAY($A12)),TRUE,"") -> 46023 | N12: =IFS($F12="bi-weekly",$A12+CEILING(('13-week CF Forecast'!$B$1-$A12)/14,1)*14+14*(COLUMN()-7),$F12="weekly",$A12+CEILING(('13-week CF Forecast'!$B$1-$A12)/7,1)*7+7*(COLUMN()-7),$F12="monthly",DATE(YEAR($A12),MONTH($A12)+CEILING(DATEDIF($A12,'13-week CF Forecast'!$B$1,"m")+1,1)+COLUMN()-7,DAY($A12)),$F12="quarterly",DATE(YEAR($A12),MONTH($A12)+3*CEILING((DATEDIF($A12,'13-week CF Forecast'!$B$1,"m")+1)/3,1)+(COLUMN()-7)*3,DAY($A12)),$F12="yearly",DATE(YEAR($A12)+CEILING((DATEDIF($A12,'13-week CF Forecast'!$B$1,"y")+1),1)+COLUMN()-7,MONTH($A12),DAY($A12)),TRUE,"") -> 46054 | ... S12: =IFS($F12="bi-weekly",$A12+CEILING(('13-week CF Forecast'!$B$1-$A12)/14,1)*14+14*(COLUMN()-7),$F12="weekly",$A12+CEILING(('13-week CF Forecast'!$B$1-$A12)/7,1)*7+7*(COLUMN()-7),$F12="monthly",DATE(YEAR($A12),MONTH($A12)+CEILING(DATEDIF($A12,'13-week CF Forecast'!$B$1,"m")+1,1)+COLUMN()-7,DAY($A12)),$F12="quarterly",DATE(YEAR($A12),MONTH($A12)+3*CEILING((DATEDIF($A12,'13-week CF Forecast'!$B$1,"m")+1)/3,1)+(COLUMN()-7)*3,DAY($A12)),$F12="yearly",DATE(YEAR($A12)+CEILING((DATEDIF($A12,'13-week CF Forecast'!$B$1,"y")+1),1)+COLUMN()-7,MONTH($A12),DAY($A12)),TRUE,"") -> 46204 | T12: =IFERROR(ROWSDUMMYFUNCTION(UNNEST(PAIR2JSON('Recurring Transactions'!$A$1,'Recurring Transactions'!A12,'Recurring Transactions'!$B$1,'Recurring Transactions'!B12,'Recurring Transactions'!$C$1,'Recurring Transactions'!C12,'Recurring Transactions'!$D$1,'Recurring Transactions'!D12,'Recurring Transactions'!$E$1,'Recurring Transactions'!E12,'Recurring Transactions'!$F$1,'Recurring Transactions'!F12,"Payment schedule",VALUE(RANGE2JSON('Recurring Transactions'!F12,'Recurring Transactions'!G12:S12))))),"[{""First payment date"":""2025-01-01"",""Counterparty"":""Klaviyo"",""Description"":""Klaviyo"",""Amount"":""$1000"",""Category"":""Software"",""Frequency"":""monthly"",""Payment schedule_0"":""2025-07-01""},{""First payment date"":""2025-01-01"",""Counterparty"":""Klaviyo"",""Description"":"&"""Klaviyo"",""Amount"":""$1000"",""Category"":""Software"",""Frequency"":""monthly"",""Payment schedule_0"":""2025-08-01""},{""First payment date"":""2025-01-01"",""Counterparty"":""Klaviyo"",""Description"":""Klaviyo"",""Amount"":""$1000"",""Category"":""Software"",""Frequency"":""monthly"",""Pay"&"ment schedule_0"":""2025-09-01""},{""First payment date"":""2025-01-01"",""Counterparty"":""Klaviyo"",""Description"":""Klaviyo"",""Amount"":""$1000"",""Category"":""Software"",""Frequency"":""monthly"",""Payment schedule_0"":""2025-10-01""},{""First payment date"":""2025-01-01"",""Counterp"&"arty"":""Klaviyo"",""Description"":""Klaviyo"",""Amount"":""$1000"",""Category"":""Software"",""Frequency"":""monthly"",""Payment schedule_0"":""2025-11-01""},{""First payment date"":""2025-01-01"",""Counterparty"":""Klaviyo"",""Description"":""Klaviyo"",""Amount"":""$1000"",""Category"":""Softwa"&"re"",""Frequency"":""monthly"",""Payment schedule_0"":""2025-12-01""},{""First payment date"":""2025-01-01"",""Counterparty"":""Klaviyo"",""Description"":""Klaviyo"",""Amount"":""$1000"",""Category"":""Software"",""Frequency"":""monthly"",""Payment schedule_0"":""2026-01-01""},{""First paymen"&"t date"":""2025-01-01"",""Counterparty"":""Klaviyo"",""Description"":""Klaviyo"",""Amount"":""$1000"",""Category"":""Software"",""Frequency"":""monthly"",""Payment schedule_0"":""2026-02-01""},{""First payment date"":""2025-01-01"",""Counterparty"":""Klaviyo"",""Description"":""Klaviyo"",""Amou"&"nt"":""$1000"",""Category"":""Software"",""Frequency"":""monthly"",""Payment schedule_0"":""2026-03-01""},{""First payment date"":""2025-01-01"",""Counterparty"":""Klaviyo"",""Description"":""Klaviyo"",""Amount"":""$1000"",""Category"":""Software"",""Frequency"":""monthly"",""Payment schedule_0"&""":""2026-04-01""},{""First payment date"":""2025-01-01"",""Counterparty"":""Klaviyo"",""Description"":""Klaviyo"",""Amount"":""$1000"",""Category"":""Software"",""Frequency"":""monthly"",""Payment schedule_0"":""2026-05-01""},{""First payment date"":""2025-01-01"",""Counterparty"":""Klaviyo"""&",""Description"":""Klaviyo"",""Amount"":""$1000"",""Category"":""Software"",""Frequency"":""monthly"",""Payment schedule_0"":""2026-06-01""},{""First payment date"":""2025-01-01"",""Counterparty"":""Klaviyo"",""Description"":""Klaviyo"",""Amount"":""$1000"",""Category"":""Software"",""Frequency"""&":""monthly"",""Payment schedule_0"":""2026-07-01""}]") -> [{"First payment date":"2025-01-01","Counterparty":"Klaviyo","Description":"Klaviyo","Amount":"$1000","Category":"Software","Frequency":"monthly","Payment schedule_0":"2025-07-01"},{"First payment date":"2025-01-01","Counterparty":"Klaviyo","Description":"Klaviyo","Amount":"$1000","Category":"Software","Frequency":"monthly","Payment schedule_0":"2025-08-01"},{"First payment date":"2025-01-01","Counterparty":"Klaviyo","Description":"Klaviyo","Amount":"$1000","Category":"Software","Frequency":"monthly","Payment schedule_0":"2025-09-01"},{"First payment date":"2025-01-01","Counterparty":"Klaviyo","Description":"Klaviyo","Amount":"$1000","Category":"Software","Frequency":"monthly","Payment schedule_0":"2025-10-01"},{"First payment date":"2025-01-01","Counterparty":"Klaviyo","Description":"Klaviyo","Amount":"$1000","Category":"Software","Frequency":"monthly","Payment schedule_0":"2025-11-01"},{"First payment date":"2025-01-01","Counterparty":"Klaviyo","Description":"Klaviyo","Amount":"$1000","Category":"Software","Frequency":"monthly","Payment schedule_0":"2025-12-01"},{"First payment date":"2025-01-01","Counterparty":"Klaviyo","Description":"Klaviyo","Amount":"$1000","Category":"Software","Frequency":"monthly","Payment schedule_0":"2026-01-01"},{"First payment date":"2025-01-01","Counterparty":"Klaviyo","Description":"Klaviyo","Amount":"$1000","Category":"Software","Frequency":"monthly","Payment schedule_0":"2026-02-01"},{"First payment date":"2025-01-01","Counterparty":"Klaviyo","Description":"Klaviyo","Amount":"$1000","Category":"Software","Frequency":"monthly","Payment schedule_0":"2026-03-01"},{"First payment date":"2025-01-01","Counterparty":"Klaviyo","Description":"Klaviyo","Amount":"$1000","Category":"Software","Frequency":"monthly","Payment schedule_0":"2026-04-01"},{"First payment date":"2025-01-01","Counterparty":"Klaviyo","Description":"Klaviyo","Amount":"$1000","Category":"Software","Frequency":"monthly","Payment schedule_0":"2026-05-01"},{"First payment date":"2025-01-01","Counterparty":"Klaviyo","Description":"Klaviyo","Amount":"$1000","Category":"Software","Frequency":"monthly","Payment schedule_0":"2026-06-01"},{"First payment date":"2025-01-01","Counterparty":"Klaviyo","Description":"Klaviyo","Amount":"$1000","Category":"Software","Frequency":"monthly","Payment schedule_0":"2026-07-01"}] | U12: Chase Inc
A13: 45658 | B13: Loop Returns | C13: Loop Returns | D13: 500 | E13: Software | F13: monthly | G13: =IFS($F13="bi-weekly",$A13+CEILING(('13-week CF Forecast'!$B$1-$A13)/14,1)*14+14*(COLUMN()-7),$F13="weekly",$A13+CEILING(('13-week CF Forecast'!$B$1-$A13)/7,1)*7+7*(COLUMN()-7),$F13="monthly",DATE(YEAR($A13),MONTH($A13)+CEILING(DATEDIF($A13,'13-week CF Forecast'!$B$1,"m")+1,1)+COLUMN()-7,DAY($A13)),$F13="quarterly",DATE(YEAR($A13),MONTH($A13)+3*CEILING((DATEDIF($A13,'13-week CF Forecast'!$B$1,"m")+1)/3,1)+(COLUMN()-7)*3,DAY($A13)),$F13="yearly",DATE(YEAR($A13)+CEILING((DATEDIF($A13,'13-week CF Forecast'!$B$1,"y")+1),1)+COLUMN()-7,MONTH($A13),DAY($A13)),TRUE,"") -> 45839 | H13: =IFS($F13="bi-weekly",$A13+CEILING(('13-week CF Forecast'!$B$1-$A13)/14,1)*14+14*(COLUMN()-7),$F13="weekly",$A13+CEILING(('13-week CF Forecast'!$B$1-$A13)/7,1)*7+7*(COLUMN()-7),$F13="monthly",DATE(YEAR($A13),MONTH($A13)+CEILING(DATEDIF($A13,'13-week CF Forecast'!$B$1,"m")+1,1)+COLUMN()-7,DAY($A13)),$F13="quarterly",DATE(YEAR($A13),MONTH($A13)+3*CEILING((DATEDIF($A13,'13-week CF Forecast'!$B$1,"m")+1)/3,1)+(COLUMN()-7)*3,DAY($A13)),$F13="yearly",DATE(YEAR($A13)+CEILING((DATEDIF($A13,'13-week CF Forecast'!$B$1,"y")+1),1)+COLUMN()-7,MONTH($A13),DAY($A13)),TRUE,"") -> 45870 | I13: =IFS($F13="bi-weekly",$A13+CEILING(('13-week CF Forecast'!$B$1-$A13)/14,1)*14+14*(COLUMN()-7),$F13="weekly",$A13+CEILING(('13-week CF Forecast'!$B$1-$A13)/7,1)*7+7*(COLUMN()-7),$F13="monthly",DATE(YEAR($A13),MONTH($A13)+CEILING(DATEDIF($A13,'13-week CF Forecast'!$B$1,"m")+1,1)+COLUMN()-7,DAY($A13)),$F13="quarterly",DATE(YEAR($A13),MONTH($A13)+3*CEILING((DATEDIF($A13,'13-week CF Forecast'!$B$1,"m")+1)/3,1)+(COLUMN()-7)*3,DAY($A13)),$F13="yearly",DATE(YEAR($A13)+CEILING((DATEDIF($A13,'13-week CF Forecast'!$B$1,"y")+1),1)+COLUMN()-7,MONTH($A13),DAY($A13)),TRUE,"") -> 45901 | J13: =IFS($F13="bi-weekly",$A13+CEILING(('13-week CF Forecast'!$B$1-$A13)/14,1)*14+14*(COLUMN()-7),$F13="weekly",$A13+CEILING(('13-week CF Forecast'!$B$1-$A13)/7,1)*7+7*(COLUMN()-7),$F13="monthly",DATE(YEAR($A13),MONTH($A13)+CEILING(DATEDIF($A13,'13-week CF Forecast'!$B$1,"m")+1,1)+COLUMN()-7,DAY($A13)),$F13="quarterly",DATE(YEAR($A13),MONTH($A13)+3*CEILING((DATEDIF($A13,'13-week CF Forecast'!$B$1,"m")+1)/3,1)+(COLUMN()-7)*3,DAY($A13)),$F13="yearly",DATE(YEAR($A13)+CEILING((DATEDIF($A13,'13-week CF Forecast'!$B$1,"y")+1),1)+COLUMN()-7,MONTH($A13),DAY($A13)),TRUE,"") -> 45931 | K13: =IFS($F13="bi-weekly",$A13+CEILING(('13-week CF Forecast'!$B$1-$A13)/14,1)*14+14*(COLUMN()-7),$F13="weekly",$A13+CEILING(('13-week CF Forecast'!$B$1-$A13)/7,1)*7+7*(COLUMN()-7),$F13="monthly",DATE(YEAR($A13),MONTH($A13)+CEILING(DATEDIF($A13,'13-week CF Forecast'!$B$1,"m")+1,1)+COLUMN()-7,DAY($A13)),$F13="quarterly",DATE(YEAR($A13),MONTH($A13)+3*CEILING((DATEDIF($A13,'13-week CF Forecast'!$B$1,"m")+1)/3,1)+(COLUMN()-7)*3,DAY($A13)),$F13="yearly",DATE(YEAR($A13)+CEILING((DATEDIF($A13,'13-week CF Forecast'!$B$1,"y")+1),1)+COLUMN()-7,MONTH($A13),DAY($A13)),TRUE,"") -> 45962 | L13: =IFS($F13="bi-weekly",$A13+CEILING(('13-week CF Forecast'!$B$1-$A13)/14,1)*14+14*(COLUMN()-7),$F13="weekly",$A13+CEILING(('13-week CF Forecast'!$B$1-$A13)/7,1)*7+7*(COLUMN()-7),$F13="monthly",DATE(YEAR($A13),MONTH($A13)+CEILING(DATEDIF($A13,'13-week CF Forecast'!$B$1,"m")+1,1)+COLUMN()-7,DAY($A13)),$F13="quarterly",DATE(YEAR($A13),MONTH($A13)+3*CEILING((DATEDIF($A13,'13-week CF Forecast'!$B$1,"m")+1)/3,1)+(COLUMN()-7)*3,DAY($A13)),$F13="yearly",DATE(YEAR($A13)+CEILING((DATEDIF($A13,'13-week CF Forecast'!$B$1,"y")+1),1)+COLUMN()-7,MONTH($A13),DAY($A13)),TRUE,"") -> 45992 | M13: =IFS($F13="bi-weekly",$A13+CEILING(('13-week CF Forecast'!$B$1-$A13)/14,1)*14+14*(COLUMN()-7),$F13="weekly",$A13+CEILING(('13-week CF Forecast'!$B$1-$A13)/7,1)*7+7*(COLUMN()-7),$F13="monthly",DATE(YEAR($A13),MONTH($A13)+CEILING(DATEDIF($A13,'13-week CF Forecast'!$B$1,"m")+1,1)+COLUMN()-7,DAY($A13)),$F13="quarterly",DATE(YEAR($A13),MONTH($A13)+3*CEILING((DATEDIF($A13,'13-week CF Forecast'!$B$1,"m")+1)/3,1)+(COLUMN()-7)*3,DAY($A13)),$F13="yearly",DATE(YEAR($A13)+CEILING((DATEDIF($A13,'13-week CF Forecast'!$B$1,"y")+1),1)+COLUMN()-7,MONTH($A13),DAY($A13)),TRUE,"") -> 46023 | N13: =IFS($F13="bi-weekly",$A13+CEILING(('13-week CF Forecast'!$B$1-$A13)/14,1)*14+14*(COLUMN()-7),$F13="weekly",$A13+CEILING(('13-week CF Forecast'!$B$1-$A13)/7,1)*7+7*(COLUMN()-7),$F13="monthly",DATE(YEAR($A13),MONTH($A13)+CEILING(DATEDIF($A13,'13-week CF Forecast'!$B$1,"m")+1,1)+COLUMN()-7,DAY($A13)),$F13="quarterly",DATE(YEAR($A13),MONTH($A13)+3*CEILING((DATEDIF($A13,'13-week CF Forecast'!$B$1,"m")+1)/3,1)+(COLUMN()-7)*3,DAY($A13)),$F13="yearly",DATE(YEAR($A13)+CEILING((DATEDIF($A13,'13-week CF Forecast'!$B$1,"y")+1),1)+COLUMN()-7,MONTH($A13),DAY($A13)),TRUE,"") -> 46054 | ... S13: =IFS($F13="bi-weekly",$A13+CEILING(('13-week CF Forecast'!$B$1-$A13)/14,1)*14+14*(COLUMN()-7),$F13="weekly",$A13+CEILING(('13-week CF Forecast'!$B$1-$A13)/7,1)*7+7*(COLUMN()-7),$F13="monthly",DATE(YEAR($A13),MONTH($A13)+CEILING(DATEDIF($A13,'13-week CF Forecast'!$B$1,"m")+1,1)+COLUMN()-7,DAY($A13)),$F13="quarterly",DATE(YEAR($A13),MONTH($A13)+3*CEILING((DATEDIF($A13,'13-week CF Forecast'!$B$1,"m")+1)/3,1)+(COLUMN()-7)*3,DAY($A13)),$F13="yearly",DATE(YEAR($A13)+CEILING((DATEDIF($A13,'13-week CF Forecast'!$B$1,"y")+1),1)+COLUMN()-7,MONTH($A13),DAY($A13)),TRUE,"") -> 46204 | T13: =IFERROR(ROWSDUMMYFUNCTION(UNNEST(PAIR2JSON('Recurring Transactions'!$A$1,'Recurring Transactions'!A13,'Recurring Transactions'!$B$1,'Recurring Transactions'!B13,'Recurring Transactions'!$C$1,'Recurring Transactions'!C13,'Recurring Transactions'!$D$1,'Recurring Transactions'!D13,'Recurring Transactions'!$E$1,'Recurring Transactions'!E13,'Recurring Transactions'!$F$1,'Recurring Transactions'!F13,"Payment schedule",VALUE(RANGE2JSON('Recurring Transactions'!F13,'Recurring Transactions'!G13:S13))))),"[{""First payment date"":""2025-01-01"",""Counterparty"":""Loop Returns"",""Description"":""Loop Returns"",""Amount"":""$500"",""Category"":""Software"",""Frequency"":""monthly"",""Payment schedule_0"":""2025-07-01""},{""First payment date"":""2025-01-01"",""Counterparty"":""Loop Returns"","&"""Description"":""Loop Returns"",""Amount"":""$500"",""Category"":""Software"",""Frequency"":""monthly"",""Payment schedule_0"":""2025-08-01""},{""First payment date"":""2025-01-01"",""Counterparty"":""Loop Returns"",""Description"":""Loop Returns"",""Amount"":""$500"",""Category"":""Software"""&",""Frequency"":""monthly"",""Payment schedule_0"":""2025-09-01""},{""First payment date"":""2025-01-01"",""Counterparty"":""Loop Returns"",""Description"":""Loop Returns"",""Amount"":""$500"",""Category"":""Software"",""Frequency"":""monthly"",""Payment schedule_0"":""2025-10-01""},{""First "&"payment date"":""2025-01-01"",""Counterparty"":""Loop Returns"",""Description"":""Loop Returns"",""Amount"":""$500"",""Category"":""Software"",""Frequency"":""monthly"",""Payment schedule_0"":""2025-11-01""},{""First payment date"":""2025-01-01"",""Counterparty"":""Loop Returns"",""Descript"&"ion"":""Loop Returns"",""Amount"":""$500"",""Category"":""Software"",""Frequency"":""monthly"",""Payment schedule_0"":""2025-12-01""},{""First payment date"":""2025-01-01"",""Counterparty"":""Loop Returns"",""Description"":""Loop Returns"",""Amount"":""$500"",""Category"":""Software"",""Frequen"&"cy"":""monthly"",""Payment schedule_0"":""2026-01-01""},{""First payment date"":""2025-01-01"",""Counterparty"":""Loop Returns"",""Description"":""Loop Returns"",""Amount"":""$500"",""Category"":""Software"",""Frequency"":""monthly"",""Payment schedule_0"":""2026-02-01""},{""First payment d"&"ate"":""2025-01-01"",""Counterparty"":""Loop Returns"",""Description"":""Loop Returns"",""Amount"":""$500"",""Category"":""Software"",""Frequency"":""monthly"",""Payment schedule_0"":""2026-03-01""},{""First payment date"":""2025-01-01"",""Counterparty"":""Loop Returns"",""Description"":""Loo"&"p Returns"",""Amount"":""$500"",""Category"":""Software"",""Frequency"":""monthly"",""Payment schedule_0"":""2026-04-01""},{""First payment date"":""2025-01-01"",""Counterparty"":""Loop Returns"",""Description"":""Loop Returns"",""Amount"":""$500"",""Category"":""Software"",""Frequency"":""mont"&"hly"",""Payment schedule_0"":""2026-05-01""},{""First payment date"":""2025-01-01"",""Counterparty"":""Loop Returns"",""Description"":""Loop Returns"",""Amount"":""$500"",""Category"":""Software"",""Frequency"":""monthly"",""Payment schedule_0"":""2026-06-01""},{""First payment date"":""202"&"5-01-01"",""Counterparty"":""Loop Returns"",""Description"":""Loop Returns"",""Amount"":""$500"",""Category"":""Software"",""Frequency"":""monthly"",""Payment schedule_0"":""2026-07-01""}]") -> [{"First payment date":"2025-01-01","Counterparty":"Loop Returns","Description":"Loop Returns","Amount":"$500","Category":"Software","Frequency":"monthly","Payment schedule_0":"2025-07-01"},{"First payment date":"2025-01-01","Counterparty":"Loop Returns","Description":"Loop Returns","Amount":"$500","Category":"Software","Frequency":"monthly","Payment schedule_0":"2025-08-01"},{"First payment date":"2025-01-01","Counterparty":"Loop Returns","Description":"Loop Returns","Amount":"$500","Category":"Software","Frequency":"monthly","Payment schedule_0":"2025-09-01"},{"First payment date":"2025-01-01","Counterparty":"Loop Returns","Description":"Loop Returns","Amount":"$500","Category":"Software","Frequency":"monthly","Payment schedule_0":"2025-10-01"},{"First payment date":"2025-01-01","Counterparty":"Loop Returns","Description":"Loop Returns","Amount":"$500","Category":"Software","Frequency":"monthly","Payment schedule_0":"2025-11-01"},{"First payment date":"2025-01-01","Counterparty":"Loop Returns","Description":"Loop Returns","Amount":"$500","Category":"Software","Frequency":"monthly","Payment schedule_0":"2025-12-01"},{"First payment date":"2025-01-01","Counterparty":"Loop Returns","Description":"Loop Returns","Amount":"$500","Category":"Software","Frequency":"monthly","Payment schedule_0":"2026-01-01"},{"First payment date":"2025-01-01","Counterparty":"Loop Returns","Description":"Loop Returns","Amount":"$500","Category":"Software","Frequency":"monthly","Payment schedule_0":"2026-02-01"},{"First payment date":"2025-01-01","Counterparty":"Loop Returns","Description":"Loop Returns","Amount":"$500","Category":"Software","Frequency":"monthly","Payment schedule_0":"2026-03-01"},{"First payment date":"2025-01-01","Counterparty":"Loop Returns","Description":"Loop Returns","Amount":"$500","Category":"Software","Frequency":"monthly","Payment schedule_0":"2026-04-01"},{"First payment date":"2025-01-01","Counterparty":"Loop Returns","Description":"Loop Returns","Amount":"$500","Category":"Software","Frequency":"monthly","Payment schedule_0":"2026-05-01"},{"First payment date":"2025-01-01","Counterparty":"Loop Returns","Description":"Loop Returns","Amount":"$500","Category":"Software","Frequency":"monthly","Payment schedule_0":"2026-06-01"},{"First payment date":"2025-01-01","Counterparty":"Loop Returns","Description":"Loop Returns","Amount":"$500","Category":"Software","Frequency":"monthly","Payment schedule_0":"2026-07-01"}] | U13: Chase Inc
A14: 45658 | B14: Forklift | C14: Forklift | D14: 688 | E14: Overhead Expenditures | F14: monthly | G14: =IFS($F14="bi-weekly",$A14+CEILING(('13-week CF Forecast'!$B$1-$A14)/14,1)*14+14*(COLUMN()-7),$F14="weekly",$A14+CEILING(('13-week CF Forecast'!$B$1-$A14)/7,1)*7+7*(COLUMN()-7),$F14="monthly",DATE(YEAR($A14),MONTH($A14)+CEILING(DATEDIF($A14,'13-week CF Forecast'!$B$1,"m")+1,1)+COLUMN()-7,DAY($A14)),$F14="quarterly",DATE(YEAR($A14),MONTH($A14)+3*CEILING((DATEDIF($A14,'13-week CF Forecast'!$B$1,"m")+1)/3,1)+(COLUMN()-7)*3,DAY($A14)),$F14="yearly",DATE(YEAR($A14)+CEILING((DATEDIF($A14,'13-week CF Forecast'!$B$1,"y")+1),1)+COLUMN()-7,MONTH($A14),DAY($A14)),TRUE,"") -> 45839 | H14: =IFS($F14="bi-weekly",$A14+CEILING(('13-week CF Forecast'!$B$1-$A14)/14,1)*14+14*(COLUMN()-7),$F14="weekly",$A14+CEILING(('13-week CF Forecast'!$B$1-$A14)/7,1)*7+7*(COLUMN()-7),$F14="monthly",DATE(YEAR($A14),MONTH($A14)+CEILING(DATEDIF($A14,'13-week CF Forecast'!$B$1,"m")+1,1)+COLUMN()-7,DAY($A14)),$F14="quarterly",DATE(YEAR($A14),MONTH($A14)+3*CEILING((DATEDIF($A14,'13-week CF Forecast'!$B$1,"m")+1)/3,1)+(COLUMN()-7)*3,DAY($A14)),$F14="yearly",DATE(YEAR($A14)+CEILING((DATEDIF($A14,'13-week CF Forecast'!$B$1,"y")+1),1)+COLUMN()-7,MONTH($A14),DAY($A14)),TRUE,"") -> 45870 | I14: =IFS($F14="bi-weekly",$A14+CEILING(('13-week CF Forecast'!$B$1-$A14)/14,1)*14+14*(COLUMN()-7),$F14="weekly",$A14+CEILING(('13-week CF Forecast'!$B$1-$A14)/7,1)*7+7*(COLUMN()-7),$F14="monthly",DATE(YEAR($A14),MONTH($A14)+CEILING(DATEDIF($A14,'13-week CF Forecast'!$B$1,"m")+1,1)+COLUMN()-7,DAY($A14)),$F14="quarterly",DATE(YEAR($A14),MONTH($A14)+3*CEILING((DATEDIF($A14,'13-week CF Forecast'!$B$1,"m")+1)/3,1)+(COLUMN()-7)*3,DAY($A14)),$F14="yearly",DATE(YEAR($A14)+CEILING((DATEDIF($A14,'13-week CF Forecast'!$B$1,"y")+1),1)+COLUMN()-7,MONTH($A14),DAY($A14)),TRUE,"") -> 45901 | J14: =IFS($F14="bi-weekly",$A14+CEILING(('13-week CF Forecast'!$B$1-$A14)/14,1)*14+14*(COLUMN()-7),$F14="weekly",$A14+CEILING(('13-week CF Forecast'!$B$1-$A14)/7,1)*7+7*(COLUMN()-7),$F14="monthly",DATE(YEAR($A14),MONTH($A14)+CEILING(DATEDIF($A14,'13-week CF Forecast'!$B$1,"m")+1,1)+COLUMN()-7,DAY($A14)),$F14="quarterly",DATE(YEAR($A14),MONTH($A14)+3*CEILING((DATEDIF($A14,'13-week CF Forecast'!$B$1,"m")+1)/3,1)+(COLUMN()-7)*3,DAY($A14)),$F14="yearly",DATE(YEAR($A14)+CEILING((DATEDIF($A14,'13-week CF Forecast'!$B$1,"y")+1),1)+COLUMN()-7,MONTH($A14),DAY($A14)),TRUE,"") -> 45931 | K14: =IFS($F14="bi-weekly",$A14+CEILING(('13-week CF Forecast'!$B$1-$A14)/14,1)*14+14*(COLUMN()-7),$F14="weekly",$A14+CEILING(('13-week CF Forecast'!$B$1-$A14)/7,1)*7+7*(COLUMN()-7),$F14="monthly",DATE(YEAR($A14),MONTH($A14)+CEILING(DATEDIF($A14,'13-week CF Forecast'!$B$1,"m")+1,1)+COLUMN()-7,DAY($A14)),$F14="quarterly",DATE(YEAR($A14),MONTH($A14)+3*CEILING((DATEDIF($A14,'13-week CF Forecast'!$B$1,"m")+1)/3,1)+(COLUMN()-7)*3,DAY($A14)),$F14="yearly",DATE(YEAR($A14)+CEILING((DATEDIF($A14,'13-week CF Forecast'!$B$1,"y")+1),1)+COLUMN()-7,MONTH($A14),DAY($A14)),TRUE,"") -> 45962 | L14: =IFS($F14="bi-weekly",$A14+CEILING(('13-week CF Forecast'!$B$1-$A14)/14,1)*14+14*(COLUMN()-7),$F14="weekly",$A14+CEILING(('13-week CF Forecast'!$B$1-$A14)/7,1)*7+7*(COLUMN()-7),$F14="monthly",DATE(YEAR($A14),MONTH($A14)+CEILING(DATEDIF($A14,'13-week CF Forecast'!$B$1,"m")+1,1)+COLUMN()-7,DAY($A14)),$F14="quarterly",DATE(YEAR($A14),MONTH($A14)+3*CEILING((DATEDIF($A14,'13-week CF Forecast'!$B$1,"m")+1)/3,1)+(COLUMN()-7)*3,DAY($A14)),$F14="yearly",DATE(YEAR($A14)+CEILING((DATEDIF($A14,'13-week CF Forecast'!$B$1,"y")+1),1)+COLUMN()-7,MONTH($A14),DAY($A14)),TRUE,"") -> 45992 | M14: =IFS($F14="bi-weekly",$A14+CEILING(('13-week CF Forecast'!$B$1-$A14)/14,1)*14+14*(COLUMN()-7),$F14="weekly",$A14+CEILING(('13-week CF Forecast'!$B$1-$A14)/7,1)*7+7*(COLUMN()-7),$F14="monthly",DATE(YEAR($A14),MONTH($A14)+CEILING(DATEDIF($A14,'13-week CF Forecast'!$B$1,"m")+1,1)+COLUMN()-7,DAY($A14)),$F14="quarterly",DATE(YEAR($A14),MONTH($A14)+3*CEILING((DATEDIF($A14,'13-week CF Forecast'!$B$1,"m")+1)/3,1)+(COLUMN()-7)*3,DAY($A14)),$F14="yearly",DATE(YEAR($A14)+CEILING((DATEDIF($A14,'13-week CF Forecast'!$B$1,"y")+1),1)+COLUMN()-7,MONTH($A14),DAY($A14)),TRUE,"") -> 46023 | N14: =IFS($F14="bi-weekly",$A14+CEILING(('13-week CF Forecast'!$B$1-$A14)/14,1)*14+14*(COLUMN()-7),$F14="weekly",$A14+CEILING(('13-week CF Forecast'!$B$1-$A14)/7,1)*7+7*(COLUMN()-7),$F14="monthly",DATE(YEAR($A14),MONTH($A14)+CEILING(DATEDIF($A14,'13-week CF Forecast'!$B$1,"m")+1,1)+COLUMN()-7,DAY($A14)),$F14="quarterly",DATE(YEAR($A14),MONTH($A14)+3*CEILING((DATEDIF($A14,'13-week CF Forecast'!$B$1,"m")+1)/3,1)+(COLUMN()-7)*3,DAY($A14)),$F14="yearly",DATE(YEAR($A14)+CEILING((DATEDIF($A14,'13-week CF Forecast'!$B$1,"y")+1),1)+COLUMN()-7,MONTH($A14),DAY($A14)),TRUE,"") -> 46054 | ... S14: =IFS($F14="bi-weekly",$A14+CEILING(('13-week CF Forecast'!$B$1-$A14)/14,1)*14+14*(COLUMN()-7),$F14="weekly",$A14+CEILING(('13-week CF Forecast'!$B$1-$A14)/7,1)*7+7*(COLUMN()-7),$F14="monthly",DATE(YEAR($A14),MONTH($A14)+CEILING(DATEDIF($A14,'13-week CF Forecast'!$B$1,"m")+1,1)+COLUMN()-7,DAY($A14)),$F14="quarterly",DATE(YEAR($A14),MONTH($A14)+3*CEILING((DATEDIF($A14,'13-week CF Forecast'!$B$1,"m")+1)/3,1)+(COLUMN()-7)*3,DAY($A14)),$F14="yearly",DATE(YEAR($A14)+CEILING((DATEDIF($A14,'13-week CF Forecast'!$B$1,"y")+1),1)+COLUMN()-7,MONTH($A14),DAY($A14)),TRUE,"") -> 46204 | T14: =IFERROR(ROWSDUMMYFUNCTION(UNNEST(PAIR2JSON('Recurring Transactions'!$A$1,'Recurring Transactions'!A14,'Recurring Transactions'!$B$1,'Recurring Transactions'!B14,'Recurring Transactions'!$C$1,'Recurring Transactions'!C14,'Recurring Transactions'!$D$1,'Recurring Transactions'!D14,'Recurring Transactions'!$E$1,'Recurring Transactions'!E14,'Recurring Transactions'!$F$1,'Recurring Transactions'!F14,"Payment schedule",VALUE(RANGE2JSON('Recurring Transactions'!F14,'Recurring Transactions'!G14:S14))))),"[{""First payment date"":""2025-01-01"",""Counterparty"":""Forklift"",""Description"":""Forklift"",""Amount"":""$688"",""Category"":""Overhead Expenditures"",""Frequency"":""monthly"",""Payment schedule_0"":""2025-07-01""},{""First payment date"":""2025-01-01"",""Counterparty"":""Forklift"""&",""Description"":""Forklift"",""Amount"":""$688"",""Category"":""Overhead Expenditures"",""Frequency"":""monthly"",""Payment schedule_0"":""2025-08-01""},{""First payment date"":""2025-01-01"",""Counterparty"":""Forklift"",""Description"":""Forklift"",""Amount"":""$688"",""Category"":""Overhea"&"d Expenditures"",""Frequency"":""monthly"",""Payment schedule_0"":""2025-09-01""},{""First payment date"":""2025-01-01"",""Counterparty"":""Forklift"",""Description"":""Forklift"",""Amount"":""$688"",""Category"":""Overhead Expenditures"",""Frequency"":""monthly"",""Payment schedule_0"":""2"&"025-10-01""},{""First payment date"":""2025-01-01"",""Counterparty"":""Forklift"",""Description"":""Forklift"",""Amount"":""$688"",""Category"":""Overhead Expenditures"",""Frequency"":""monthly"",""Payment schedule_0"":""2025-11-01""},{""First payment date"":""2025-01-01"",""Counterparty"""&":""Forklift"",""Description"":""Forklift"",""Amount"":""$688"",""Category"":""Overhead Expenditures"",""Frequency"":""monthly"",""Payment schedule_0"":""2025-12-01""},{""First payment date"":""2025-01-01"",""Counterparty"":""Forklift"",""Description"":""Forklift"",""Amount"":""$688"",""Categor"&"y"":""Overhead Expenditures"",""Frequency"":""monthly"",""Payment schedule_0"":""2026-01-01""},{""First payment date"":""2025-01-01"",""Counterparty"":""Forklift"",""Description"":""Forklift"",""Amount"":""$688"",""Category"":""Overhead Expenditures"",""Frequency"":""monthly"",""Payment sch"&"edule_0"":""2026-02-01""},{""First payment date"":""2025-01-01"",""Counterparty"":""Forklift"",""Description"":""Forklift"",""Amount"":""$688"",""Category"":""Overhead Expenditures"",""Frequency"":""monthly"",""Payment schedule_0"":""2026-03-01""},{""First payment date"":""2025-01-01"",""Co"&"unterparty"":""Forklift"",""Description"":""Forklift"",""Amount"":""$688"",""Category"":""Overhead Expenditures"",""Frequency"":""monthly"",""Payment schedule_0"":""2026-04-01""},{""First payment date"":""2025-01-01"",""Counterparty"":""Forklift"",""Description"":""Forklift"",""Amount"":""$68"&"8"",""Category"":""Overhead Expenditures"",""Frequency"":""monthly"",""Payment schedule_0"":""2026-05-01""},{""First payment date"":""2025-01-01"",""Counterparty"":""Forklift"",""Description"":""Forklift"",""Amount"":""$688"",""Category"":""Overhead Expenditures"",""Frequency"":""monthly"","""&"Payment schedule_0"":""2026-06-01""},{""First payment date"":""2025-01-01"",""Counterparty"":""Forklift"",""Description"":""Forklift"",""Amount"":""$688"",""Category"":""Overhead Expenditures"",""Frequency"":""monthly"",""Payment schedule_0"":""2026-07-01""}]") -> [{"First payment date":"2025-01-01","Counterparty":"Forklift","Description":"Forklift","Amount":"$688","Category":"Overhead Expenditures","Frequency":"monthly","Payment schedule_0":"2025-07-01"},{"First payment date":"2025-01-01","Counterparty":"Forklift","Description":"Forklift","Amount":"$688","Category":"Overhead Expenditures","Frequency":"monthly","Payment schedule_0":"2025-08-01"},{"First payment date":"2025-01-01","Counterparty":"Forklift","Description":"Forklift","Amount":"$688","Category":"Overhead Expenditures","Frequency":"monthly","Payment schedule_0":"2025-09-01"},{"First payment date":"2025-01-01","Counterparty":"Forklift","Description":"Forklift","Amount":"$688","Category":"Overhead Expenditures","Frequency":"monthly","Payment schedule_0":"2025-10-01"},{"First payment date":"2025-01-01","Counterparty":"Forklift","Description":"Forklift","Amount":"$688","Category":"Overhead Expenditures","Frequency":"monthly","Payment schedule_0":"2025-11-01"},{"First payment date":"2025-01-01","Counterparty":"Forklift","Description":"Forklift","Amount":"$688","Category":"Overhead Expenditures","Frequency":"monthly","Payment schedule_0":"2025-12-01"},{"First payment date":"2025-01-01","Counterparty":"Forklift","Description":"Forklift","Amount":"$688","Category":"Overhead Expenditures","Frequency":"monthly","Payment schedule_0":"2026-01-01"},{"First payment date":"2025-01-01","Counterparty":"Forklift","Description":"Forklift","Amount":"$688","Category":"Overhead Expenditures","Frequency":"monthly","Payment schedule_0":"2026-02-01"},{"First payment date":"2025-01-01","Counterparty":"Forklift","Description":"Forklift","Amount":"$688","Category":"Overhead Expenditures","Frequency":"monthly","Payment schedule_0":"2026-03-01"},{"First payment date":"2025-01-01","Counterparty":"Forklift","Description":"Forklift","Amount":"$688","Category":"Overhead Expenditures","Frequency":"monthly","Payment schedule_0":"2026-04-01"},{"First payment date":"2025-01-01","Counterparty":"Forklift","Description":"Forklift","Amount":"$688","Category":"Overhead Expenditures","Frequency":"monthly","Payment schedule_0":"2026-05-01"},{"First payment date":"2025-01-01","Counterparty":"Forklift","Description":"Forklift","Amount":"$688","Category":"Overhead Expenditures","Frequency":"monthly","Payment schedule_0":"2026-06-01"},{"First payment date":"2025-01-01","Counterparty":"Forklift","Description":"Forklift","Amount":"$688","Category":"Overhead Expenditures","Frequency":"monthly","Payment schedule_0":"2026-07-01"}] | U14: Staychill
A15: 45658 | B15: Bobby/Peggy | C15: Bobby/Peggy | D15: 2500 | E15: Interest Expenditures | F15: quarterly | G15: =IFS($F15="bi-weekly",$A15+CEILING(('13-week CF Forecast'!$B$1-$A15)/14,1)*14+14*(COLUMN()-7),$F15="weekly",$A15+CEILING(('13-week CF Forecast'!$B$1-$A15)/7,1)*7+7*(COLUMN()-7),$F15="monthly",DATE(YEAR($A15),MONTH($A15)+CEILING(DATEDIF($A15,'13-week CF Forecast'!$B$1,"m")+1,1)+COLUMN()-7,DAY($A15)),$F15="quarterly",DATE(YEAR($A15),MONTH($A15)+3*CEILING((DATEDIF($A15,'13-week CF Forecast'!$B$1,"m")+1)/3,1)+(COLUMN()-7)*3,DAY($A15)),$F15="yearly",DATE(YEAR($A15)+CEILING((DATEDIF($A15,'13-week CF Forecast'!$B$1,"y")+1),1)+COLUMN()-7,MONTH($A15),DAY($A15)),TRUE,"") -> 45839 | H15: =IFS($F15="bi-weekly",$A15+CEILING(('13-week CF Forecast'!$B$1-$A15)/14,1)*14+14*(COLUMN()-7),$F15="weekly",$A15+CEILING(('13-week CF Forecast'!$B$1-$A15)/7,1)*7+7*(COLUMN()-7),$F15="monthly",DATE(YEAR($A15),MONTH($A15)+CEILING(DATEDIF($A15,'13-week CF Forecast'!$B$1,"m")+1,1)+COLUMN()-7,DAY($A15)),$F15="quarterly",DATE(YEAR($A15),MONTH($A15)+3*CEILING((DATEDIF($A15,'13-week CF Forecast'!$B$1,"m")+1)/3,1)+(COLUMN()-7)*3,DAY($A15)),$F15="yearly",DATE(YEAR($A15)+CEILING((DATEDIF($A15,'13-week CF Forecast'!$B$1,"y")+1),1)+COLUMN()-7,MONTH($A15),DAY($A15)),TRUE,"") -> 45931 | I15: =IFS($F15="bi-weekly",$A15+CEILING(('13-week CF Forecast'!$B$1-$A15)/14,1)*14+14*(COLUMN()-7),$F15="weekly",$A15+CEILING(('13-week CF Forecast'!$B$1-$A15)/7,1)*7+7*(COLUMN()-7),$F15="monthly",DATE(YEAR($A15),MONTH($A15)+CEILING(DATEDIF($A15,'13-week CF Forecast'!$B$1,"m")+1,1)+COLUMN()-7,DAY($A15)),$F15="quarterly",DATE(YEAR($A15),MONTH($A15)+3*CEILING((DATEDIF($A15,'13-week CF Forecast'!$B$1,"m")+1)/3,1)+(COLUMN()-7)*3,DAY($A15)),$F15="yearly",DATE(YEAR($A15)+CEILING((DATEDIF($A15,'13-week CF Forecast'!$B$1,"y")+1),1)+COLUMN()-7,MONTH($A15),DAY($A15)),TRUE,"") -> 46023 | J15: =IFS($F15="bi-weekly",$A15+CEILING(('13-week CF Forecast'!$B$1-$A15)/14,1)*14+14*(COLUMN()-7),$F15="weekly",$A15+CEILING(('13-week CF Forecast'!$B$1-$A15)/7,1)*7+7*(COLUMN()-7),$F15="monthly",DATE(YEAR($A15),MONTH($A15)+CEILING(DATEDIF($A15,'13-week CF Forecast'!$B$1,"m")+1,1)+COLUMN()-7,DAY($A15)),$F15="quarterly",DATE(YEAR($A15),MONTH($A15)+3*CEILING((DATEDIF($A15,'13-week CF Forecast'!$B$1,"m")+1)/3,1)+(COLUMN()-7)*3,DAY($A15)),$F15="yearly",DATE(YEAR($A15)+CEILING((DATEDIF($A15,'13-week CF Forecast'!$B$1,"y")+1),1)+COLUMN()-7,MONTH($A15),DAY($A15)),TRUE,"") -> 46113 | K15: =IFS($F15="bi-weekly",$A15+CEILING(('13-week CF Forecast'!$B$1-$A15)/14,1)*14+14*(COLUMN()-7),$F15="weekly",$A15+CEILING(('13-week CF Forecast'!$B$1-$A15)/7,1)*7+7*(COLUMN()-7),$F15="monthly",DATE(YEAR($A15),MONTH($A15)+CEILING(DATEDIF($A15,'13-week CF Forecast'!$B$1,"m")+1,1)+COLUMN()-7,DAY($A15)),$F15="quarterly",DATE(YEAR($A15),MONTH($A15)+3*CEILING((DATEDIF($A15,'13-week CF Forecast'!$B$1,"m")+1)/3,1)+(COLUMN()-7)*3,DAY($A15)),$F15="yearly",DATE(YEAR($A15)+CEILING((DATEDIF($A15,'13-week CF Forecast'!$B$1,"y")+1),1)+COLUMN()-7,MONTH($A15),DAY($A15)),TRUE,"") -> 46204 | L15: =IFS($F15="bi-weekly",$A15+CEILING(('13-week CF Forecast'!$B$1-$A15)/14,1)*14+14*(COLUMN()-7),$F15="weekly",$A15+CEILING(('13-week CF Forecast'!$B$1-$A15)/7,1)*7+7*(COLUMN()-7),$F15="monthly",DATE(YEAR($A15),MONTH($A15)+CEILING(DATEDIF($A15,'13-week CF Forecast'!$B$1,"m")+1,1)+COLUMN()-7,DAY($A15)),$F15="quarterly",DATE(YEAR($A15),MONTH($A15)+3*CEILING((DATEDIF($A15,'13-week CF Forecast'!$B$1,"m")+1)/3,1)+(COLUMN()-7)*3,DAY($A15)),$F15="yearly",DATE(YEAR($A15)+CEILING((DATEDIF($A15,'13-week CF Forecast'!$B$1,"y")+1),1)+COLUMN()-7,MONTH($A15),DAY($A15)),TRUE,"") -> 46296 | M15: =IFS($F15="bi-weekly",$A15+CEILING(('13-week CF Forecast'!$B$1-$A15)/14,1)*14+14*(COLUMN()-7),$F15="weekly",$A15+CEILING(('13-week CF Forecast'!$B$1-$A15)/7,1)*7+7*(COLUMN()-7),$F15="monthly",DATE(YEAR($A15),MONTH($A15)+CEILING(DATEDIF($A15,'13-week CF Forecast'!$B$1,"m")+1,1)+COLUMN()-7,DAY($A15)),$F15="quarterly",DATE(YEAR($A15),MONTH($A15)+3*CEILING((DATEDIF($A15,'13-week CF Forecast'!$B$1,"m")+1)/3,1)+(COLUMN()-7)*3,DAY($A15)),$F15="yearly",DATE(YEAR($A15)+CEILING((DATEDIF($A15,'13-week CF Forecast'!$B$1,"y")+1),1)+COLUMN()-7,MONTH($A15),DAY($A15)),TRUE,"") -> 46388 | N15: =IFS($F15="bi-weekly",$A15+CEILING(('13-week CF Forecast'!$B$1-$A15)/14,1)*14+14*(COLUMN()-7),$F15="weekly",$A15+CEILING(('13-week CF Forecast'!$B$1-$A15)/7,1)*7+7*(COLUMN()-7),$F15="monthly",DATE(YEAR($A15),MONTH($A15)+CEILING(DATEDIF($A15,'13-week CF Forecast'!$B$1,"m")+1,1)+COLUMN()-7,DAY($A15)),$F15="quarterly",DATE(YEAR($A15),MONTH($A15)+3*CEILING((DATEDIF($A15,'13-week CF Forecast'!$B$1,"m")+1)/3,1)+(COLUMN()-7)*3,DAY($A15)),$F15="yearly",DATE(YEAR($A15)+CEILING((DATEDIF($A15,'13-week CF Forecast'!$B$1,"y")+1),1)+COLUMN()-7,MONTH($A15),DAY($A15)),TRUE,"") -> 46478 | ... S15: =IFS($F15="bi-weekly",$A15+CEILING(('13-week CF Forecast'!$B$1-$A15)/14,1)*14+14*(COLUMN()-7),$F15="weekly",$A15+CEILING(('13-week CF Forecast'!$B$1-$A15)/7,1)*7+7*(COLUMN()-7),$F15="monthly",DATE(YEAR($A15),MONTH($A15)+CEILING(DATEDIF($A15,'13-week CF Forecast'!$B$1,"m")+1,1)+COLUMN()-7,DAY($A15)),$F15="quarterly",DATE(YEAR($A15),MONTH($A15)+3*CEILING((DATEDIF($A15,'13-week CF Forecast'!$B$1,"m")+1)/3,1)+(COLUMN()-7)*3,DAY($A15)),$F15="yearly",DATE(YEAR($A15)+CEILING((DATEDIF($A15,'13-week CF Forecast'!$B$1,"y")+1),1)+COLUMN()-7,MONTH($A15),DAY($A15)),TRUE,"") -> 46935 | T15: =IFERROR(ROWSDUMMYFUNCTION(UNNEST(PAIR2JSON('Recurring Transactions'!$A$1,'Recurring Transactions'!A15,'Recurring Transactions'!$B$1,'Recurring Transactions'!B15,'Recurring Transactions'!$C$1,'Recurring Transactions'!C15,'Recurring Transactions'!$D$1,'Recurring Transactions'!D15,'Recurring Transactions'!$E$1,'Recurring Transactions'!E15,'Recurring Transactions'!$F$1,'Recurring Transactions'!F15,"Payment schedule",VALUE(RANGE2JSON('Recurring Transactions'!F15,'Recurring Transactions'!G15:S15))))),"[{""First payment date"":""2025-01-01"",""Counterparty"":""Bobby/Peggy"",""Description"":""Bobby/Peggy"",""Amount"":""$2500"",""Category"":""Interest Expenditures"",""Frequency"":""quarterly"",""Payment schedule_0"":""2025-07-01""},{""First payment date"":""2025-01-01"",""Counterparty"":"""&"Bobby/Peggy"",""Description"":""Bobby/Peggy"",""Amount"":""$2500"",""Category"":""Interest Expenditures"",""Frequency"":""quarterly"",""Payment schedule_0"":""2025-10-01""},{""First payment date"":""2025-01-01"",""Counterparty"":""Bobby/Peggy"",""Description"":""Bobby/Peggy"",""Amount"":""$"&"2500"",""Category"":""Interest Expenditures"",""Frequency"":""quarterly"",""Payment schedule_0"":""2026-01-01""},{""First payment date"":""2025-01-01"",""Counterparty"":""Bobby/Peggy"",""Description"":""Bobby/Peggy"",""Amount"":""$2500"",""Category"":""Interest Expenditures"",""Frequency"""&":""quarterly"",""Payment schedule_0"":""2026-04-01""},{""First payment date"":""2025-01-01"",""Counterparty"":""Bobby/Peggy"",""Description"":""Bobby/Peggy"",""Amount"":""$2500"",""Category"":""Interest Expenditures"",""Frequency"":""quarterly"",""Payment schedule_0"":""2026-07-01""},{""Fi"&"rst payment date"":""2025-01-01"",""Counterparty"":""Bobby/Peggy"",""Description"":""Bobby/Peggy"",""Amount"":""$2500"",""Category"":""Interest Expenditures"",""Frequency"":""quarterly"",""Payment schedule_0"":""2026-10-01""},{""First payment date"":""2025-01-01"",""Counterparty"":""Bobby"&"/Peggy"",""Description"":""Bobby/Peggy"",""Amount"":""$2500"",""Category"":""Interest Expenditures"",""Frequency"":""quarterly"",""Payment schedule_0"":""2027-01-01""},{""First payment date"":""2025-01-01"",""Counterparty"":""Bobby/Peggy"",""Description"":""Bobby/Peggy"",""Amount"":""$2500"""&",""Category"":""Interest Expenditures"",""Frequency"":""quarterly"",""Payment schedule_0"":""2027-04-01""},{""First payment date"":""2025-01-01"",""Counterparty"":""Bobby/Peggy"",""Description"":""Bobby/Peggy"",""Amount"":""$2500"",""Category"":""Interest Expenditures"",""Frequency"":""qua"&"rterly"",""Payment schedule_0"":""2027-07-01""},{""First payment date"":""2025-01-01"",""Counterparty"":""Bobby/Peggy"",""Description"":""Bobby/Peggy"",""Amount"":""$2500"",""Category"":""Interest Expenditures"",""Frequency"":""quarterly"",""Payment schedule_0"":""2027-10-01""},{""First p"&"ayment date"":""2025-01-01"",""Counterparty"":""Bobby/Peggy"",""Description"":""Bobby/Peggy"",""Amount"":""$2500"",""Category"":""Interest Expenditures"",""Frequency"":""quarterly"",""Payment schedule_0"":""2028-01-01""},{""First payment date"":""2025-01-01"",""Counterparty"":""Bobby/Pegg"&"y"",""Description"":""Bobby/Peggy"",""Amount"":""$2500"",""Category"":""Interest Expenditures"",""Frequency"":""quarterly"",""Payment schedule_0"":""2028-04-01""},{""First payment date"":""2025-01-01"",""Counterparty"":""Bobby/Peggy"",""Description"":""Bobby/Peggy"",""Amount"":""$2500"",""Cat"&"egory"":""Interest Expenditures"",""Frequency"":""quarterly"",""Payment schedule_0"":""2028-07-01""}]") -> [{"First payment date":"2025-01-01","Counterparty":"Bobby/Peggy","Description":"Bobby/Peggy","Amount":"$2500","Category":"Interest Expenditures","Frequency":"quarterly","Payment schedule_0":"2025-07-01"},{"First payment date":"2025-01-01","Counterparty":"Bobby/Peggy","Description":"Bobby/Peggy","Amount":"$2500","Category":"Interest Expenditures","Frequency":"quarterly","Payment schedule_0":"2025-10-01"},{"First payment date":"2025-01-01","Counterparty":"Bobby/Peggy","Description":"Bobby/Peggy","Amount":"$2500","Category":"Interest Expenditures","Frequency":"quarterly","Payment schedule_0":"2026-01-01"},{"First payment date":"2025-01-01","Counterparty":"Bobby/Peggy","Description":"Bobby/Peggy","Amount":"$2500","Category":"Interest Expenditures","Frequency":"quarterly","Payment schedule_0":"2026-04-01"},{"First payment date":"2025-01-01","Counterparty":"Bobby/Peggy","Description":"Bobby/Peggy","Amount":"$2500","Category":"Interest Expenditures","Frequency":"quarterly","Payment schedule_0":"2026-07-01"},{"First payment date":"2025-01-01","Counterparty":"Bobby/Peggy","Description":"Bobby/Peggy","Amount":"$2500","Category":"Interest Expenditures","Frequency":"quarterly","Payment schedule_0":"2026-10-01"},{"First payment date":"2025-01-01","Counterparty":"Bobby/Peggy","Description":"Bobby/Peggy","Amount":"$2500","Category":"Interest Expenditures","Frequency":"quarterly","Payment schedule_0":"2027-01-01"},{"First payment date":"2025-01-01","Counterparty":"Bobby/Peggy","Description":"Bobby/Peggy","Amount":"$2500","Category":"Interest Expenditures","Frequency":"quarterly","Payment schedule_0":"2027-04-01"},{"First payment date":"2025-01-01","Counterparty":"Bobby/Peggy","Description":"Bobby/Peggy","Amount":"$2500","Category":"Interest Expenditures","Frequency":"quarterly","Payment schedule_0":"2027-07-01"},{"First payment date":"2025-01-01","Counterparty":"Bobby/Peggy","Description":"Bobby/Peggy","Amount":"$2500","Category":"Interest Expenditures","Frequency":"quarterly","Payment schedule_0":"2027-10-01"},{"First payment date":"2025-01-01","Counterparty":"Bobby/Peggy","Description":"Bobby/Peggy","Amount":"$2500","Category":"Interest Expenditures","Frequency":"quarterly","Payment schedule_0":"2028-01-01"},{"First payment date":"2025-01-01","Counterparty":"Bobby/Peggy","Description":"Bobby/Peggy","Amount":"$2500","Category":"Interest Expenditures","Frequency":"quarterly","Payment schedule_0":"2028-04-01"},{"First payment date":"2025-01-01","Counterparty":"Bobby/Peggy","Description":"Bobby/Peggy","Amount":"$2500","Category":"Interest Expenditures","Frequency":"quarterly","Payment schedule_0":"2028-07-01"}] | U15: Staychill
A16: 45658 | B16: Easyship | C16: Easyship | D16: 100 | E16: Software | F16: monthly | G16: =IFS($F16="bi-weekly",$A16+CEILING(('13-week CF Forecast'!$B$1-$A16)/14,1)*14+14*(COLUMN()-7),$F16="weekly",$A16+CEILING(('13-week CF Forecast'!$B$1-$A16)/7,1)*7+7*(COLUMN()-7),$F16="monthly",DATE(YEAR($A16),MONTH($A16)+CEILING(DATEDIF($A16,'13-week CF Forecast'!$B$1,"m")+1,1)+COLUMN()-7,DAY($A16)),$F16="quarterly",DATE(YEAR($A16),MONTH($A16)+3*CEILING((DATEDIF($A16,'13-week CF Forecast'!$B$1,"m")+1)/3,1)+(COLUMN()-7)*3,DAY($A16)),$F16="yearly",DATE(YEAR($A16)+CEILING((DATEDIF($A16,'13-week CF Forecast'!$B$1,"y")+1),1)+COLUMN()-7,MONTH($A16),DAY($A16)),TRUE,"") -> 45839 | H16: =IFS($F16="bi-weekly",$A16+CEILING(('13-week CF Forecast'!$B$1-$A16)/14,1)*14+14*(COLUMN()-7),$F16="weekly",$A16+CEILING(('13-week CF Forecast'!$B$1-$A16)/7,1)*7+7*(COLUMN()-7),$F16="monthly",DATE(YEAR($A16),MONTH($A16)+CEILING(DATEDIF($A16,'13-week CF Forecast'!$B$1,"m")+1,1)+COLUMN()-7,DAY($A16)),$F16="quarterly",DATE(YEAR($A16),MONTH($A16)+3*CEILING((DATEDIF($A16,'13-week CF Forecast'!$B$1,"m")+1)/3,1)+(COLUMN()-7)*3,DAY($A16)),$F16="yearly",DATE(YEAR($A16)+CEILING((DATEDIF($A16,'13-week CF Forecast'!$B$1,"y")+1),1)+COLUMN()-7,MONTH($A16),DAY($A16)),TRUE,"") -> 45870 | I16: =IFS($F16="bi-weekly",$A16+CEILING(('13-week CF Forecast'!$B$1-$A16)/14,1)*14+14*(COLUMN()-7),$F16="weekly",$A16+CEILING(('13-week CF Forecast'!$B$1-$A16)/7,1)*7+7*(COLUMN()-7),$F16="monthly",DATE(YEAR($A16),MONTH($A16)+CEILING(DATEDIF($A16,'13-week CF Forecast'!$B$1,"m")+1,1)+COLUMN()-7,DAY($A16)),$F16="quarterly",DATE(YEAR($A16),MONTH($A16)+3*CEILING((DATEDIF($A16,'13-week CF Forecast'!$B$1,"m")+1)/3,1)+(COLUMN()-7)*3,DAY($A16)),$F16="yearly",DATE(YEAR($A16)+CEILING((DATEDIF($A16,'13-week CF Forecast'!$B$1,"y")+1),1)+COLUMN()-7,MONTH($A16),DAY($A16)),TRUE,"") -> 45901 | J16: =IFS($F16="bi-weekly",$A16+CEILING(('13-week CF Forecast'!$B$1-$A16)/14,1)*14+14*(COLUMN()-7),$F16="weekly",$A16+CEILING(('13-week CF Forecast'!$B$1-$A16)/7,1)*7+7*(COLUMN()-7),$F16="monthly",DATE(YEAR($A16),MONTH($A16)+CEILING(DATEDIF($A16,'13-week CF Forecast'!$B$1,"m")+1,1)+COLUMN()-7,DAY($A16)),$F16="quarterly",DATE(YEAR($A16),MONTH($A16)+3*CEILING((DATEDIF($A16,'13-week CF Forecast'!$B$1,"m")+1)/3,1)+(COLUMN()-7)*3,DAY($A16)),$F16="yearly",DATE(YEAR($A16)+CEILING((DATEDIF($A16,'13-week CF Forecast'!$B$1,"y")+1),1)+COLUMN()-7,MONTH($A16),DAY($A16)),TRUE,"") -> 45931 | K16: =IFS($F16="bi-weekly",$A16+CEILING(('13-week CF Forecast'!$B$1-$A16)/14,1)*14+14*(COLUMN()-7),$F16="weekly",$A16+CEILING(('13-week CF Forecast'!$B$1-$A16)/7,1)*7+7*(COLUMN()-7),$F16="monthly",DATE(YEAR($A16),MONTH($A16)+CEILING(DATEDIF($A16,'13-week CF Forecast'!$B$1,"m")+1,1)+COLUMN()-7,DAY($A16)),$F16="quarterly",DATE(YEAR($A16),MONTH($A16)+3*CEILING((DATEDIF($A16,'13-week CF Forecast'!$B$1,"m")+1)/3,1)+(COLUMN()-7)*3,DAY($A16)),$F16="yearly",DATE(YEAR($A16)+CEILING((DATEDIF($A16,'13-week CF Forecast'!$B$1,"y")+1),1)+COLUMN()-7,MONTH($A16),DAY($A16)),TRUE,"") -> 45962 | L16: =IFS($F16="bi-weekly",$A16+CEILING(('13-week CF Forecast'!$B$1-$A16)/14,1)*14+14*(COLUMN()-7),$F16="weekly",$A16+CEILING(('13-week CF Forecast'!$B$1-$A16)/7,1)*7+7*(COLUMN()-7),$F16="monthly",DATE(YEAR($A16),MONTH($A16)+CEILING(DATEDIF($A16,'13-week CF Forecast'!$B$1,"m")+1,1)+COLUMN()-7,DAY($A16)),$F16="quarterly",DATE(YEAR($A16),MONTH($A16)+3*CEILING((DATEDIF($A16,'13-week CF Forecast'!$B$1,"m")+1)/3,1)+(COLUMN()-7)*3,DAY($A16)),$F16="yearly",DATE(YEAR($A16)+CEILING((DATEDIF($A16,'13-week CF Forecast'!$B$1,"y")+1),1)+COLUMN()-7,MONTH($A16),DAY($A16)),TRUE,"") -> 45992 | M16: =IFS($F16="bi-weekly",$A16+CEILING(('13-week CF Forecast'!$B$1-$A16)/14,1)*14+14*(COLUMN()-7),$F16="weekly",$A16+CEILING(('13-week CF Forecast'!$B$1-$A16)/7,1)*7+7*(COLUMN()-7),$F16="monthly",DATE(YEAR($A16),MONTH($A16)+CEILING(DATEDIF($A16,'13-week CF Forecast'!$B$1,"m")+1,1)+COLUMN()-7,DAY($A16)),$F16="quarterly",DATE(YEAR($A16),MONTH($A16)+3*CEILING((DATEDIF($A16,'13-week CF Forecast'!$B$1,"m")+1)/3,1)+(COLUMN()-7)*3,DAY($A16)),$F16="yearly",DATE(YEAR($A16)+CEILING((DATEDIF($A16,'13-week CF Forecast'!$B$1,"y")+1),1)+COLUMN()-7,MONTH($A16),DAY($A16)),TRUE,"") -> 46023 | N16: =IFS($F16="bi-weekly",$A16+CEILING(('13-week CF Forecast'!$B$1-$A16)/14,1)*14+14*(COLUMN()-7),$F16="weekly",$A16+CEILING(('13-week CF Forecast'!$B$1-$A16)/7,1)*7+7*(COLUMN()-7),$F16="monthly",DATE(YEAR($A16),MONTH($A16)+CEILING(DATEDIF($A16,'13-week CF Forecast'!$B$1,"m")+1,1)+COLUMN()-7,DAY($A16)),$F16="quarterly",DATE(YEAR($A16),MONTH($A16)+3*CEILING((DATEDIF($A16,'13-week CF Forecast'!$B$1,"m")+1)/3,1)+(COLUMN()-7)*3,DAY($A16)),$F16="yearly",DATE(YEAR($A16)+CEILING((DATEDIF($A16,'13-week CF Forecast'!$B$1,"y")+1),1)+COLUMN()-7,MONTH($A16),DAY($A16)),TRUE,"") -> 46054 | ... S16: =IFS($F16="bi-weekly",$A16+CEILING(('13-week CF Forecast'!$B$1-$A16)/14,1)*14+14*(COLUMN()-7),$F16="weekly",$A16+CEILING(('13-week CF Forecast'!$B$1-$A16)/7,1)*7+7*(COLUMN()-7),$F16="monthly",DATE(YEAR($A16),MONTH($A16)+CEILING(DATEDIF($A16,'13-week CF Forecast'!$B$1,"m")+1,1)+COLUMN()-7,DAY($A16)),$F16="quarterly",DATE(YEAR($A16),MONTH($A16)+3*CEILING((DATEDIF($A16,'13-week CF Forecast'!$B$1,"m")+1)/3,1)+(COLUMN()-7)*3,DAY($A16)),$F16="yearly",DATE(YEAR($A16)+CEILING((DATEDIF($A16,'13-week CF Forecast'!$B$1,"y")+1),1)+COLUMN()-7,MONTH($A16),DAY($A16)),TRUE,"") -> 46204 | T16: =IFERROR(ROWSDUMMYFUNCTION(UNNEST(PAIR2JSON('Recurring Transactions'!$A$1,'Recurring Transactions'!A16,'Recurring Transactions'!$B$1,'Recurring Transactions'!B16,'Recurring Transactions'!$C$1,'Recurring Transactions'!C16,'Recurring Transactions'!$D$1,'Recurring Transactions'!D16,'Recurring Transactions'!$E$1,'Recurring Transactions'!E16,'Recurring Transactions'!$F$1,'Recurring Transactions'!F16,"Payment schedule",VALUE(RANGE2JSON('Recurring Transactions'!F16,'Recurring Transactions'!G16:S16))))),"[{""First payment date"":""2025-01-01"",""Counterparty"":""Easyship"",""Description"":""Easyship"",""Amount"":""$100"",""Category"":""Software"",""Frequency"":""monthly"",""Payment schedule_0"":""2025-07-01""},{""First payment date"":""2025-01-01"",""Counterparty"":""Easyship"",""Description"&""":""Easyship"",""Amount"":""$100"",""Category"":""Software"",""Frequency"":""monthly"",""Payment schedule_0"":""2025-08-01""},{""First payment date"":""2025-01-01"",""Counterparty"":""Easyship"",""Description"":""Easyship"",""Amount"":""$100"",""Category"":""Software"",""Frequency"":""monthly"","""&"Payment schedule_0"":""2025-09-01""},{""First payment date"":""2025-01-01"",""Counterparty"":""Easyship"",""Description"":""Easyship"",""Amount"":""$100"",""Category"":""Software"",""Frequency"":""monthly"",""Payment schedule_0"":""2025-10-01""},{""First payment date"":""2025-01-01"",""Coun"&"terparty"":""Easyship"",""Description"":""Easyship"",""Amount"":""$100"",""Category"":""Software"",""Frequency"":""monthly"",""Payment schedule_0"":""2025-11-01""},{""First payment date"":""2025-01-01"",""Counterparty"":""Easyship"",""Description"":""Easyship"",""Amount"":""$100"",""Category"":"""&"Software"",""Frequency"":""monthly"",""Payment schedule_0"":""2025-12-01""},{""First payment date"":""2025-01-01"",""Counterparty"":""Easyship"",""Description"":""Easyship"",""Amount"":""$100"",""Category"":""Software"",""Frequency"":""monthly"",""Payment schedule_0"":""2026-01-01""},{""First"&" payment date"":""2025-01-01"",""Counterparty"":""Easyship"",""Description"":""Easyship"",""Amount"":""$100"",""Category"":""Software"",""Frequency"":""monthly"",""Payment schedule_0"":""2026-02-01""},{""First payment date"":""2025-01-01"",""Counterparty"":""Easyship"",""Description"":""Easys"&"hip"",""Amount"":""$100"",""Category"":""Software"",""Frequency"":""monthly"",""Payment schedule_0"":""2026-03-01""},{""First payment date"":""2025-01-01"",""Counterparty"":""Easyship"",""Description"":""Easyship"",""Amount"":""$100"",""Category"":""Software"",""Frequency"":""monthly"",""Payment "&"schedule_0"":""2026-04-01""},{""First payment date"":""2025-01-01"",""Counterparty"":""Easyship"",""Description"":""Easyship"",""Amount"":""$100"",""Category"":""Software"",""Frequency"":""monthly"",""Payment schedule_0"":""2026-05-01""},{""First payment date"":""2025-01-01"",""Counterparty"&""":""Easyship"",""Description"":""Easyship"",""Amount"":""$100"",""Category"":""Software"",""Frequency"":""monthly"",""Payment schedule_0"":""2026-06-01""},{""First payment date"":""2025-01-01"",""Counterparty"":""Easyship"",""Description"":""Easyship"",""Amount"":""$100"",""Category"":""Software"&""",""Frequency"":""monthly"",""Payment schedule_0"":""2026-07-01""}]") -> [{"First payment date":"2025-01-01","Counterparty":"Easyship","Description":"Easyship","Amount":"$100","Category":"Software","Frequency":"monthly","Payment schedule_0":"2025-07-01"},{"First payment date":"2025-01-01","Counterparty":"Easyship","Description":"Easyship","Amount":"$100","Category":"Software","Frequency":"monthly","Payment schedule_0":"2025-08-01"},{"First payment date":"2025-01-01","Counterparty":"Easyship","Description":"Easyship","Amount":"$100","Category":"Software","Frequency":"monthly","Payment schedule_0":"2025-09-01"},{"First payment date":"2025-01-01","Counterparty":"Easyship","Description":"Easyship","Amount":"$100","Category":"Software","Frequency":"monthly","Payment schedule_0":"2025-10-01"},{"First payment date":"2025-01-01","Counterparty":"Easyship","Description":"Easyship","Amount":"$100","Category":"Software","Frequency":"monthly","Payment schedule_0":"2025-11-01"},{"First payment date":"2025-01-01","Counterparty":"Easyship","Description":"Easyship","Amount":"$100","Category":"Software","Frequency":"monthly","Payment schedule_0":"2025-12-01"},{"First payment date":"2025-01-01","Counterparty":"Easyship","Description":"Easyship","Amount":"$100","Category":"Software","Frequency":"monthly","Payment schedule_0":"2026-01-01"},{"First payment date":"2025-01-01","Counterparty":"Easyship","Description":"Easyship","Amount":"$100","Category":"Software","Frequency":"monthly","Payment schedule_0":"2026-02-01"},{"First payment date":"2025-01-01","Counterparty":"Easyship","Description":"Easyship","Amount":"$100","Category":"Software","Frequency":"monthly","Payment schedule_0":"2026-03-01"},{"First payment date":"2025-01-01","Counterparty":"Easyship","Description":"Easyship","Amount":"$100","Category":"Software","Frequency":"monthly","Payment schedule_0":"2026-04-01"},{"First payment date":"2025-01-01","Counterparty":"Easyship","Description":"Easyship","Amount":"$100","Category":"Software","Frequency":"monthly","Payment schedule_0":"2026-05-01"},{"First payment date":"2025-01-01","Counterparty":"Easyship","Description":"Easyship","Amount":"$100","Category":"Software","Frequency":"monthly","Payment schedule_0":"2026-06-01"},{"First payment date":"2025-01-01","Counterparty":"Easyship","Description":"Easyship","Amount":"$100","Category":"Software","Frequency":"monthly","Payment schedule_0":"2026-07-01"}] | U16: Chase Inc
